[
  {
    "title": "从一座纪念馆看克敌制胜法宝",
    "description": "8月16日，习近平总书记来到辽沈战役纪念馆，回顾东北解放战争历史和辽沈战役胜利进程。让我们跟随总书记的脚步，探寻克敌制胜...   8月16日，习近平总书记来到辽沈战役纪念馆，回顾东北解放战争历史和辽沈战役胜利进程。让我们跟随总书记的脚步，探寻克敌制胜的法宝。",
    "url": "https://www.baidu.com/s?wd=%E4%BB%8E%E4%B8%80%E5%BA%A7%E7%BA%AA%E5%BF%B5%E9%A6%86%E7%9C%8B%E5%85%8B%E6%95%8C%E5%88%B6%E8%83%9C%E6%B3%95%E5%AE%9D&sa=fyb_news&rsv_dl=fyb_news"
  },
  {
    "title": "现场：重庆涪陵突发山火",
    "description": "8月17日晚，涪陵北山坪突发山火，现场火光冲天，消防紧急赶赴灭火。重庆消防回应：目前山火仍在扑救过程中，暂无人员伤亡。   8月17日晚，涪陵北山坪突发山火，现场火光冲天，消防紧急赶赴灭火。重庆消防回应：目前山火仍在扑救过程中，暂无人员伤亡。",
    "url": "https://www.baidu.com/s?wd=%E7%8E%B0%E5%9C%BA%EF%BC%9A%E9%87%8D%E5%BA%86%E6%B6%AA%E9%99%B5%E7%AA%81%E5%8F%91%E5%B1%B1%E7%81%AB&sa=fyb_news&rsv_dl=fyb_news"
  },
  {
    "title": "国防部：中国军队赴俄参加演习",
    "description": "",
    "url": "https://www.baidu.com/s?wd=%E5%9B%BD%E9%98%B2%E9%83%A8%EF%BC%9A%E4%B8%AD%E5%9B%BD%E5%86%9B%E9%98%9F%E8%B5%B4%E4%BF%84%E5%8F%82%E5%8A%A0%E6%BC%94%E4%B9%A0&sa=fyb_news&rsv_dl=fyb_news"
  },
  {
    "title": "犯我中华者必将受到惩处",
    "description": "8月17日，针对美方称中方反制是反应过度一事，外交部发言人汪文斌回应，我们严正警告美方，玩火者绝对没有好下场，犯我中华者...   8月17日，针对美方称中方反制是反应过度一事，外交部发言人汪文斌回应，我们严正警告美方，玩火者绝对没有好下场，犯我中华者必将受到惩处。",
    "url": "https://www.baidu.com/s?wd=%E7%8A%AF%E6%88%91%E4%B8%AD%E5%8D%8E%E8%80%85%E5%BF%85%E5%B0%86%E5%8F%97%E5%88%B0%E6%83%A9%E5%A4%84&sa=fyb_news&rsv_dl=fyb_news"
  },
  {
    "title": "劳荣枝家属将赶赴庭审：望发回重审",
    "description": "劳荣枝案8月18日二审开庭，劳荣枝二哥希望能进入庭审现场旁听，他还认为，一审中劳荣枝法子英供述多处不一致，辩护人或提“证...   劳荣枝案8月18日二审开庭，劳荣枝二哥希望能进入庭审现场旁听，他还认为，一审中劳荣枝法子英供述多处不一致，辩护人或提“证据不足，望发回重审”。",
    "url": "https://www.baidu.com/s?wd=%E5%8A%B3%E8%8D%A3%E6%9E%9D%E5%AE%B6%E5%B1%9E%E5%B0%86%E8%B5%B6%E8%B5%B4%E5%BA%AD%E5%AE%A1%EF%BC%9A%E6%9C%9B%E5%8F%91%E5%9B%9E%E9%87%8D%E5%AE%A1&sa=fyb_news&rsv_dl=fyb_news"
  },
  {
    "title": "青海西宁辟谣今晚封城",
    "description": "",
    "url": "https://www.baidu.com/s?wd=%E9%9D%92%E6%B5%B7%E8%A5%BF%E5%AE%81%E8%BE%9F%E8%B0%A3%E4%BB%8A%E6%99%9A%E5%B0%81%E5%9F%8E&sa=fyb_news&rsv_dl=fyb_news"
  },
  {
    "title": "75岁嫌犯在逃 村民:十几岁女孩被害",
    "description": "8月6日，广西岑溪木榔村发生一起重大刑事案件，75岁的男子高某有重大作案嫌疑，目前在逃。岑溪木榔村的村民称，遇害的是一名...   8月6日，广西岑溪木榔村发生一起重大刑事案件，75岁的男子高某有重大作案嫌疑，目前在逃。岑溪木榔村的村民称，遇害的是一名十四五岁的女孩。",
    "url": "https://www.baidu.com/s?wd=75%E5%B2%81%E5%AB%8C%E7%8A%AF%E5%9C%A8%E9%80%83+%E6%9D%91%E6%B0%91%3A%E5%8D%81%E5%87%A0%E5%B2%81%E5%A5%B3%E5%AD%A9%E8%A2%AB%E5%AE%B3&sa=fyb_news&rsv_dl=fyb_news"
  },
  {
    "title": "钱泳辰方发声明否认骗学费被包养",
    "description": "",
    "url": "https://www.baidu.com/s?wd=%E9%92%B1%E6%B3%B3%E8%BE%B0%E6%96%B9%E5%8F%91%E5%A3%B0%E6%98%8E%E5%90%A6%E8%AE%A4%E9%AA%97%E5%AD%A6%E8%B4%B9%E8%A2%AB%E5%8C%85%E5%85%BB&sa=fyb_news&rsv_dl=fyb_news"
  },
  {
    "title": "实习生因拒吃生鸡蛋被辞退",
    "description": "",
    "url": "https://www.baidu.com/s?wd=%E5%AE%9E%E4%B9%A0%E7%94%9F%E5%9B%A0%E6%8B%92%E5%90%83%E7%94%9F%E9%B8%A1%E8%9B%8B%E8%A2%AB%E8%BE%9E%E9%80%80&sa=fyb_news&rsv_dl=fyb_news"
  },
  {
    "title": "国务院：严格禁止以罚款进行创收",
    "description": "",
    "url": "https://www.baidu.com/s?wd=%E5%9B%BD%E5%8A%A1%E9%99%A2%EF%BC%9A%E4%B8%A5%E6%A0%BC%E7%A6%81%E6%AD%A2%E4%BB%A5%E7%BD%9A%E6%AC%BE%E8%BF%9B%E8%A1%8C%E5%88%9B%E6%94%B6&sa=fyb_news&rsv_dl=fyb_news"
  },
  {
    "title": "多人洞穴探险后肺部感染险丧命",
    "description": "近日，云南一网友分享自己一段野外洞穴探险劫后余生的经历。2018年该名网友与驴友组队前往山洞探险后肺部感染险丧命，两年之...   近日，云南一网友分享自己一段野外洞穴探险劫后余生的经历。2018年该名网友与驴友组队前往山洞探险后肺部感染险丧命，两年之后，才逐渐恢复体力。",
    "url": "https://www.baidu.com/s?wd=%E5%A4%9A%E4%BA%BA%E6%B4%9E%E7%A9%B4%E6%8E%A2%E9%99%A9%E5%90%8E%E8%82%BA%E9%83%A8%E6%84%9F%E6%9F%93%E9%99%A9%E4%B8%A7%E5%91%BD&sa=fyb_news&rsv_dl=fyb_news"
  },
  {
    "title": "肛肠科实习医生收到锦旗写肛好有你",
    "description": "8月17日，广西南宁一实习医学生收到“肛好有你”四字锦旗在社交平台晒出。该同学表示，自己是肛肠科实习生，收到锦旗也是大为...   8月17日，广西南宁一实习医学生收到“肛好有你”四字锦旗在社交平台晒出。该同学表示，自己是肛肠科实习生，收到锦旗也是大为震惊。",
    "url": "https://www.baidu.com/s?wd=%E8%82%9B%E8%82%A0%E7%A7%91%E5%AE%9E%E4%B9%A0%E5%8C%BB%E7%94%9F%E6%94%B6%E5%88%B0%E9%94%A6%E6%97%97%E5%86%99%E8%82%9B%E5%A5%BD%E6%9C%89%E4%BD%A0&sa=fyb_news&rsv_dl=fyb_news"
  },
  {
    "title": "男子厨房里炒菜患热射病住进ICU",
    "description": "",
    "url": "https://www.baidu.com/s?wd=%E7%94%B7%E5%AD%90%E5%8E%A8%E6%88%BF%E9%87%8C%E7%82%92%E8%8F%9C%E6%82%A3%E7%83%AD%E5%B0%84%E7%97%85%E4%BD%8F%E8%BF%9BICU&sa=fyb_news&rsv_dl=fyb_news"
  },
  {
    "title": "劳荣枝案小木匠妻子希望维持原判",
    "description": "18日9时30分，劳荣枝案将在江西省高级人民法院开庭审理。被害人妻子表示，自此次开庭她不会前往现场，希望维持原判。   18日9时30分，劳荣枝案将在江西省高级人民法院开庭审理。被害人妻子表示，自此次开庭她不会前往现场，希望维持原判。",
    "url": "https://www.baidu.com/s?wd=%E5%8A%B3%E8%8D%A3%E6%9E%9D%E6%A1%88%E5%B0%8F%E6%9C%A8%E5%8C%A0%E5%A6%BB%E5%AD%90%E5%B8%8C%E6%9C%9B%E7%BB%B4%E6%8C%81%E5%8E%9F%E5%88%A4&sa=fyb_news&rsv_dl=fyb_news"
  },
  {
    "title": "男子被困海上用摩斯密码获救",
    "description": "",
    "url": "https://www.baidu.com/s?wd=%E7%94%B7%E5%AD%90%E8%A2%AB%E5%9B%B0%E6%B5%B7%E4%B8%8A%E7%94%A8%E6%91%A9%E6%96%AF%E5%AF%86%E7%A0%81%E8%8E%B7%E6%95%91&sa=fyb_news&rsv_dl=fyb_news"
  },
  {
    "title": "男孩故意按停扶梯致女孩摔倒",
    "description": "8月16日，广东深圳一商场内，一男孩走下扶梯后突然转身关停了扶梯，导致扶梯上的一名5岁女孩摔倒。目前警方已介入，还没找到...   8月16日，广东深圳一商场内，一男孩走下扶梯后突然转身关停了扶梯，导致扶梯上的一名5岁女孩摔倒。目前警方已介入，还没找到这名男孩。",
    "url": "https://www.baidu.com/s?wd=%E7%94%B7%E5%AD%A9%E6%95%85%E6%84%8F%E6%8C%89%E5%81%9C%E6%89%B6%E6%A2%AF%E8%87%B4%E5%A5%B3%E5%AD%A9%E6%91%94%E5%80%92&sa=fyb_news&rsv_dl=fyb_news"
  },
  {
    "title": "湘潭大学回应强制毕业生换10人寝",
    "description": "近日，网传湖南湘潭大学强制临近毕业的大四学生由原先的4人及6人寝换成10人寝。对此，湘潭大学官方回应：具体情况还在研究，...   近日，网传湖南湘潭大学强制临近毕业的大四学生由原先的4人及6人寝换成10人寝。对此，湘潭大学官方回应：具体情况还在研究，过多消息不方便透露。",
    "url": "https://www.baidu.com/s?wd=%E6%B9%98%E6%BD%AD%E5%A4%A7%E5%AD%A6%E5%9B%9E%E5%BA%94%E5%BC%BA%E5%88%B6%E6%AF%95%E4%B8%9A%E7%94%9F%E6%8D%A210%E4%BA%BA%E5%AF%9D&sa=fyb_news&rsv_dl=fyb_news"
  },
  {
    "title": "西南交大上百研究生新生需校外租房",
    "description": "近日，不少大学迎来了开学季。据悉，来自西南交通大学的研究生再过10天就要开学，但目前至少二百名全日制硕博新生在开学时面临...   近日，不少大学迎来了开学季。据悉，来自西南交通大学的研究生再过10天就要开学，但目前至少二百名全日制硕博新生在开学时面临着无宿舍可住的烦恼。",
    "url": "https://www.baidu.com/s?wd=%E8%A5%BF%E5%8D%97%E4%BA%A4%E5%A4%A7%E4%B8%8A%E7%99%BE%E7%A0%94%E7%A9%B6%E7%94%9F%E6%96%B0%E7%94%9F%E9%9C%80%E6%A0%A1%E5%A4%96%E7%A7%9F%E6%88%BF&sa=fyb_news&rsv_dl=fyb_news"
  },
  {
    "title": "三峡水库加大下泄向长江中下游补水",
    "description": "为了应对高温干旱影响，8月16日，水利部长江水利委员会发布调度令，调度三峡水库于16日12时起向长江中下游补水。   为了应对高温干旱影响，8月16日，水利部长江水利委员会发布调度令，调度三峡水库于16日12时起向长江中下游补水。",
    "url": "https://www.baidu.com/s?wd=%E4%B8%89%E5%B3%A1%E6%B0%B4%E5%BA%93%E5%8A%A0%E5%A4%A7%E4%B8%8B%E6%B3%84%E5%90%91%E9%95%BF%E6%B1%9F%E4%B8%AD%E4%B8%8B%E6%B8%B8%E8%A1%A5%E6%B0%B4&sa=fyb_news&rsv_dl=fyb_news"
  },
  {
    "title": "药企卖两套学区房换来2100万",
    "description": "",
    "url": "https://www.baidu.com/s?wd=%E8%8D%AF%E4%BC%81%E5%8D%96%E4%B8%A4%E5%A5%97%E5%AD%A6%E5%8C%BA%E6%88%BF%E6%8D%A2%E6%9D%A52100%E4%B8%87&sa=fyb_news&rsv_dl=fyb_news"
  },
  {
    "title": "土耳其2岁女童遭蛇咬后咬死蛇",
    "description": "据报道，当地时间8月10日，土耳其一名2岁女童被一条50厘米长的蛇袭击，随后这名女童反将蛇咬死。   据报道，当地时间8月10日，土耳其一名2岁女童被一条50厘米长的蛇袭击，随后这名女童反将蛇咬死。",
    "url": "https://www.baidu.com/s?wd=%E5%9C%9F%E8%80%B3%E5%85%B62%E5%B2%81%E5%A5%B3%E7%AB%A5%E9%81%AD%E8%9B%87%E5%92%AC%E5%90%8E%E5%92%AC%E6%AD%BB%E8%9B%87&sa=fyb_news&rsv_dl=fyb_news"
  },
  {
    "title": "公司称猫5次入镜影响上课开除老师",
    "description": "某教育公司因授课老师在线授课中猫咪5次蹿入镜头，判定教师违规，将其开除。近日，法院判决公司向该教师支付违法解除劳动关系赔...   某教育公司因授课老师在线授课中猫咪5次蹿入镜头，判定教师违规，将其开除。近日，法院判决公司向该教师支付违法解除劳动关系赔偿金41236.16元。",
    "url": "https://www.baidu.com/s?wd=%E5%85%AC%E5%8F%B8%E7%A7%B0%E7%8C%AB5%E6%AC%A1%E5%85%A5%E9%95%9C%E5%BD%B1%E5%93%8D%E4%B8%8A%E8%AF%BE%E5%BC%80%E9%99%A4%E8%80%81%E5%B8%88&sa=fyb_news&rsv_dl=fyb_news"
  },
  {
    "title": "高温下 近600年前摩崖造像露出江面",
    "description": "近期，重庆多地持续高温天气。由于长江水位回落，重庆一常年淹没在江水中的佛爷梁岛礁露出江面，岛礁最高处发现摩崖造像，距今有...   近期，重庆多地持续高温天气。由于长江水位回落，重庆一常年淹没在江水中的佛爷梁岛礁露出江面，岛礁最高处发现摩崖造像，距今有近六百年历史。",
    "url": "https://www.baidu.com/s?wd=%E9%AB%98%E6%B8%A9%E4%B8%8B+%E8%BF%91600%E5%B9%B4%E5%89%8D%E6%91%A9%E5%B4%96%E9%80%A0%E5%83%8F%E9%9C%B2%E5%87%BA%E6%B1%9F%E9%9D%A2&sa=fyb_news&rsv_dl=fyb_news"
  },
  {
    "title": "鼓励生三孩 17部门联合发文",
    "description": "16日，国家卫生健康委等17部门发布指导意见，进一步完善和落实积极生育支持措施。意见要求，深入实施一对夫妻可以生育三个子...   16日，国家卫生健康委等17部门发布指导意见，进一步完善和落实积极生育支持措施。意见要求，深入实施一对夫妻可以生育三个子女政策及配套支持措施。",
    "url": "https://www.baidu.com/s?wd=%E9%BC%93%E5%8A%B1%E7%94%9F%E4%B8%89%E5%AD%A9+17%E9%83%A8%E9%97%A8%E8%81%94%E5%90%88%E5%8F%91%E6%96%87&sa=fyb_news&rsv_dl=fyb_news"
  },
  {
    "title": "婴幼儿无人照料是阻碍生育首要因素",
    "description": "17日国家卫健委发布会上，发改委工作人员介绍：调查显示，婴幼儿无人照料是阻碍生育的首要因素，发展托育对减轻家庭负担、提高...   17日国家卫健委发布会上，发改委工作人员介绍：调查显示，婴幼儿无人照料是阻碍生育的首要因素，发展托育对减轻家庭负担、提高生育意愿有显著效果。",
    "url": "https://www.baidu.com/s?wd=%E5%A9%B4%E5%B9%BC%E5%84%BF%E6%97%A0%E4%BA%BA%E7%85%A7%E6%96%99%E6%98%AF%E9%98%BB%E7%A2%8D%E7%94%9F%E8%82%B2%E9%A6%96%E8%A6%81%E5%9B%A0%E7%B4%A0&sa=fyb_news&rsv_dl=fyb_news"
  },
  {
    "title": "四川乐山一公立医院倒闭",
    "description": "",
    "url": "https://www.baidu.com/s?wd=%E5%9B%9B%E5%B7%9D%E4%B9%90%E5%B1%B1%E4%B8%80%E5%85%AC%E7%AB%8B%E5%8C%BB%E9%99%A2%E5%80%92%E9%97%AD&sa=fyb_news&rsv_dl=fyb_news"
  },
  {
    "title": "比亚迪汉被曝上牌仅3天自燃",
    "description": "",
    "url": "https://www.baidu.com/s?wd=%E6%AF%94%E4%BA%9A%E8%BF%AA%E6%B1%89%E8%A2%AB%E6%9B%9D%E4%B8%8A%E7%89%8C%E4%BB%853%E5%A4%A9%E8%87%AA%E7%87%83&sa=fyb_news&rsv_dl=fyb_news"
  },
  {
    "title": "高温下居民到古墓纳凉？当地回应",
    "description": "近日，眉山青神县不少网友去国家文物重点保护单位瑞峰崖墓群避暑。对此，青神县文物保护中心工作人员称，乘凉基本上对崖墓群没有...   近日，眉山青神县不少网友去国家文物重点保护单位瑞峰崖墓群避暑。对此，青神县文物保护中心工作人员称，乘凉基本上对崖墓群没有损坏，会加强巡查。",
    "url": "https://www.baidu.com/s?wd=%E9%AB%98%E6%B8%A9%E4%B8%8B%E5%B1%85%E6%B0%91%E5%88%B0%E5%8F%A4%E5%A2%93%E7%BA%B3%E5%87%89%EF%BC%9F%E5%BD%93%E5%9C%B0%E5%9B%9E%E5%BA%94&sa=fyb_news&rsv_dl=fyb_news"
  },
  {
    "title": "京津冀等8省区市有大到暴雨",
    "description": "",
    "url": "https://www.baidu.com/s?wd=%E4%BA%AC%E6%B4%A5%E5%86%80%E7%AD%898%E7%9C%81%E5%8C%BA%E5%B8%82%E6%9C%89%E5%A4%A7%E5%88%B0%E6%9A%B4%E9%9B%A8&sa=fyb_news&rsv_dl=fyb_news"
  },
  {
    "title": "盲盒产品出现色情擦边球造型",
    "description": "近年来，盲盒潮玩类产品越发火热，但随之出现的盲盒产品夹杂色情题材、色情造型等问题也频频引发一些家长质疑和担心。   近年来，盲盒潮玩类产品越发火热，但随之出现的盲盒产品夹杂色情题材、色情造型等问题也频频引发一些家长质疑和担心。",
    "url": "https://www.baidu.com/s?wd=%E7%9B%B2%E7%9B%92%E4%BA%A7%E5%93%81%E5%87%BA%E7%8E%B0%E8%89%B2%E6%83%85%E6%93%A6%E8%BE%B9%E7%90%83%E9%80%A0%E5%9E%8B&sa=fyb_news&rsv_dl=fyb_news"
  },
  {
    "title": "大爷大妈进超市避暑脱鞋躺货架",
    "description": "近日，孝感天气炎热不少人选择在空调房纳凉。商场中，一位大叔直接脱鞋躺在货架上，上面还放着商场出售的商品。这样的行为被网友...   近日，孝感天气炎热不少人选择在空调房纳凉。商场中，一位大叔直接脱鞋躺在货架上，上面还放着商场出售的商品。这样的行为被网友吐槽：素质堪忧。",
    "url": "https://www.baidu.com/s?wd=%E5%A4%A7%E7%88%B7%E5%A4%A7%E5%A6%88%E8%BF%9B%E8%B6%85%E5%B8%82%E9%81%BF%E6%9A%91%E8%84%B1%E9%9E%8B%E8%BA%BA%E8%B4%A7%E6%9E%B6&sa=fyb_news&rsv_dl=fyb_news"
  },
  {
    "title": "四川简阳一天接诊13位热射病患者",
    "description": "8月16日，简阳一医院一天接诊了13位热射病患者，其中危重症有5人。据悉，这些患者有的曾步行下班回家，有的曾外出散步。   8月16日，简阳一医院一天接诊了13位热射病患者，其中危重症有5人。据悉，这些患者有的曾步行下班回家，有的曾外出散步。",
    "url": "https://www.baidu.com/s?wd=%E5%9B%9B%E5%B7%9D%E7%AE%80%E9%98%B3%E4%B8%80%E5%A4%A9%E6%8E%A5%E8%AF%8A13%E4%BD%8D%E7%83%AD%E5%B0%84%E7%97%85%E6%82%A3%E8%80%85&sa=fyb_news&rsv_dl=fyb_news"
  },
  {
    "title": "成都限电：太古里大屏关闭扶梯停运",
    "description": "8月17日，因持续高温，成都多个写字楼限电，空调停止制冷。有网友发现，太古里裸眼3D大屏熄灭，IFS商场下行扶梯也已停运...   8月17日，因持续高温，成都多个写字楼限电，空调停止制冷。有网友发现，太古里裸眼3D大屏熄灭，IFS商场下行扶梯也已停运。",
    "url": "https://www.baidu.com/s?wd=%E6%88%90%E9%83%BD%E9%99%90%E7%94%B5%EF%BC%9A%E5%A4%AA%E5%8F%A4%E9%87%8C%E5%A4%A7%E5%B1%8F%E5%85%B3%E9%97%AD%E6%89%B6%E6%A2%AF%E5%81%9C%E8%BF%90&sa=fyb_news&rsv_dl=fyb_news"
  },
  {
    "title": "川渝包揽最热前十",
    "description": "据中央气象台消息 ，17日气温实况排行榜，重庆、四川包揽最热前10排行榜。其中重庆北碚温度最高，为44.6℃。重庆潼南、...   据中央气象台消息 ，17日气温实况排行榜，重庆、四川包揽最热前10排行榜。其中重庆北碚温度最高，为44.6℃。重庆潼南、四川简阳等地气温均超过43℃...",
    "url": "https://www.baidu.com/s?wd=%E5%B7%9D%E6%B8%9D%E5%8C%85%E6%8F%BD%E6%9C%80%E7%83%AD%E5%89%8D%E5%8D%81&sa=fyb_news&rsv_dl=fyb_news"
  },
  {
    "title": "腾讯二季度净利润下滑56%",
    "description": "8月17日，腾讯控股发布2022年度第二季度财报。财报显示，腾讯控股二季度净利润186.19亿元，同比下降56%。   8月17日，腾讯控股发布2022年度第二季度财报。财报显示，腾讯控股二季度净利润186.19亿元，同比下降56%。",
    "url": "https://www.baidu.com/s?wd=%E8%85%BE%E8%AE%AF%E4%BA%8C%E5%AD%A3%E5%BA%A6%E5%87%80%E5%88%A9%E6%B6%A6%E4%B8%8B%E6%BB%9156%25&sa=fyb_news&rsv_dl=fyb_news"
  },
  {
    "title": "济南首推二手房“带押过户”",
    "description": "8月17日，济南市委、市政府召开新闻发布会，围绕济南在全国首次创新推出二手房“带押过户”登记新模式展开介绍。   8月17日，济南市委、市政府召开新闻发布会，围绕济南在全国首次创新推出二手房“带押过户”登记新模式展开介绍。",
    "url": "https://www.baidu.com/s?wd=%E6%B5%8E%E5%8D%97%E9%A6%96%E6%8E%A8%E4%BA%8C%E6%89%8B%E6%88%BF%E2%80%9C%E5%B8%A6%E6%8A%BC%E8%BF%87%E6%88%B7%E2%80%9D&sa=fyb_news&rsv_dl=fyb_news"
  },
  {
    "title": "奢侈品电商寺库疑似跑路",
    "description": "近日，有媒体报道称寺库北京总部疑似跑路，整座大厦几近人去楼空的消息引发热议。对此寺库方面回应称，此报道不实，目前在岗员工...   近日，有媒体报道称寺库北京总部疑似跑路，整座大厦几近人去楼空的消息引发热议。对此寺库方面回应称，此报道不实，目前在岗员工有几百人。",
    "url": "https://www.baidu.com/s?wd=%E5%A5%A2%E4%BE%88%E5%93%81%E7%94%B5%E5%95%86%E5%AF%BA%E5%BA%93%E7%96%91%E4%BC%BC%E8%B7%91%E8%B7%AF&sa=fyb_news&rsv_dl=fyb_news"
  },
  {
    "title": "iPhone14将与华为Mate50同期发布",
    "description": "苹果内部文件显示， iPhone 14系列将提前至9月6日发布。同时有消息称，华为Mate 50系列将在9月7日发布。这...   苹果内部文件显示， iPhone 14系列将提前至9月6日发布。同时有消息称，华为Mate 50系列将在9月7日发布。这意味着手机届两巨头将同期发布...",
    "url": "https://www.baidu.com/s?wd=iPhone14%E5%B0%86%E4%B8%8E%E5%8D%8E%E4%B8%BAMate50%E5%90%8C%E6%9C%9F%E5%8F%91%E5%B8%83&sa=fyb_news&rsv_dl=fyb_news"
  },
  {
    "title": "1岁男童钥匙插充电桩脸被电黑",
    "description": "近日，河北廊坊一名1岁多的男童在小区玩耍时，把钥匙插进了电动车充电桩的充电孔里，导致手被电伤，脸也被电黑。经紧急就医后，...   近日，河北廊坊一名1岁多的男童在小区玩耍时，把钥匙插进了电动车充电桩的充电孔里，导致手被电伤，脸也被电黑。经紧急就医后，目前伤情已稳定。",
    "url": "https://www.baidu.com/s?wd=1%E5%B2%81%E7%94%B7%E7%AB%A5%E9%92%A5%E5%8C%99%E6%8F%92%E5%85%85%E7%94%B5%E6%A1%A9%E8%84%B8%E8%A2%AB%E7%94%B5%E9%BB%91&sa=fyb_news&rsv_dl=fyb_news"
  },
  {
    "title": "韩军方称朝鲜发射两枚巡航导弹",
    "description": "",
    "url": "https://www.baidu.com/s?wd=%E9%9F%A9%E5%86%9B%E6%96%B9%E7%A7%B0%E6%9C%9D%E9%B2%9C%E5%8F%91%E5%B0%84%E4%B8%A4%E6%9E%9A%E5%B7%A1%E8%88%AA%E5%AF%BC%E5%BC%B9&sa=fyb_news&rsv_dl=fyb_news"
  },
  {
    "title": "要求4省完成财政上缴任务有何深意?",
    "description": "8月16日，中共中央政治局常委、国务院总理李克强在深圳主持召开经济大省政府主要负责人座谈会。总理要求东部4省完成中央财政...   8月16日，中共中央政治局常委、国务院总理李克强在深圳主持召开经济大省政府主要负责人座谈会。总理要求东部4省完成中央财政上缴任务，有何深意？",
    "url": "https://www.baidu.com/s?wd=%E8%A6%81%E6%B1%824%E7%9C%81%E5%AE%8C%E6%88%90%E8%B4%A2%E6%94%BF%E4%B8%8A%E7%BC%B4%E4%BB%BB%E5%8A%A1%E6%9C%89%E4%BD%95%E6%B7%B1%E6%84%8F%3F&sa=fyb_news&rsv_dl=fyb_news"
  },
  {
    "title": "女子生产后两块纱布被遗留体内",
    "description": "",
    "url": "https://www.baidu.com/s?wd=%E5%A5%B3%E5%AD%90%E7%94%9F%E4%BA%A7%E5%90%8E%E4%B8%A4%E5%9D%97%E7%BA%B1%E5%B8%83%E8%A2%AB%E9%81%97%E7%95%99%E4%BD%93%E5%86%85&sa=fyb_news&rsv_dl=fyb_news"
  },
  {
    "title": "湖北超过100万人参与抗旱",
    "description": "",
    "url": "https://www.baidu.com/s?wd=%E6%B9%96%E5%8C%97%E8%B6%85%E8%BF%87100%E4%B8%87%E4%BA%BA%E5%8F%82%E4%B8%8E%E6%8A%97%E6%97%B1&sa=fyb_news&rsv_dl=fyb_news"
  },
  {
    "title": "四川2小孩夏令营溜号被教官打伤",
    "description": "",
    "url": "https://www.baidu.com/s?wd=%E5%9B%9B%E5%B7%9D2%E5%B0%8F%E5%AD%A9%E5%A4%8F%E4%BB%A4%E8%90%A5%E6%BA%9C%E5%8F%B7%E8%A2%AB%E6%95%99%E5%AE%98%E6%89%93%E4%BC%A4&sa=fyb_news&rsv_dl=fyb_news"
  },
  {
    "title": "房屋公摊达46％ 违背基本常识",
    "description": "",
    "url": "https://www.baidu.com/s?wd=%E6%88%BF%E5%B1%8B%E5%85%AC%E6%91%8A%E8%BE%BE46%EF%BC%85+%E8%BF%9D%E8%83%8C%E5%9F%BA%E6%9C%AC%E5%B8%B8%E8%AF%86&sa=fyb_news&rsv_dl=fyb_news"
  },
  {
    "title": "戚薇工作室回应卖假货质疑",
    "description": "",
    "url": "https://www.baidu.com/s?wd=%E6%88%9A%E8%96%87%E5%B7%A5%E4%BD%9C%E5%AE%A4%E5%9B%9E%E5%BA%94%E5%8D%96%E5%81%87%E8%B4%A7%E8%B4%A8%E7%96%91&sa=fyb_news&rsv_dl=fyb_news"
  },
  {
    "title": "玲娜贝儿卖42元主播直播被抓",
    "description": "玲娜贝儿、星黛露等迪士尼网红玩偶，在直播间内“秒杀价”只卖40余元？大V直播带货时被民警上门抓获，捣毁售假窝点3处、制假...   玲娜贝儿、星黛露等迪士尼网红玩偶，在直播间内“秒杀价”只卖40余元？大V直播带货时被民警上门抓获，捣毁售假窝点3处、制假窝点1处，涉案2500万。",
    "url": "https://www.baidu.com/s?wd=%E7%8E%B2%E5%A8%9C%E8%B4%9D%E5%84%BF%E5%8D%9642%E5%85%83%E4%B8%BB%E6%92%AD%E7%9B%B4%E6%92%AD%E8%A2%AB%E6%8A%93&sa=fyb_news&rsv_dl=fyb_news"
  },
  {
    "title": "《明日战记》回应被偷票房传言",
    "description": "",
    "url": "https://www.baidu.com/s?wd=%E3%80%8A%E6%98%8E%E6%97%A5%E6%88%98%E8%AE%B0%E3%80%8B%E5%9B%9E%E5%BA%94%E8%A2%AB%E5%81%B7%E7%A5%A8%E6%88%BF%E4%BC%A0%E8%A8%80&sa=fyb_news&rsv_dl=fyb_news"
  },
  {
    "title": "成都高温限电 地铁关闭部分照明",
    "description": "近期，四川各地持续高温，有网友晒出成都的地铁站已关闭部分广告灯箱和部分照明。   近期，四川各地持续高温，有网友晒出成都的地铁站已关闭部分广告灯箱和部分照明。",
    "url": "https://www.baidu.com/s?wd=%E6%88%90%E9%83%BD%E9%AB%98%E6%B8%A9%E9%99%90%E7%94%B5+%E5%9C%B0%E9%93%81%E5%85%B3%E9%97%AD%E9%83%A8%E5%88%86%E7%85%A7%E6%98%8E&sa=fyb_news&rsv_dl=fyb_news"
  },
  {
    "title": "老年健走队无视红绿灯逼停众车",
    "description": "8月16日，河南周口郸城一段老人健走队在机动车道行走视频引发热议。视频中，统一着红衣白裤的老年队伍穿过斑马线，数辆汽车被...   8月16日，河南周口郸城一段老人健走队在机动车道行走视频引发热议。视频中，统一着红衣白裤的老年队伍穿过斑马线，数辆汽车被逼停。",
    "url": "https://www.baidu.com/s?wd=%E8%80%81%E5%B9%B4%E5%81%A5%E8%B5%B0%E9%98%9F%E6%97%A0%E8%A7%86%E7%BA%A2%E7%BB%BF%E7%81%AF%E9%80%BC%E5%81%9C%E4%BC%97%E8%BD%A6&sa=fyb_news&rsv_dl=fyb_news"
  },
  {
    "title": "女子商场内试戴戒指戴上就跑",
    "description": "近日，广东佛山某商场内，一女子试戴戒指，趁店员不备戴着戒指扭头就跑，半小时后被警方人赃并获。据嫌疑人卢某交代，戒指很漂亮...   近日，广东佛山某商场内，一女子试戴戒指，趁店员不备戴着戒指扭头就跑，半小时后被警方人赃并获。据嫌疑人卢某交代，戒指很漂亮，但身上钱不够。",
    "url": "https://www.baidu.com/s?wd=%E5%A5%B3%E5%AD%90%E5%95%86%E5%9C%BA%E5%86%85%E8%AF%95%E6%88%B4%E6%88%92%E6%8C%87%E6%88%B4%E4%B8%8A%E5%B0%B1%E8%B7%91&sa=fyb_news&rsv_dl=fyb_news"
  },
  {
    "title": "文在寅散步被男子威胁辱骂",
    "description": "据韩媒报道，15日韩国前总统文在寅夫妇与保镖在庆尚南道梁山市平山村出门散步时，一男子上前对其威胁辱骂。这是文在寅卸任返乡...   据韩媒报道，15日韩国前总统文在寅夫妇与保镖在庆尚南道梁山市平山村出门散步时，一男子上前对其威胁辱骂。这是文在寅卸任返乡后，首次在村里散步。",
    "url": "https://www.baidu.com/s?wd=%E6%96%87%E5%9C%A8%E5%AF%85%E6%95%A3%E6%AD%A5%E8%A2%AB%E7%94%B7%E5%AD%90%E5%A8%81%E8%83%81%E8%BE%B1%E9%AA%82&sa=fyb_news&rsv_dl=fyb_news"
  },
  {
    "title": "乌克兰粮食现身断交国港口",
    "description": "",
    "url": "https://www.baidu.com/s?wd=%E4%B9%8C%E5%85%8B%E5%85%B0%E7%B2%AE%E9%A3%9F%E7%8E%B0%E8%BA%AB%E6%96%AD%E4%BA%A4%E5%9B%BD%E6%B8%AF%E5%8F%A3&sa=fyb_news&rsv_dl=fyb_news"
  },
  {
    "title": "多地办公楼限电 开启花式降暑",
    "description": "近日，随着各地持续高温，当前电力供需紧张形势进一步加剧。重庆、成都、武汉等多地办公楼被要求限电，办公现场开启花式降暑模式...   近日，随着各地持续高温，当前电力供需紧张形势进一步加剧。重庆、成都、武汉等多地办公楼被要求限电，办公现场开启花式降暑模式。",
    "url": "https://www.baidu.com/s?wd=%E5%A4%9A%E5%9C%B0%E5%8A%9E%E5%85%AC%E6%A5%BC%E9%99%90%E7%94%B5+%E5%BC%80%E5%90%AF%E8%8A%B1%E5%BC%8F%E9%99%8D%E6%9A%91&sa=fyb_news&rsv_dl=fyb_news"
  },
  {
    "title": "尹锡悦:朝鲜若弃核 韩国将考虑裁军",
    "description": "韩国总统尹锡悦8月17日在就职百日记者会上表示，若朝鲜停止开发核武器，韩国将提供包括推动朝美关系正常化在内的外交支持，并...   韩国总统尹锡悦8月17日在就职百日记者会上表示，若朝鲜停止开发核武器，韩国将提供包括推动朝美关系正常化在内的外交支持，并考虑裁减常规武器。",
    "url": "https://www.baidu.com/s?wd=%E5%B0%B9%E9%94%A1%E6%82%A6%3A%E6%9C%9D%E9%B2%9C%E8%8B%A5%E5%BC%83%E6%A0%B8+%E9%9F%A9%E5%9B%BD%E5%B0%86%E8%80%83%E8%99%91%E8%A3%81%E5%86%9B&sa=fyb_news&rsv_dl=fyb_news"
  },
  {
    "title": "德国否认战机要“穿越台湾海峡”",
    "description": "近日，有德媒报道称，德空军战机将穿越台湾海峡。而德空军总监格哈茨否认了该计划，并表示飞行高度会超过10公里，会将触及南海...   近日，有德媒报道称，德空军战机将穿越台湾海峡。而德空军总监格哈茨否认了该计划，并表示飞行高度会超过10公里，会将触及南海，会用国际航线。",
    "url": "https://www.baidu.com/s?wd=%E5%BE%B7%E5%9B%BD%E5%90%A6%E8%AE%A4%E6%88%98%E6%9C%BA%E8%A6%81%E2%80%9C%E7%A9%BF%E8%B6%8A%E5%8F%B0%E6%B9%BE%E6%B5%B7%E5%B3%A1%E2%80%9D&sa=fyb_news&rsv_dl=fyb_news"
  },
  {
    "title": "普京批佩洛西 中方高度评价相关表态",
    "description": "普京批佩洛西窜台是精心策划的挑衅。8月17日，中方对普京总统的表态给予高度评价，并透露，佩洛西窜台以来，已有170多个国...   普京批佩洛西窜台是精心策划的挑衅。8月17日，中方对普京总统的表态给予高度评价，并透露，佩洛西窜台以来，已有170多个国家发出正义的声音。",
    "url": "https://www.baidu.com/s?wd=%E6%99%AE%E4%BA%AC%E6%89%B9%E4%BD%A9%E6%B4%9B%E8%A5%BF+%E4%B8%AD%E6%96%B9%E9%AB%98%E5%BA%A6%E8%AF%84%E4%BB%B7%E7%9B%B8%E5%85%B3%E8%A1%A8%E6%80%81&sa=fyb_news&rsv_dl=fyb_news"
  },
  {
    "title": "王思聪林更新合伙公司申请注销",
    "description": "",
    "url": "https://www.baidu.com/s?wd=%E7%8E%8B%E6%80%9D%E8%81%AA%E6%9E%97%E6%9B%B4%E6%96%B0%E5%90%88%E4%BC%99%E5%85%AC%E5%8F%B8%E7%94%B3%E8%AF%B7%E6%B3%A8%E9%94%80&sa=fyb_news&rsv_dl=fyb_news"
  },
  {
    "title": "大旱会引发粮价、菜价上涨吗？",
    "description": "近期，持续的高温干旱天气成为多地农作物的最大威胁，农作物受灾面积1764万亩，部分地区蔬菜生产受影响。那么，旱情会引发粮...   近期，持续的高温干旱天气成为多地农作物的最大威胁，农作物受灾面积1764万亩，部分地区蔬菜生产受影响。那么，旱情会引发粮价、菜价波动吗？",
    "url": "https://www.baidu.com/s?wd=%E5%A4%A7%E6%97%B1%E4%BC%9A%E5%BC%95%E5%8F%91%E7%B2%AE%E4%BB%B7%E3%80%81%E8%8F%9C%E4%BB%B7%E4%B8%8A%E6%B6%A8%E5%90%97%EF%BC%9F&sa=fyb_news&rsv_dl=fyb_news"
  },
  {
    "title": "劳荣枝二哥：她在里面精神有些崩溃",
    "description": "",
    "url": "https://www.baidu.com/s?wd=%E5%8A%B3%E8%8D%A3%E6%9E%9D%E4%BA%8C%E5%93%A5%EF%BC%9A%E5%A5%B9%E5%9C%A8%E9%87%8C%E9%9D%A2%E7%B2%BE%E7%A5%9E%E6%9C%89%E4%BA%9B%E5%B4%A9%E6%BA%83&sa=fyb_news&rsv_dl=fyb_news"
  },
  {
    "title": "杭州气温跌破26℃",
    "description": "",
    "url": "https://www.baidu.com/s?wd=%E6%9D%AD%E5%B7%9E%E6%B0%94%E6%B8%A9%E8%B7%8C%E7%A0%B426%E2%84%83&sa=fyb_news&rsv_dl=fyb_news"
  },
  {
    "title": "拉萨抵京列车在河北检出多例阳性",
    "description": "据河北石家庄市疫情防控总指挥部发布，8月17日，在由拉萨至北京西的Z22次列车上发现多例阳性感染者，有多名乘客在石家庄站...   据河北石家庄市疫情防控总指挥部发布，8月17日，在由拉萨至北京西的Z22次列车上发现多例阳性感染者，有多名乘客在石家庄站下车。",
    "url": "https://www.baidu.com/s?wd=%E6%8B%89%E8%90%A8%E6%8A%B5%E4%BA%AC%E5%88%97%E8%BD%A6%E5%9C%A8%E6%B2%B3%E5%8C%97%E6%A3%80%E5%87%BA%E5%A4%9A%E4%BE%8B%E9%98%B3%E6%80%A7&sa=fyb_news&rsv_dl=fyb_news"
  },
  {
    "title": "未婚已育女性办生育津贴不需结婚证",
    "description": "国家医保局待遇保障司副司长刘娟表示，关于领取生育津贴的门槛，只要履行了生育保险的缴费责任，国家层面在待遇享受方面是没有门...   国家医保局待遇保障司副司长刘娟表示，关于领取生育津贴的门槛，只要履行了生育保险的缴费责任，国家层面在待遇享受方面是没有门槛的。",
    "url": "https://www.baidu.com/s?wd=%E6%9C%AA%E5%A9%9A%E5%B7%B2%E8%82%B2%E5%A5%B3%E6%80%A7%E5%8A%9E%E7%94%9F%E8%82%B2%E6%B4%A5%E8%B4%B4%E4%B8%8D%E9%9C%80%E7%BB%93%E5%A9%9A%E8%AF%81&sa=fyb_news&rsv_dl=fyb_news"
  },
  {
    "title": "广州一门店禁止员工上班讲粤语",
    "description": "",
    "url": "https://www.baidu.com/s?wd=%E5%B9%BF%E5%B7%9E%E4%B8%80%E9%97%A8%E5%BA%97%E7%A6%81%E6%AD%A2%E5%91%98%E5%B7%A5%E4%B8%8A%E7%8F%AD%E8%AE%B2%E7%B2%A4%E8%AF%AD&sa=fyb_news&rsv_dl=fyb_news"
  },
  {
    "title": "三亚昨日新增本土“417+814”",
    "description": "8月17日0时至24时，三亚市新增417例确诊病例（其中2例为无症状感染者转归）、814例无症状感染者。   8月17日0时至24时，三亚市新增417例确诊病例（其中2例为无症状感染者转归）、814例无症状感染者。",
    "url": "https://www.baidu.com/s?wd=%E4%B8%89%E4%BA%9A%E6%98%A8%E6%97%A5%E6%96%B0%E5%A2%9E%E6%9C%AC%E5%9C%9F%E2%80%9C417%2B814%E2%80%9D&sa=fyb_news&rsv_dl=fyb_news"
  },
  {
    "title": "农民日报评多地鼓励农民进城买房",
    "description": "这两天，某县县委书记号召领导干部买房的视频刷了屏，而近期“多地鼓励农民进城买房”的话题也备受关注。农民日报评鼓励农民进城...   这两天，某县县委书记号召领导干部买房的视频刷了屏，而近期“多地鼓励农民进城买房”的话题也备受关注。农民日报评鼓励农民进城买房：不能不算后路账。",
    "url": "https://www.baidu.com/s?wd=%E5%86%9C%E6%B0%91%E6%97%A5%E6%8A%A5%E8%AF%84%E5%A4%9A%E5%9C%B0%E9%BC%93%E5%8A%B1%E5%86%9C%E6%B0%91%E8%BF%9B%E5%9F%8E%E4%B9%B0%E6%88%BF&sa=fyb_news&rsv_dl=fyb_news"
  },
  {
    "title": "上海将发放10亿元电子消费券",
    "description": "",
    "url": "https://www.baidu.com/s?wd=%E4%B8%8A%E6%B5%B7%E5%B0%86%E5%8F%91%E6%94%BE10%E4%BA%BF%E5%85%83%E7%94%B5%E5%AD%90%E6%B6%88%E8%B4%B9%E5%88%B8&sa=fyb_news&rsv_dl=fyb_news"
  },
  {
    "title": "经济日报：理性看待居民电费攀升",
    "description": "今夏电费出现大幅上涨，实则是用电量增加所致。参考发达国家经验，随着经济社会发展和人民生活水平的提高，居民用电量和电费上涨...   今夏电费出现大幅上涨，实则是用电量增加所致。参考发达国家经验，随着经济社会发展和人民生活水平的提高，居民用电量和电费上涨属于正常现象。",
    "url": "https://www.baidu.com/s?wd=%E7%BB%8F%E6%B5%8E%E6%97%A5%E6%8A%A5%EF%BC%9A%E7%90%86%E6%80%A7%E7%9C%8B%E5%BE%85%E5%B1%85%E6%B0%91%E7%94%B5%E8%B4%B9%E6%94%80%E5%8D%87&sa=fyb_news&rsv_dl=fyb_news"
  },
  {
    "title": "北京多家银行可做接力贷",
    "description": "近日，北京部分银行开展接力贷业务，即父母作为主借款人，子女作为共同借款人，只要父母具备北京购房资格，父母和子女的收入总计...   近日，北京部分银行开展接力贷业务，即父母作为主借款人，子女作为共同借款人，只要父母具备北京购房资格，父母和子女的收入总计不低于月供的2倍。",
    "url": "https://www.baidu.com/s?wd=%E5%8C%97%E4%BA%AC%E5%A4%9A%E5%AE%B6%E9%93%B6%E8%A1%8C%E5%8F%AF%E5%81%9A%E6%8E%A5%E5%8A%9B%E8%B4%B7&sa=fyb_news&rsv_dl=fyb_news"
  },
  {
    "title": "村民在墓穴躺坐一排乘凉：人多不怕",
    "description": "近日，有网传视频显示，在眉山市青神县，当地村民到全国重点文物保护单位瑞峰崖墓群里部分崖墓避暑，他们在墓穴里躺坐一排，称人...   近日，有网传视频显示，在眉山市青神县，当地村民到全国重点文物保护单位瑞峰崖墓群里部分崖墓避暑，他们在墓穴里躺坐一排，称人多就不害怕。",
    "url": "https://www.baidu.com/s?wd=%E6%9D%91%E6%B0%91%E5%9C%A8%E5%A2%93%E7%A9%B4%E8%BA%BA%E5%9D%90%E4%B8%80%E6%8E%92%E4%B9%98%E5%87%89%EF%BC%9A%E4%BA%BA%E5%A4%9A%E4%B8%8D%E6%80%95&sa=fyb_news&rsv_dl=fyb_news"
  },
  {
    "title": "劳荣枝案二审开庭",
    "description": "8月18日9时30分，劳荣枝案二审在江西省高级人民法院开庭。此前，劳荣枝一审被判死刑。据悉，此次庭审将以视频的方式进行。   8月18日9时30分，劳荣枝案二审在江西省高级人民法院开庭。此前，劳荣枝一审被判死刑。据悉，此次庭审将以视频的方式进行。",
    "url": "https://www.baidu.com/s?wd=%E5%8A%B3%E8%8D%A3%E6%9E%9D%E6%A1%88%E4%BA%8C%E5%AE%A1%E5%BC%80%E5%BA%AD&sa=fyb_news&rsv_dl=fyb_news"
  },
  {
    "title": "重庆高温 地铁楼梯上长满了人",
    "description": "持续高温，各地电网负荷屡创新高，川渝多地开启省电模式。重庆地铁楼梯上“长满了人”，网友表示：家里能省电，还能给城市电力减...   持续高温，各地电网负荷屡创新高，川渝多地开启省电模式。重庆地铁楼梯上“长满了人”，网友表示：家里能省电，还能给城市电力减压。",
    "url": "https://www.baidu.com/s?wd=%E9%87%8D%E5%BA%86%E9%AB%98%E6%B8%A9+%E5%9C%B0%E9%93%81%E6%A5%BC%E6%A2%AF%E4%B8%8A%E9%95%BF%E6%BB%A1%E4%BA%86%E4%BA%BA&sa=fyb_news&rsv_dl=fyb_news"
  },
  {
    "title": "两千多家在印外企为何“跑路”了",
    "description": "近期，印度以涉嫌逃税等理由对vivo、小米等中国企业进行突击检查。据印度政府数据显示，在过去七八年，超过2000家跨国公...   近期，印度以涉嫌逃税等理由对vivo、小米等中国企业进行突击检查。据印度政府数据显示，在过去七八年，超过2000家跨国公司暂停其在印度业务。",
    "url": "https://www.baidu.com/s?wd=%E4%B8%A4%E5%8D%83%E5%A4%9A%E5%AE%B6%E5%9C%A8%E5%8D%B0%E5%A4%96%E4%BC%81%E4%B8%BA%E4%BD%95%E2%80%9C%E8%B7%91%E8%B7%AF%E2%80%9D%E4%BA%86&sa=fyb_news&rsv_dl=fyb_news"
  },
  {
    "title": "中日在天津举行高级别政治对话",
    "description": "8月17日，中共中央政治局委员、中央外事工作委员会办公室主任杨洁篪在天津同日本国家安全保障局长秋叶刚男共同主持中日第九次...   8月17日，中共中央政治局委员、中央外事工作委员会办公室主任杨洁篪在天津同日本国家安全保障局长秋叶刚男共同主持中日第九次高级别政治对话。",
    "url": "https://www.baidu.com/s?wd=%E4%B8%AD%E6%97%A5%E5%9C%A8%E5%A4%A9%E6%B4%A5%E4%B8%BE%E8%A1%8C%E9%AB%98%E7%BA%A7%E5%88%AB%E6%94%BF%E6%B2%BB%E5%AF%B9%E8%AF%9D&sa=fyb_news&rsv_dl=fyb_news"
  },
  {
    "title": "英首相候选人录音外泄引争议",
    "description": "",
    "url": "https://www.baidu.com/s?wd=%E8%8B%B1%E9%A6%96%E7%9B%B8%E5%80%99%E9%80%89%E4%BA%BA%E5%BD%95%E9%9F%B3%E5%A4%96%E6%B3%84%E5%BC%95%E4%BA%89%E8%AE%AE&sa=fyb_news&rsv_dl=fyb_news"
  },
  {
    "title": "818百度搜索节：老板们的专属福利",
    "description": "",
    "url": "https://www.baidu.com/s?wd=818%E7%99%BE%E5%BA%A6%E6%90%9C%E7%B4%A2%E8%8A%82&sa=fyb_news&rsv_dl=fyb_news"
  },
  {
    "title": "31省份昨日新增本土“614+2810”",
    "description": "8月17日0—24时，31个省（自治区、直辖市）和新疆生产建设兵团报告新增本土确诊病例614例，新增本土无症状感染者28...   8月17日0—24时，31个省（自治区、直辖市）和新疆生产建设兵团报告新增本土确诊病例614例，新增本土无症状感染者2810例。",
    "url": "https://www.baidu.com/s?wd=31%E7%9C%81%E4%BB%BD%E6%98%A8%E6%97%A5%E6%96%B0%E5%A2%9E%E6%9C%AC%E5%9C%9F%E2%80%9C614%2B2810%E2%80%9D&sa=fyb_news&rsv_dl=fyb_news"
  },
  {
    "title": "寿司郎回应禁止员工上班说粤语",
    "description": "近日，网传寿司郎广州一门店禁止员工上班期间说粤语，违反者会被严格处理。寿司郎回应：内部信息传递表述不当，从未禁止员工以粤...   近日，网传寿司郎广州一门店禁止员工上班期间说粤语，违反者会被严格处理。寿司郎回应：内部信息传递表述不当，从未禁止员工以粤语与客人沟通。",
    "url": "https://www.baidu.com/s?wd=%E5%AF%BF%E5%8F%B8%E9%83%8E%E5%9B%9E%E5%BA%94%E7%A6%81%E6%AD%A2%E5%91%98%E5%B7%A5%E4%B8%8A%E7%8F%AD%E8%AF%B4%E7%B2%A4%E8%AF%AD&sa=fyb_news&rsv_dl=fyb_news"
  },
  {
    "title": "庐山瀑布缩水成一根线",
    "description": "近日，江西庐山市，受连续高温干旱影响，庐山瀑布缩水成一根线。   近日，江西庐山市，受连续高温干旱影响，庐山瀑布缩水成一根线。",
    "url": "https://www.baidu.com/s?wd=%E5%BA%90%E5%B1%B1%E7%80%91%E5%B8%83%E7%BC%A9%E6%B0%B4%E6%88%90%E4%B8%80%E6%A0%B9%E7%BA%BF&sa=fyb_news&rsv_dl=fyb_news"
  },
  {
    "title": "韩外长：排除中国何谈印太未来",
    "description": "",
    "url": "https://www.baidu.com/s?wd=%E9%9F%A9%E5%A4%96%E9%95%BF%EF%BC%9A%E6%8E%92%E9%99%A4%E4%B8%AD%E5%9B%BD%E4%BD%95%E8%B0%88%E5%8D%B0%E5%A4%AA%E6%9C%AA%E6%9D%A5&sa=fyb_news&rsv_dl=fyb_news"
  },
  {
    "title": "世卫征集猴痘新名字：避免污名化",
    "description": "",
    "url": "https://www.baidu.com/s?wd=%E4%B8%96%E5%8D%AB%E5%BE%81%E9%9B%86%E7%8C%B4%E7%97%98%E6%96%B0%E5%90%8D%E5%AD%97%EF%BC%9A%E9%81%BF%E5%85%8D%E6%B1%A1%E5%90%8D%E5%8C%96&sa=fyb_news&rsv_dl=fyb_news"
  },
  {
    "title": "青海西宁发生山洪已致4死27失联",
    "description": "8月18日，西宁市大通县发生山洪灾害造成4人死亡，27人失联。青海省突发公共事件应急管理委员会决定，针对此次灾害启动省级...   8月18日，西宁市大通县发生山洪灾害造成4人死亡，27人失联。青海省突发公共事件应急管理委员会决定，针对此次灾害启动省级突发灾害事件Ⅱ应急响应。",
    "url": "https://www.baidu.com/s?wd=%E9%9D%92%E6%B5%B7%E8%A5%BF%E5%AE%81%E5%8F%91%E7%94%9F%E5%B1%B1%E6%B4%AA%E5%B7%B2%E8%87%B44%E6%AD%BB27%E5%A4%B1%E8%81%94&sa=fyb_news&rsv_dl=fyb_news"
  },
  {
    "title": "Z22次列车已检出4例阳性 涉3省多地",
    "description": "由西藏拉萨站开往北京西站的Z22次列车，共有10站，途经多个省份。目前该车次已至少检出4例阳性人员，涉及河北沧州、山西晋...   由西藏拉萨站开往北京西站的Z22次列车，共有10站，途经多个省份。目前该车次已至少检出4例阳性人员，涉及河北沧州、山西晋城、山东枣庄等地。",
    "url": "https://www.baidu.com/s?wd=Z22%E6%AC%A1%E5%88%97%E8%BD%A6%E5%B7%B2%E6%A3%80%E5%87%BA4%E4%BE%8B%E9%98%B3%E6%80%A7+%E6%B6%893%E7%9C%81%E5%A4%9A%E5%9C%B0&sa=fyb_news&rsv_dl=fyb_news"
  },
  {
    "title": "中国统一时间表提速了？秦刚回应",
    "description": "16日，秦刚大使在华盛顿接受美媒联合采访。关于统一台湾时间表的问题，秦刚大使表示，不知道有什么具体的时间表，但有实现和平...   16日，秦刚大使在华盛顿接受美媒联合采访。关于统一台湾时间表的问题，秦刚大使表示，不知道有什么具体的时间表，但有实现和平统一的愿望和前景。",
    "url": "https://www.baidu.com/s?wd=%E4%B8%AD%E5%9B%BD%E7%BB%9F%E4%B8%80%E6%97%B6%E9%97%B4%E8%A1%A8%E6%8F%90%E9%80%9F%E4%BA%86%EF%BC%9F%E7%A7%A6%E5%88%9A%E5%9B%9E%E5%BA%94&sa=fyb_news&rsv_dl=fyb_news"
  },
  {
    "title": "南京茶颜悦色黄牛代购1杯200元",
    "description": "8月18日，南京首家茶颜悦色开业，一大早店还没开门，人们已在门口排起长队。有网友称，有黄牛开出代排队买奶茶的价格：200...   8月18日，南京首家茶颜悦色开业，一大早店还没开门，人们已在门口排起长队。有网友称，有黄牛开出代排队买奶茶的价格：200元1杯。",
    "url": "https://www.baidu.com/s?wd=%E5%8D%97%E4%BA%AC%E8%8C%B6%E9%A2%9C%E6%82%A6%E8%89%B2%E9%BB%84%E7%89%9B%E4%BB%A3%E8%B4%AD1%E6%9D%AF200%E5%85%83&sa=fyb_news&rsv_dl=fyb_news"
  },
  {
    "title": "男孩按停扶梯致女孩摔伤 双方和解",
    "description": "近日，深圳某商场内一男孩无故按停电梯导致女孩摔倒受伤引关注。17日晚，在警方的介入下，按停电梯的男孩已找到，男孩家长诚恳...   近日，深圳某商场内一男孩无故按停电梯导致女孩摔倒受伤引关注。17日晚，在警方的介入下，按停电梯的男孩已找到，男孩家长诚恳致歉，双方达成和解。",
    "url": "https://www.baidu.com/s?wd=%E7%94%B7%E5%AD%A9%E6%8C%89%E5%81%9C%E6%89%B6%E6%A2%AF%E8%87%B4%E5%A5%B3%E5%AD%A9%E6%91%94%E4%BC%A4+%E5%8F%8C%E6%96%B9%E5%92%8C%E8%A7%A3&sa=fyb_news&rsv_dl=fyb_news"
  },
  {
    "title": "官方回应厦门给鱼做核酸",
    "description": "8月17日，一则关于厦门市集美区给渔获做核酸的报道引发关注。一名工作人员回应：“目前厦门市全员都要核酸，渔获也要进行核酸...   8月17日，一则关于厦门市集美区给渔获做核酸的报道引发关注。一名工作人员回应：“目前厦门市全员都要核酸，渔获也要进行核酸。”",
    "url": "https://www.baidu.com/s?wd=%E5%AE%98%E6%96%B9%E5%9B%9E%E5%BA%94%E5%8E%A6%E9%97%A8%E7%BB%99%E9%B1%BC%E5%81%9A%E6%A0%B8%E9%85%B8&sa=fyb_news&rsv_dl=fyb_news"
  },
  {
    "title": "四川男子嘉陵江救人遇难",
    "description": "",
    "url": "https://www.baidu.com/s?wd=%E5%9B%9B%E5%B7%9D%E7%94%B7%E5%AD%90%E5%98%89%E9%99%B5%E6%B1%9F%E6%95%91%E4%BA%BA%E9%81%87%E9%9A%BE&sa=fyb_news&rsv_dl=fyb_news"
  },
  {
    "title": "台空军90人疑似集体食物中毒",
    "description": "据台湾雅虎新闻消息，17日下午，台湾屏东空军基地被曝疑似出现集体食物中毒事件，90多名官兵被紧急送医治疗。   据台湾雅虎新闻消息，17日下午，台湾屏东空军基地被曝疑似出现集体食物中毒事件，90多名官兵被紧急送医治疗。",
    "url": "https://www.baidu.com/s?wd=%E5%8F%B0%E7%A9%BA%E5%86%9B90%E4%BA%BA%E7%96%91%E4%BC%BC%E9%9B%86%E4%BD%93%E9%A3%9F%E7%89%A9%E4%B8%AD%E6%AF%92&sa=fyb_news&rsv_dl=fyb_news"
  },
  {
    "title": "日本7月恢复进口俄罗斯石油",
    "description": "",
    "url": "https://www.baidu.com/s?wd=%E6%97%A5%E6%9C%AC7%E6%9C%88%E6%81%A2%E5%A4%8D%E8%BF%9B%E5%8F%A3%E4%BF%84%E7%BD%97%E6%96%AF%E7%9F%B3%E6%B2%B9&sa=fyb_news&rsv_dl=fyb_news"
  },
  {
    "title": "劳荣枝庭审现场：穿防护服 戴手铐",
    "description": "8月18日，江西南昌劳荣枝案二审开庭审理。庭审现场，劳荣枝身穿防护服戴手铐，被法警押解出庭。   8月18日，江西南昌劳荣枝案二审开庭审理。庭审现场，劳荣枝身穿防护服戴手铐，被法警押解出庭。",
    "url": "https://www.baidu.com/s?wd=%E5%8A%B3%E8%8D%A3%E6%9E%9D%E5%BA%AD%E5%AE%A1%E7%8E%B0%E5%9C%BA%EF%BC%9A%E7%A9%BF%E9%98%B2%E6%8A%A4%E6%9C%8D+%E6%88%B4%E6%89%8B%E9%93%90&sa=fyb_news&rsv_dl=fyb_news"
  },
  {
    "title": "女游客在海面上漂浮一夜后被救",
    "description": "",
    "url": "https://www.baidu.com/s?wd=%E5%A5%B3%E6%B8%B8%E5%AE%A2%E5%9C%A8%E6%B5%B7%E9%9D%A2%E4%B8%8A%E6%BC%82%E6%B5%AE%E4%B8%80%E5%A4%9C%E5%90%8E%E8%A2%AB%E6%95%91&sa=fyb_news&rsv_dl=fyb_news"
  },
  {
    "title": "成都：关闭所有户外广告照明",
    "description": "8月16日，成都市城管委要求关闭全部政府投资建设和企业自建自管的景观照明、灯光秀、形象展示及非安全照明设施，关闭所有户外...   8月16日，成都市城管委要求关闭全部政府投资建设和企业自建自管的景观照明、灯光秀、形象展示及非安全照明设施，关闭所有户外广告照明。",
    "url": "https://www.baidu.com/s?wd=%E6%88%90%E9%83%BD%EF%BC%9A%E5%85%B3%E9%97%AD%E6%89%80%E6%9C%89%E6%88%B7%E5%A4%96%E5%B9%BF%E5%91%8A%E7%85%A7%E6%98%8E&sa=fyb_news&rsv_dl=fyb_news"
  },
  {
    "title": "江疏影方回应网传猜测",
    "description": "近日，有网友曝江疏影与已婚富豪酒店约会。18日，江疏影工作室发布声明：舆论被有心之人煽动愈演愈烈，对造谣、传谣绝不姑息。   近日，有网友曝江疏影与已婚富豪酒店约会。18日，江疏影工作室发布声明：舆论被有心之人煽动愈演愈烈，对造谣、传谣绝不姑息。",
    "url": "https://www.baidu.com/s?wd=%E6%B1%9F%E7%96%8F%E5%BD%B1%E6%96%B9%E5%9B%9E%E5%BA%94%E7%BD%91%E4%BC%A0%E7%8C%9C%E6%B5%8B&sa=fyb_news&rsv_dl=fyb_news"
  },
  {
    "title": "男子把锅改装成方向盘边开车边泡面",
    "description": "近日，一条视频引发网友关注，视频中男子将锅改成方向盘，边开车边泡面。经查，视频中的男子但某从事汽修行业，目前但某已被交警...   近日，一条视频引发网友关注，视频中男子将锅改成方向盘，边开车边泡面。经查，视频中的男子但某从事汽修行业，目前但某已被交警部门批评和处罚。",
    "url": "https://www.baidu.com/s?wd=%E7%94%B7%E5%AD%90%E6%8A%8A%E9%94%85%E6%94%B9%E8%A3%85%E6%88%90%E6%96%B9%E5%90%91%E7%9B%98%E8%BE%B9%E5%BC%80%E8%BD%A6%E8%BE%B9%E6%B3%A1%E9%9D%A2&sa=fyb_news&rsv_dl=fyb_news"
  },
  {
    "title": "英雄万惠文今日安葬",
    "description": "",
    "url": "https://www.baidu.com/s?wd=%E8%8B%B1%E9%9B%84%E4%B8%87%E6%83%A0%E6%96%87%E4%BB%8A%E6%97%A5%E5%AE%89%E8%91%AC&sa=fyb_news&rsv_dl=fyb_news"
  },
  {
    "title": "女孩取快递被骚扰老板呵斥保护",
    "description": "8月17日，江苏扬州。一位小女孩独自去母婴店取快递，被一名男子尾随骚扰，老板发现异常后呵斥男子离开，并把女孩留在店里，最...   8月17日，江苏扬州。一位小女孩独自去母婴店取快递，被一名男子尾随骚扰，老板发现异常后呵斥男子离开，并把女孩留在店里，最终让妈妈把她接了回去。",
    "url": "https://www.baidu.com/s?wd=%E5%A5%B3%E5%AD%A9%E5%8F%96%E5%BF%AB%E9%80%92%E8%A2%AB%E9%AA%9A%E6%89%B0%E8%80%81%E6%9D%BF%E5%91%B5%E6%96%A5%E4%BF%9D%E6%8A%A4&sa=fyb_news&rsv_dl=fyb_news"
  },
  {
    "title": "西宁洪灾致4死27失联 直击现场",
    "description": "8月17日至18日，青海西宁市地区出现强降雨天气。18日，西宁市大通县发生山洪灾害已造成4人死亡，27人失联。   8月17日至18日，青海西宁市地区出现强降雨天气。18日，西宁市大通县发生山洪灾害已造成4人死亡，27人失联。",
    "url": "https://www.baidu.com/s?wd=%E8%A5%BF%E5%AE%81%E6%B4%AA%E7%81%BE%E8%87%B44%E6%AD%BB27%E5%A4%B1%E8%81%94+%E7%9B%B4%E5%87%BB%E7%8E%B0%E5%9C%BA&sa=fyb_news&rsv_dl=fyb_news"
  },
  {
    "title": "黄之锋等人承认串谋颠覆国家政权罪",
    "description": "8月18日，反中乱港分子戴耀庭、黄之锋等29名被告，承认“串谋颠覆国家政权罪”，将交付香港高等法院判刑。   8月18日，反中乱港分子戴耀庭、黄之锋等29名被告，承认“串谋颠覆国家政权罪”，将交付香港高等法院判刑。",
    "url": "https://www.baidu.com/s?wd=%E9%BB%84%E4%B9%8B%E9%94%8B%E7%AD%89%E4%BA%BA%E6%89%BF%E8%AE%A4%E4%B8%B2%E8%B0%8B%E9%A2%A0%E8%A6%86%E5%9B%BD%E5%AE%B6%E6%94%BF%E6%9D%83%E7%BD%AA&sa=fyb_news&rsv_dl=fyb_news"
  },
  {
    "title": "男孩阻止老人插队引发打架 老人被拘",
    "description": "近日，陕西安康一15岁男孩在排队接水过程中，阻止63岁男子徐某某插队，引发争吵打架。8月17日，安康市公安局高新分局通报...   近日，陕西安康一15岁男孩在排队接水过程中，阻止63岁男子徐某某插队，引发争吵打架。8月17日，安康市公安局高新分局通报，已给予徐某某行政拘留处罚。",
    "url": "https://www.baidu.com/s?wd=%E7%94%B7%E5%AD%A9%E9%98%BB%E6%AD%A2%E8%80%81%E4%BA%BA%E6%8F%92%E9%98%9F%E5%BC%95%E5%8F%91%E6%89%93%E6%9E%B6+%E8%80%81%E4%BA%BA%E8%A2%AB%E6%8B%98&sa=fyb_news&rsv_dl=fyb_news"
  },
  {
    "title": "部分广播剧因技术原因下架",
    "description": "",
    "url": "https://www.baidu.com/s?wd=%E9%83%A8%E5%88%86%E5%B9%BF%E6%92%AD%E5%89%A7%E5%9B%A0%E6%8A%80%E6%9C%AF%E5%8E%9F%E5%9B%A0%E4%B8%8B%E6%9E%B6&sa=fyb_news&rsv_dl=fyb_news"
  },
  {
    "title": "法庭驳回劳荣枝对案件管辖权异议",
    "description": "8月18日上午，劳荣枝案进行二审。在庭前会议中，劳荣枝及其辩护人表示不申请回避。劳荣枝及其辩护人对案件管辖权发表异议，被...   8月18日上午，劳荣枝案进行二审。在庭前会议中，劳荣枝及其辩护人表示不申请回避。劳荣枝及其辩护人对案件管辖权发表异议，被法庭依法驳回。",
    "url": "https://www.baidu.com/s?wd=%E6%B3%95%E5%BA%AD%E9%A9%B3%E5%9B%9E%E5%8A%B3%E8%8D%A3%E6%9E%9D%E5%AF%B9%E6%A1%88%E4%BB%B6%E7%AE%A1%E8%BE%96%E6%9D%83%E5%BC%82%E8%AE%AE&sa=fyb_news&rsv_dl=fyb_news"
  },
  {
    "title": "受害者家属：劳荣枝仍自称是受害人",
    "description": "8月18日，劳荣枝案二审上午庭审结束后，受害人熊某某的弟弟接受采访时提到，劳荣枝在庭审中表现淡定，并不紧张，仍自称是受害...   8月18日，劳荣枝案二审上午庭审结束后，受害人熊某某的弟弟接受采访时提到，劳荣枝在庭审中表现淡定，并不紧张，仍自称是受害人。",
    "url": "https://www.baidu.com/s?wd=%E5%8F%97%E5%AE%B3%E8%80%85%E5%AE%B6%E5%B1%9E%EF%BC%9A%E5%8A%B3%E8%8D%A3%E6%9E%9D%E4%BB%8D%E8%87%AA%E7%A7%B0%E6%98%AF%E5%8F%97%E5%AE%B3%E4%BA%BA&sa=fyb_news&rsv_dl=fyb_news"
  },
  {
    "title": "合肥严格处置故意躺平房企",
    "description": "",
    "url": "https://www.baidu.com/s?wd=%E5%90%88%E8%82%A5%E4%B8%A5%E6%A0%BC%E5%A4%84%E7%BD%AE%E6%95%85%E6%84%8F%E8%BA%BA%E5%B9%B3%E6%88%BF%E4%BC%81&sa=fyb_news&rsv_dl=fyb_news"
  },
  {
    "title": "王霜首次首发斩获留美生涯首球",
    "description": "",
    "url": "https://www.baidu.com/s?wd=%E7%8E%8B%E9%9C%9C%E9%A6%96%E6%AC%A1%E9%A6%96%E5%8F%91%E6%96%A9%E8%8E%B7%E7%95%99%E7%BE%8E%E7%94%9F%E6%B6%AF%E9%A6%96%E7%90%83&sa=fyb_news&rsv_dl=fyb_news"
  },
  {
    "title": "青海西宁山洪已致16死36失联",
    "description": "8月17日22时25分，青海省西宁市大通县瞬间强降雨，引发山洪，造成泥石流。截至18日12时，已造成16人死亡，36人失...   8月17日22时25分，青海省西宁市大通县瞬间强降雨，引发山洪，造成泥石流。截至18日12时，已造成16人死亡，36人失联。",
    "url": "https://www.baidu.com/s?wd=%E9%9D%92%E6%B5%B7%E8%A5%BF%E5%AE%81%E5%B1%B1%E6%B4%AA%E5%B7%B2%E8%87%B416%E6%AD%BB36%E5%A4%B1%E8%81%94&sa=fyb_news&rsv_dl=fyb_news"
  },
  {
    "title": "长沙一医生被曝医疗作风有问题",
    "description": "17日，网友反映中南大学湘雅二医院一医生医疗作风有问题，引起关注。18日，湘雅二院医疗作风建设办公室回应：该医生已停职，...   17日，网友反映中南大学湘雅二医院一医生医疗作风有问题，引起关注。18日，湘雅二院医疗作风建设办公室回应：该医生已停职，正在接受调查。",
    "url": "https://www.baidu.com/s?wd=%E9%95%BF%E6%B2%99%E4%B8%80%E5%8C%BB%E7%94%9F%E8%A2%AB%E6%9B%9D%E5%8C%BB%E7%96%97%E4%BD%9C%E9%A3%8E%E6%9C%89%E9%97%AE%E9%A2%98&sa=fyb_news&rsv_dl=fyb_news"
  },
  {
    "title": "南京一茶颜悦色开业半小时后停业",
    "description": "8月18日南京一家茶颜悦色开业，因人流量过大造成拥堵，大约开业半小时后暂停营业。对此茶颜悦色方面表示，“我们现在正在和商...   8月18日南京一家茶颜悦色开业，因人流量过大造成拥堵，大约开业半小时后暂停营业。对此茶颜悦色方面表示，“我们现在正在和商场方协调沟通解决”。",
    "url": "https://www.baidu.com/s?wd=%E5%8D%97%E4%BA%AC%E4%B8%80%E8%8C%B6%E9%A2%9C%E6%82%A6%E8%89%B2%E5%BC%80%E4%B8%9A%E5%8D%8A%E5%B0%8F%E6%97%B6%E5%90%8E%E5%81%9C%E4%B8%9A&sa=fyb_news&rsv_dl=fyb_news"
  },
  {
    "title": "劳荣枝案庭审对抗激烈 或持续多日",
    "description": "8月18日，劳荣枝案二审在江西省高级人民法院开庭审理。当日上午，仅就一个问题双方对抗相当激烈，庭审将持续多日。   8月18日，劳荣枝案二审在江西省高级人民法院开庭审理。当日上午，仅就一个问题双方对抗相当激烈，庭审将持续多日。",
    "url": "https://www.baidu.com/s?wd=%E5%8A%B3%E8%8D%A3%E6%9E%9D%E6%A1%88%E5%BA%AD%E5%AE%A1%E5%AF%B9%E6%8A%97%E6%BF%80%E7%83%88+%E6%88%96%E6%8C%81%E7%BB%AD%E5%A4%9A%E6%97%A5&sa=fyb_news&rsv_dl=fyb_news"
  },
  {
    "title": "青海西宁山洪已致16死",
    "description": "8月17日22时25分，青海省西宁市大通县瞬间强降雨，引发山洪，造成泥石流。截至18日12时，已造成16人死亡。   8月17日22时25分，青海省西宁市大通县瞬间强降雨，引发山洪，造成泥石流。截至18日12时，已造成16人死亡。",
    "url": "https://www.baidu.com/s?wd=%E9%9D%92%E6%B5%B7%E8%A5%BF%E5%AE%81%E5%B1%B1%E6%B4%AA%E5%B7%B2%E8%87%B416%E6%AD%BB&sa=fyb_news&rsv_dl=fyb_news"
  },
  {
    "title": "长沙湘雅二院通报网传医生作风问题",
    "description": "17日，网友反映中南大学湘雅二医院一医生医疗作风有问题，引起关注。18日，湘雅二院医疗作风建设办公室回应：该医生已停职，...   17日，网友反映中南大学湘雅二医院一医生医疗作风有问题，引起关注。18日，湘雅二院医疗作风建设办公室回应：该医生已停职，正在接受调查。",
    "url": "https://www.baidu.com/s?wd=%E9%95%BF%E6%B2%99%E6%B9%98%E9%9B%85%E4%BA%8C%E9%99%A2%E9%80%9A%E6%8A%A5%E7%BD%91%E4%BC%A0%E5%8C%BB%E7%94%9F%E4%BD%9C%E9%A3%8E%E9%97%AE%E9%A2%98&sa=fyb_news&rsv_dl=fyb_news"
  },
  {
    "title": "鄱阳湖被热缩水了",
    "description": "受持续高温影响，我国最大淡水湖，江西鄱阳湖的水位持续走低。截止到17日8点，长江湖口站水位和鄱阳湖星子站水位均比往年偏低...   受持续高温影响，我国最大淡水湖，江西鄱阳湖的水位持续走低。截止到17日8点，长江湖口站水位和鄱阳湖星子站水位均比往年偏低6米多。",
    "url": "https://www.baidu.com/s?wd=%E9%84%B1%E9%98%B3%E6%B9%96%E8%A2%AB%E7%83%AD%E7%BC%A9%E6%B0%B4%E4%BA%86&sa=fyb_news&rsv_dl=fyb_news"
  },
  {
    "title": "劳荣枝案双方就11项异议举证质证",
    "description": "劳荣枝案二审于18日下午1点30分继续开庭，控辩双方对劳荣枝及其辩护人针对一审判决提出的11项异议展开举证质证。   劳荣枝案二审于18日下午1点30分继续开庭，控辩双方对劳荣枝及其辩护人针对一审判决提出的11项异议展开举证质证。",
    "url": "https://www.baidu.com/s?wd=%E5%8A%B3%E8%8D%A3%E6%9E%9D%E6%A1%88%E5%8F%8C%E6%96%B9%E5%B0%B111%E9%A1%B9%E5%BC%82%E8%AE%AE%E4%B8%BE%E8%AF%81%E8%B4%A8%E8%AF%81&sa=fyb_news&rsv_dl=fyb_news"
  },
  {
    "title": "乌克兰官员承认：爆炸我们干的",
    "description": "",
    "url": "https://www.baidu.com/s?wd=%E4%B9%8C%E5%85%8B%E5%85%B0%E5%AE%98%E5%91%98%E6%89%BF%E8%AE%A4%EF%BC%9A%E7%88%86%E7%82%B8%E6%88%91%E4%BB%AC%E5%B9%B2%E7%9A%84&sa=fyb_news&rsv_dl=fyb_news"
  },
  {
    "title": "官方回应四姑娘山万年冰川裸了",
    "description": "",
    "url": "https://www.baidu.com/s?wd=%E5%AE%98%E6%96%B9%E5%9B%9E%E5%BA%94%E5%9B%9B%E5%A7%91%E5%A8%98%E5%B1%B1%E4%B8%87%E5%B9%B4%E5%86%B0%E5%B7%9D%E8%A3%B8%E4%BA%86&sa=fyb_news&rsv_dl=fyb_news"
  },
  {
    "title": "哺乳期顾客染发遭店主秒拒",
    "description": "",
    "url": "https://www.baidu.com/s?wd=%E5%93%BA%E4%B9%B3%E6%9C%9F%E9%A1%BE%E5%AE%A2%E6%9F%93%E5%8F%91%E9%81%AD%E5%BA%97%E4%B8%BB%E7%A7%92%E6%8B%92&sa=fyb_news&rsv_dl=fyb_news"
  },
  {
    "title": "iPhone14Pro将涨价100美元",
    "description": "",
    "url": "https://www.baidu.com/s?wd=iPhone14Pro%E5%B0%86%E6%B6%A8%E4%BB%B7100%E7%BE%8E%E5%85%83&sa=fyb_news&rsv_dl=fyb_news"
  },
  {
    "title": "《亲爱的》原型男孩到武大报到",
    "description": "8月18日上午，电影《亲爱的》原型之一彭文乐到武汉大学报到。今年高考，18岁的彭文乐以总分632分的成绩被武汉大学计算机...   8月18日上午，电影《亲爱的》原型之一彭文乐到武汉大学报到。今年高考，18岁的彭文乐以总分632分的成绩被武汉大学计算机学院录取。",
    "url": "https://www.baidu.com/s?wd=%E3%80%8A%E4%BA%B2%E7%88%B1%E7%9A%84%E3%80%8B%E5%8E%9F%E5%9E%8B%E7%94%B7%E5%AD%A9%E5%88%B0%E6%AD%A6%E5%A4%A7%E6%8A%A5%E5%88%B0&sa=fyb_news&rsv_dl=fyb_news"
  },
  {
    "title": "习近平在辽宁沈阳考察调研",
    "description": "17日，习近平在辽宁沈阳市先后来到沈阳新松机器人自动化股份有限公司、皇姑区三台子街道牡丹社区，考察企业科技创新、基层党建...   17日，习近平在辽宁沈阳市先后来到沈阳新松机器人自动化股份有限公司、皇姑区三台子街道牡丹社区，考察企业科技创新、基层党建和社区服务等情况。",
    "url": "https://www.baidu.com/s?wd=%E4%B9%A0%E8%BF%91%E5%B9%B3%E5%9C%A8%E8%BE%BD%E5%AE%81%E6%B2%88%E9%98%B3%E8%80%83%E5%AF%9F%E8%B0%83%E7%A0%94&sa=fyb_news&rsv_dl=fyb_news"
  },
  {
    "title": "中国这十年",
    "description": "中共中央宣传部18日上午举行“中国这十年”系列主题新闻发布会，介绍新时代宣传文化工作举措与成效，并答记者问。   中共中央宣传部18日上午举行“中国这十年”系列主题新闻发布会，介绍新时代宣传文化工作举措与成效，并答记者问。",
    "url": "https://www.baidu.com/s?wd=%E4%B8%AD%E5%9B%BD%E8%BF%99%E5%8D%81%E5%B9%B4&sa=fyb_news&rsv_dl=fyb_news"
  },
  {
    "title": "山洪暴发前 村干部嘶吼通知撤离",
    "description": "",
    "url": "https://www.baidu.com/s?wd=%E5%B1%B1%E6%B4%AA%E6%9A%B4%E5%8F%91%E5%89%8D+%E6%9D%91%E5%B9%B2%E9%83%A8%E5%98%B6%E5%90%BC%E9%80%9A%E7%9F%A5%E6%92%A4%E7%A6%BB&sa=fyb_news&rsv_dl=fyb_news"
  },
  {
    "title": "福布斯中国发布最佳CEO排名",
    "description": "",
    "url": "https://www.baidu.com/s?wd=%E7%A6%8F%E5%B8%83%E6%96%AF%E4%B8%AD%E5%9B%BD%E5%8F%91%E5%B8%83%E6%9C%80%E4%BD%B3CEO%E6%8E%92%E5%90%8D&sa=fyb_news&rsv_dl=fyb_news"
  },
  {
    "title": "人民网评南京茶颜悦色",
    "description": "",
    "url": "https://www.baidu.com/s?wd=%E4%BA%BA%E6%B0%91%E7%BD%91%E8%AF%84%E5%8D%97%E4%BA%AC%E8%8C%B6%E9%A2%9C%E6%82%A6%E8%89%B2&sa=fyb_news&rsv_dl=fyb_news"
  },
  {
    "title": "平安银行回应员工降薪",
    "description": "",
    "url": "https://www.baidu.com/s?wd=%E5%B9%B3%E5%AE%89%E9%93%B6%E8%A1%8C%E5%9B%9E%E5%BA%94%E5%91%98%E5%B7%A5%E9%99%8D%E8%96%AA&sa=fyb_news&rsv_dl=fyb_news"
  },
  {
    "title": "南京抽调警力维护茶颜排队秩序",
    "description": "",
    "url": "https://www.baidu.com/s?wd=%E5%8D%97%E4%BA%AC%E6%8A%BD%E8%B0%83%E8%AD%A6%E5%8A%9B%E7%BB%B4%E6%8A%A4%E8%8C%B6%E9%A2%9C%E6%8E%92%E9%98%9F%E7%A7%A9%E5%BA%8F&sa=fyb_news&rsv_dl=fyb_news"
  },
  {
    "title": "故意关停电梯致女孩摔倒 男孩已道歉",
    "description": "近日，深圳某商场内一男孩无故按停电梯导致女孩摔倒受伤引关注。17日晚，在警方的介入下，按停电梯的男孩已找到，男孩家长诚恳...   近日，深圳某商场内一男孩无故按停电梯导致女孩摔倒受伤引关注。17日晚，在警方的介入下，按停电梯的男孩已找到，男孩家长诚恳致歉，双方达成和解。",
    "url": "https://www.baidu.com/s?wd=%E6%95%85%E6%84%8F%E5%85%B3%E5%81%9C%E7%94%B5%E6%A2%AF%E8%87%B4%E5%A5%B3%E5%AD%A9%E6%91%94%E5%80%92+%E7%94%B7%E5%AD%A9%E5%B7%B2%E9%81%93%E6%AD%89&sa=fyb_news&rsv_dl=fyb_news"
  },
  {
    "title": "航拍青海山洪：房屋被冲毁 满眼泥浆",
    "description": "8月18日，青海西宁大通县境内突发山洪。航拍山洪现场：房屋被冲毁，满眼泥浆。   8月18日，青海西宁大通县境内突发山洪。航拍山洪现场：房屋被冲毁，满眼泥浆。",
    "url": "https://www.baidu.com/s?wd=%E8%88%AA%E6%8B%8D%E9%9D%92%E6%B5%B7%E5%B1%B1%E6%B4%AA%EF%BC%9A%E6%88%BF%E5%B1%8B%E8%A2%AB%E5%86%B2%E6%AF%81+%E6%BB%A1%E7%9C%BC%E6%B3%A5%E6%B5%86&sa=fyb_news&rsv_dl=fyb_news"
  },
  {
    "title": "海军航空兵夜训突遇外机：驱离！",
    "description": "东海某海域，东部战区海军航空兵夜训突遇外机，官兵立即转为一等战备，在空战机由训转战，前出查证空情。驱离目标后，飞行员在相...   东海某海域，东部战区海军航空兵夜训突遇外机，官兵立即转为一等战备，在空战机由训转战，前出查证空情。驱离目标后，飞行员在相应位置巡逻待战。",
    "url": "https://www.baidu.com/s?wd=%E6%B5%B7%E5%86%9B%E8%88%AA%E7%A9%BA%E5%85%B5%E5%A4%9C%E8%AE%AD%E7%AA%81%E9%81%87%E5%A4%96%E6%9C%BA%EF%BC%9A%E9%A9%B1%E7%A6%BB%EF%BC%81&sa=fyb_news&rsv_dl=fyb_news"
  },
  {
    "title": "上海经信委回应发函向四川要电",
    "description": "8月18日，上海经信委工作人员对发函向四川要电一事回应称：不是和民生抢电力，只是等工业用电恢复的时候，希望企业被优先考虑...   8月18日，上海经信委工作人员对发函向四川要电一事回应称：不是和民生抢电力，只是等工业用电恢复的时候，希望企业被优先考虑恢复。",
    "url": "https://www.baidu.com/s?wd=%E4%B8%8A%E6%B5%B7%E7%BB%8F%E4%BF%A1%E5%A7%94%E5%9B%9E%E5%BA%94%E5%8F%91%E5%87%BD%E5%90%91%E5%9B%9B%E5%B7%9D%E8%A6%81%E7%94%B5&sa=fyb_news&rsv_dl=fyb_news"
  },
  {
    "title": "吴京两次拒绝并躲开女嘉宾挽手",
    "description": "",
    "url": "https://www.baidu.com/s?wd=%E5%90%B4%E4%BA%AC%E4%B8%A4%E6%AC%A1%E6%8B%92%E7%BB%9D%E5%B9%B6%E8%BA%B2%E5%BC%80%E5%A5%B3%E5%98%89%E5%AE%BE%E6%8C%BD%E6%89%8B&sa=fyb_news&rsv_dl=fyb_news"
  },
  {
    "title": "#部分广播剧下架#",
    "description": "",
    "url": "https://www.baidu.com/s?wd=%23%E9%83%A8%E5%88%86%E5%B9%BF%E6%92%AD%E5%89%A7%E4%B8%8B%E6%9E%B6%23&sa=fyb_news&rsv_dl=fyb_news"
  },
  {
    "title": "小天才接受三地消协整改建议",
    "description": "近期，针对小天才T1儿童平板电脑可下载不良内容的问题，三地消协联合约谈了小天才公司。对三地消协提出的整改建议，小天才公司...   近期，针对小天才T1儿童平板电脑可下载不良内容的问题，三地消协联合约谈了小天才公司。对三地消协提出的整改建议，小天才公司表示全部接受。",
    "url": "https://www.baidu.com/s?wd=%E5%B0%8F%E5%A4%A9%E6%89%8D%E6%8E%A5%E5%8F%97%E4%B8%89%E5%9C%B0%E6%B6%88%E5%8D%8F%E6%95%B4%E6%94%B9%E5%BB%BA%E8%AE%AE&sa=fyb_news&rsv_dl=fyb_news"
  },
  {
    "title": "于冬金巧巧带娃庆祝博纳上市",
    "description": "",
    "url": "https://www.baidu.com/s?wd=%E4%BA%8E%E5%86%AC%E9%87%91%E5%B7%A7%E5%B7%A7%E5%B8%A6%E5%A8%83%E5%BA%86%E7%A5%9D%E5%8D%9A%E7%BA%B3%E4%B8%8A%E5%B8%82&sa=fyb_news&rsv_dl=fyb_news"
  }
]