[
  {
    "title": "中国探月未来已来",
    "description": "来自国家航天局消息，我国探月工程有新进展。探月与航天工程中心主任刘继忠在接受采访时表示：探月工程四期任务已获国家批复，目...   来自国家航天局消息，我国探月工程有新进展。探月与航天工程中心主任刘继忠在接受采访时表示：探月工程四期任务已获国家批复，目前进展顺利。",
    "url": "https://www.baidu.com/s?wd=%E4%B8%AD%E5%9B%BD%E6%8E%A2%E6%9C%88%E6%9C%AA%E6%9D%A5%E5%B7%B2%E6%9D%A5&sa=fyb_news&rsv_dl=fyb_news"
  },
  {
    "title": "乌方：乌军已突破至乌俄边境地区",
    "description": "据报道，乌克兰哈尔科夫地区军事行政长官奥列赫·辛耶胡博夫在社交媒体上宣布，在前线的部分区域，乌军人员已经抵达乌俄边境。   据报道，乌克兰哈尔科夫地区军事行政长官奥列赫·辛耶胡博夫在社交媒体上宣布，在前线的部分区域，乌军人员已经抵达乌俄边境。",
    "url": "https://www.baidu.com/s?wd=%E4%B9%8C%E6%96%B9%EF%BC%9A%E4%B9%8C%E5%86%9B%E5%B7%B2%E7%AA%81%E7%A0%B4%E8%87%B3%E4%B9%8C%E4%BF%84%E8%BE%B9%E5%A2%83%E5%9C%B0%E5%8C%BA&sa=fyb_news&rsv_dl=fyb_news"
  },
  {
    "title": "李泽楷为被砸舞者提供1千万港元",
    "description": "",
    "url": "https://www.baidu.com/s?wd=%E6%9D%8E%E6%B3%BD%E6%A5%B7%E4%B8%BA%E8%A2%AB%E7%A0%B8%E8%88%9E%E8%80%85%E6%8F%90%E4%BE%9B1%E5%8D%83%E4%B8%87%E6%B8%AF%E5%85%83&sa=fyb_news&rsv_dl=fyb_news"
  },
  {
    "title": "消防员为震区老乡手写感谢信",
    "description": "近日，四川泸定消防员在震区救援撤离时，将街道打扫得干干净净，并为老乡手写感谢信，表示：“我们和您们永远在一起”。   近日，四川泸定消防员在震区救援撤离时，将街道打扫得干干净净，并为老乡手写感谢信，表示：“我们和您们永远在一起”。",
    "url": "https://www.baidu.com/s?wd=%E6%B6%88%E9%98%B2%E5%91%98%E4%B8%BA%E9%9C%87%E5%8C%BA%E8%80%81%E4%B9%A1%E6%89%8B%E5%86%99%E6%84%9F%E8%B0%A2%E4%BF%A1&sa=fyb_news&rsv_dl=fyb_news"
  },
  {
    "title": "浦发银行被罚没超1200万",
    "description": "",
    "url": "https://www.baidu.com/s?wd=%E6%B5%A6%E5%8F%91%E9%93%B6%E8%A1%8C%E8%A2%AB%E7%BD%9A%E6%B2%A1%E8%B6%851200%E4%B8%87&sa=fyb_news&rsv_dl=fyb_news"
  },
  {
    "title": "36岁歌手傅松因口腔癌去世",
    "description": "2007年，傅松因参加湖南卫视《快乐男声》并获得长沙赛区20强正式出道。遗憾的是，9月10日傅松因口腔癌去世，年仅36岁...   2007年，傅松因参加湖南卫视《快乐男声》并获得长沙赛区20强正式出道。遗憾的是，9月10日傅松因口腔癌去世，年仅36岁。",
    "url": "https://www.baidu.com/s?wd=36%E5%B2%81%E6%AD%8C%E6%89%8B%E5%82%85%E6%9D%BE%E5%9B%A0%E5%8F%A3%E8%85%94%E7%99%8C%E5%8E%BB%E4%B8%96&sa=fyb_news&rsv_dl=fyb_news"
  },
  {
    "title": "恒大：38个未复工项目9月30日前复工",
    "description": "",
    "url": "https://www.baidu.com/s?wd=%E6%81%92%E5%A4%A7%EF%BC%9A38%E4%B8%AA%E6%9C%AA%E5%A4%8D%E5%B7%A5%E9%A1%B9%E7%9B%AE9%E6%9C%8830%E6%97%A5%E5%89%8D%E5%A4%8D%E5%B7%A5&sa=fyb_news&rsv_dl=fyb_news"
  },
  {
    "title": "老人赶集卖的鸭被闷死 路人纷纷买下",
    "description": "",
    "url": "https://www.baidu.com/s?wd=%E8%80%81%E4%BA%BA%E8%B5%B6%E9%9B%86%E5%8D%96%E7%9A%84%E9%B8%AD%E8%A2%AB%E9%97%B7%E6%AD%BB+%E8%B7%AF%E4%BA%BA%E7%BA%B7%E7%BA%B7%E4%B9%B0%E4%B8%8B&sa=fyb_news&rsv_dl=fyb_news"
  },
  {
    "title": "渔民捕获一条50多公斤野生中华鲟",
    "description": "",
    "url": "https://www.baidu.com/s?wd=%E6%B8%94%E6%B0%91%E6%8D%95%E8%8E%B7%E4%B8%80%E6%9D%A150%E5%A4%9A%E5%85%AC%E6%96%A4%E9%87%8E%E7%94%9F%E4%B8%AD%E5%8D%8E%E9%B2%9F&sa=fyb_news&rsv_dl=fyb_news"
  },
  {
    "title": "不明国籍渔船靠近 南沙守礁官兵驱离",
    "description": "南沙美济礁附近海域，一艘不明国籍渔船悄然抵近。雷达战位第一时间捕捉到信号，官兵对目标喊话驱离，阻止了目标行动，成功处置特...   南沙美济礁附近海域，一艘不明国籍渔船悄然抵近。雷达战位第一时间捕捉到信号，官兵对目标喊话驱离，阻止了目标行动，成功处置特情。",
    "url": "https://www.baidu.com/s?wd=%E4%B8%8D%E6%98%8E%E5%9B%BD%E7%B1%8D%E6%B8%94%E8%88%B9%E9%9D%A0%E8%BF%91+%E5%8D%97%E6%B2%99%E5%AE%88%E7%A4%81%E5%AE%98%E5%85%B5%E9%A9%B1%E7%A6%BB&sa=fyb_news&rsv_dl=fyb_news"
  },
  {
    "title": "外籍男子骚扰女性被拘7日限期出境",
    "description": "",
    "url": "https://www.baidu.com/s?wd=%E5%A4%96%E7%B1%8D%E7%94%B7%E5%AD%90%E9%AA%9A%E6%89%B0%E5%A5%B3%E6%80%A7%E8%A2%AB%E6%8B%987%E6%97%A5%E9%99%90%E6%9C%9F%E5%87%BA%E5%A2%83&sa=fyb_news&rsv_dl=fyb_news"
  },
  {
    "title": "偶像的黄昏：从吴亦凡到李易峰",
    "description": "",
    "url": "https://www.baidu.com/s?wd=%E5%81%B6%E5%83%8F%E7%9A%84%E9%BB%84%E6%98%8F%EF%BC%9A%E4%BB%8E%E5%90%B4%E4%BA%A6%E5%87%A1%E5%88%B0%E6%9D%8E%E6%98%93%E5%B3%B0&sa=fyb_news&rsv_dl=fyb_news"
  },
  {
    "title": "人民网：李易峰的粉丝该醒醒了",
    "description": "",
    "url": "https://www.baidu.com/s?wd=%E4%BA%BA%E6%B0%91%E7%BD%91%EF%BC%9A%E6%9D%8E%E6%98%93%E5%B3%B0%E7%9A%84%E7%B2%89%E4%B8%9D%E8%AF%A5%E9%86%92%E9%86%92%E4%BA%86&sa=fyb_news&rsv_dl=fyb_news"
  },
  {
    "title": "中国视协评李易峰事件：影响恶劣",
    "description": "近日，演员李易峰因嫖娼被北京警方依法行拘一事引起社会舆论热议。中国视协对此评论称：影响恶劣，广大电视艺术工作者应把崇德尚...   近日，演员李易峰因嫖娼被北京警方依法行拘一事引起社会舆论热议。中国视协对此评论称：影响恶劣，广大电视艺术工作者应把崇德尚艺作为一生的功课。",
    "url": "https://www.baidu.com/s?wd=%E4%B8%AD%E5%9B%BD%E8%A7%86%E5%8D%8F%E8%AF%84%E6%9D%8E%E6%98%93%E5%B3%B0%E4%BA%8B%E4%BB%B6%EF%BC%9A%E5%BD%B1%E5%93%8D%E6%81%B6%E5%8A%A3&sa=fyb_news&rsv_dl=fyb_news"
  },
  {
    "title": "60岁房东给21岁女租客发不雅视频",
    "description": "",
    "url": "https://www.baidu.com/s?wd=60%E5%B2%81%E6%88%BF%E4%B8%9C%E7%BB%9921%E5%B2%81%E5%A5%B3%E7%A7%9F%E5%AE%A2%E5%8F%91%E4%B8%8D%E9%9B%85%E8%A7%86%E9%A2%91&sa=fyb_news&rsv_dl=fyb_news"
  },
  {
    "title": "猫咪趁主人睡觉开闸放水淹了家",
    "description": "",
    "url": "https://www.baidu.com/s?wd=%E7%8C%AB%E5%92%AA%E8%B6%81%E4%B8%BB%E4%BA%BA%E7%9D%A1%E8%A7%89%E5%BC%80%E9%97%B8%E6%94%BE%E6%B0%B4%E6%B7%B9%E4%BA%86%E5%AE%B6&sa=fyb_news&rsv_dl=fyb_news"
  },
  {
    "title": "官方回应餐厅里老鼠在包子旁理毛",
    "description": "",
    "url": "https://www.baidu.com/s?wd=%E5%AE%98%E6%96%B9%E5%9B%9E%E5%BA%94%E9%A4%90%E5%8E%85%E9%87%8C%E8%80%81%E9%BC%A0%E5%9C%A8%E5%8C%85%E5%AD%90%E6%97%81%E7%90%86%E6%AF%9B&sa=fyb_news&rsv_dl=fyb_news"
  },
  {
    "title": "剧组在学校拍戏 砸学生无人机",
    "description": "近日，有网友爆料《偷偷藏不住》剧组在取景学校内“霸道专行”，工作人员砸坏学生无人机，还影响到在校学生们的正常生活。   近日，有网友爆料《偷偷藏不住》剧组在取景学校内“霸道专行”，工作人员砸坏学生无人机，还影响到在校学生们的正常生活。",
    "url": "https://www.baidu.com/s?wd=%E5%89%A7%E7%BB%84%E5%9C%A8%E5%AD%A6%E6%A0%A1%E6%8B%8D%E6%88%8F+%E7%A0%B8%E5%AD%A6%E7%94%9F%E6%97%A0%E4%BA%BA%E6%9C%BA&sa=fyb_news&rsv_dl=fyb_news"
  },
  {
    "title": "三男孩跪楼道里饮料代酒桃园结义",
    "description": "9月11日，山东青岛三个男孩在楼梯口端着饮料跪在一篮球前进行“桃园三结义”。目击者称，感觉很可爱。   9月11日，山东青岛三个男孩在楼梯口端着饮料跪在一篮球前进行“桃园三结义”。目击者称，感觉很可爱。",
    "url": "https://www.baidu.com/s?wd=%E4%B8%89%E7%94%B7%E5%AD%A9%E8%B7%AA%E6%A5%BC%E9%81%93%E9%87%8C%E9%A5%AE%E6%96%99%E4%BB%A3%E9%85%92%E6%A1%83%E5%9B%AD%E7%BB%93%E4%B9%89&sa=fyb_news&rsv_dl=fyb_news"
  },
  {
    "title": "当事医生回应莲子壳诊断为疑似肿瘤",
    "description": "近日，一家长反映孩子上颚出现黑色肿块，被湘雅医院医生初步诊断疑似肿瘤，但到另一家医院就诊时发现肿块只是莲子壳。对此，当事...   近日，一家长反映孩子上颚出现黑色肿块，被湘雅医院医生初步诊断疑似肿瘤，但到另一家医院就诊时发现肿块只是莲子壳。对此，当事医生作出回应。",
    "url": "https://www.baidu.com/s?wd=%E5%BD%93%E4%BA%8B%E5%8C%BB%E7%94%9F%E5%9B%9E%E5%BA%94%E8%8E%B2%E5%AD%90%E5%A3%B3%E8%AF%8A%E6%96%AD%E4%B8%BA%E7%96%91%E4%BC%BC%E8%82%BF%E7%98%A4&sa=fyb_news&rsv_dl=fyb_news"
  },
  {
    "title": "全体同意的8万班费为何引质疑",
    "description": "近日，有网友称孩子所在班级收取8万班费。对此，铜陵市政府办公室回应：此费用征得全体家长同意。那么，既然征得全体家长同意，...   近日，有网友称孩子所在班级收取8万班费。对此，铜陵市政府办公室回应：此费用征得全体家长同意。那么，既然征得全体家长同意，为何还会有家长质疑呢？",
    "url": "https://www.baidu.com/s?wd=%E5%85%A8%E4%BD%93%E5%90%8C%E6%84%8F%E7%9A%848%E4%B8%87%E7%8F%AD%E8%B4%B9%E4%B8%BA%E4%BD%95%E5%BC%95%E8%B4%A8%E7%96%91&sa=fyb_news&rsv_dl=fyb_news"
  },
  {
    "title": "四川现国内未有过的奥密克戎变异株",
    "description": "9月11日，四川内江召开疫情防控发布会。会上介绍，内江市疾控中心发现奥密克戎病毒变异株存在两个位点的变异，未在我国的基因...   9月11日，四川内江召开疫情防控发布会。会上介绍，内江市疾控中心发现奥密克戎病毒变异株存在两个位点的变异，未在我国的基因测序数据库中。",
    "url": "https://www.baidu.com/s?wd=%E5%9B%9B%E5%B7%9D%E7%8E%B0%E5%9B%BD%E5%86%85%E6%9C%AA%E6%9C%89%E8%BF%87%E7%9A%84%E5%A5%A5%E5%AF%86%E5%85%8B%E6%88%8E%E5%8F%98%E5%BC%82%E6%A0%AA&sa=fyb_news&rsv_dl=fyb_news"
  },
  {
    "title": "高校食堂做黑暗料理西红柿炒月饼",
    "description": "",
    "url": "https://www.baidu.com/s?wd=%E9%AB%98%E6%A0%A1%E9%A3%9F%E5%A0%82%E5%81%9A%E9%BB%91%E6%9A%97%E6%96%99%E7%90%86%E8%A5%BF%E7%BA%A2%E6%9F%BF%E7%82%92%E6%9C%88%E9%A5%BC&sa=fyb_news&rsv_dl=fyb_news"
  },
  {
    "title": "中国财政收入承压明显 如何应对",
    "description": "",
    "url": "https://www.baidu.com/s?wd=%E4%B8%AD%E5%9B%BD%E8%B4%A2%E6%94%BF%E6%94%B6%E5%85%A5%E6%89%BF%E5%8E%8B%E6%98%8E%E6%98%BE+%E5%A6%82%E4%BD%95%E5%BA%94%E5%AF%B9&sa=fyb_news&rsv_dl=fyb_news"
  },
  {
    "title": "央行定调数字人民币",
    "description": "",
    "url": "https://www.baidu.com/s?wd=%E5%A4%AE%E8%A1%8C%E5%AE%9A%E8%B0%83%E6%95%B0%E5%AD%97%E4%BA%BA%E6%B0%91%E5%B8%81&sa=fyb_news&rsv_dl=fyb_news"
  },
  {
    "title": "“17岁少女产子案”二审改判",
    "description": "",
    "url": "https://www.baidu.com/s?wd=%E2%80%9C17%E5%B2%81%E5%B0%91%E5%A5%B3%E4%BA%A7%E5%AD%90%E6%A1%88%E2%80%9D%E4%BA%8C%E5%AE%A1%E6%94%B9%E5%88%A4&sa=fyb_news&rsv_dl=fyb_news"
  },
  {
    "title": "多人悬崖边踩巨石用力摇晃",
    "description": "11日，贵州黔南。有多人站在悬崖边一块松动的巨石上使劲晃动，引发热议。据了解，巨石属自然景观，目前已是当地网红打卡点，经...   11日，贵州黔南。有多人站在悬崖边一块松动的巨石上使劲晃动，引发热议。据了解，巨石属自然景观，目前已是当地网红打卡点，经常有人站在上面摇晃。",
    "url": "https://www.baidu.com/s?wd=%E5%A4%9A%E4%BA%BA%E6%82%AC%E5%B4%96%E8%BE%B9%E8%B8%A9%E5%B7%A8%E7%9F%B3%E7%94%A8%E5%8A%9B%E6%91%87%E6%99%83&sa=fyb_news&rsv_dl=fyb_news"
  },
  {
    "title": "车臣领导人猛批俄军战略失误",
    "description": "当地时间11日，车臣领导人卡德罗夫在社交平台发布长达11分钟的语音批评俄罗斯军队的表现，并表示如果再不改变战略，必要时将...   当地时间11日，车臣领导人卡德罗夫在社交平台发布长达11分钟的语音批评俄罗斯军队的表现，并表示如果再不改变战略，必要时将去找普京谈谈。",
    "url": "https://www.baidu.com/s?wd=%E8%BD%A6%E8%87%A3%E9%A2%86%E5%AF%BC%E4%BA%BA%E7%8C%9B%E6%89%B9%E4%BF%84%E5%86%9B%E6%88%98%E7%95%A5%E5%A4%B1%E8%AF%AF&sa=fyb_news&rsv_dl=fyb_news"
  },
  {
    "title": "985毕业生大量涌入县城",
    "description": "近年来，985毕业生大量涌入县城。据《2022年大学生就业报告》显示，毕业生企业就业率呈下降趋势，选择考研、考公、考编等...   近年来，985毕业生大量涌入县城。据《2022年大学生就业报告》显示，毕业生企业就业率呈下降趋势，选择考研、考公、考编等途径的毕业生越来越多。",
    "url": "https://www.baidu.com/s?wd=985%E6%AF%95%E4%B8%9A%E7%94%9F%E5%A4%A7%E9%87%8F%E6%B6%8C%E5%85%A5%E5%8E%BF%E5%9F%8E&sa=fyb_news&rsv_dl=fyb_news"
  },
  {
    "title": "俄军解释从乌多地撤军原因",
    "description": "近日，俄军从乌多地撤军引发关注。据悉，此次俄军撤军正值乌克兰发动大规模攻势之际。对此，俄军回应是为了重组军队，增强顿涅茨...   近日，俄军从乌多地撤军引发关注。据悉，此次俄军撤军正值乌克兰发动大规模攻势之际。对此，俄军回应是为了重组军队，增强顿涅茨克方向的军事行动。",
    "url": "https://www.baidu.com/s?wd=%E4%BF%84%E5%86%9B%E8%A7%A3%E9%87%8A%E4%BB%8E%E4%B9%8C%E5%A4%9A%E5%9C%B0%E6%92%A4%E5%86%9B%E5%8E%9F%E5%9B%A0&sa=fyb_news&rsv_dl=fyb_news"
  },
  {
    "title": "白露过后为何多地仍高温不退",
    "description": "9月7日“白露”节气过后，多地仍然高温不退。12日，据中国天气网气温排行榜显示，当日10时至15时高温排行前十名的地区气...   9月7日“白露”节气过后，多地仍然高温不退。12日，据中国天气网气温排行榜显示，当日10时至15时高温排行前十名的地区气温均超过37.3℃。",
    "url": "https://www.baidu.com/s?wd=%E7%99%BD%E9%9C%B2%E8%BF%87%E5%90%8E%E4%B8%BA%E4%BD%95%E5%A4%9A%E5%9C%B0%E4%BB%8D%E9%AB%98%E6%B8%A9%E4%B8%8D%E9%80%80&sa=fyb_news&rsv_dl=fyb_news"
  },
  {
    "title": "王岐山前往英国驻华使馆吊唁英女王",
    "description": "9月12日，国家副主席王岐山前往英国驻华使馆，吊唁英国女王伊丽莎白二世逝世。   9月12日，国家副主席王岐山前往英国驻华使馆，吊唁英国女王伊丽莎白二世逝世。",
    "url": "https://www.baidu.com/s?wd=%E7%8E%8B%E5%B2%90%E5%B1%B1%E5%89%8D%E5%BE%80%E8%8B%B1%E5%9B%BD%E9%A9%BB%E5%8D%8E%E4%BD%BF%E9%A6%86%E5%90%8A%E5%94%81%E8%8B%B1%E5%A5%B3%E7%8E%8B&sa=fyb_news&rsv_dl=fyb_news"
  },
  {
    "title": "印度暂退出印太经济框架贸易谈判",
    "description": "日前，印太经济框架（IPEF）结束了为期两天的首轮线下部长级会谈。印度在会后以“暂时看不到好处”为由，宣布暂时退出该框架...   日前，印太经济框架（IPEF）结束了为期两天的首轮线下部长级会谈。印度在会后以“暂时看不到好处”为由，宣布暂时退出该框架贸易领域的谈判。",
    "url": "https://www.baidu.com/s?wd=%E5%8D%B0%E5%BA%A6%E6%9A%82%E9%80%80%E5%87%BA%E5%8D%B0%E5%A4%AA%E7%BB%8F%E6%B5%8E%E6%A1%86%E6%9E%B6%E8%B4%B8%E6%98%93%E8%B0%88%E5%88%A4&sa=fyb_news&rsv_dl=fyb_news"
  },
  {
    "title": "保安毒死11只宠物狗获刑3年",
    "description": "",
    "url": "https://www.baidu.com/s?wd=%E4%BF%9D%E5%AE%89%E6%AF%92%E6%AD%BB11%E5%8F%AA%E5%AE%A0%E7%89%A9%E7%8B%97%E8%8E%B7%E5%88%913%E5%B9%B4&sa=fyb_news&rsv_dl=fyb_news"
  },
  {
    "title": "台风“梅花”或直穿上海",
    "description": "",
    "url": "https://www.baidu.com/s?wd=%E5%8F%B0%E9%A3%8E%E2%80%9C%E6%A2%85%E8%8A%B1%E2%80%9D%E6%88%96%E7%9B%B4%E7%A9%BF%E4%B8%8A%E6%B5%B7&sa=fyb_news&rsv_dl=fyb_news"
  },
  {
    "title": "欧洲多国物价飙升引发街头抗议",
    "description": "当地时间10日，奥地利首都维也纳爆发抗议，数千人走上街头反对不断飙升的生活成本，还有民众谴责奥地利政府及其“全球主义议程...   当地时间10日，奥地利首都维也纳爆发抗议，数千人走上街头反对不断飙升的生活成本，还有民众谴责奥地利政府及其“全球主义议程”。",
    "url": "https://www.baidu.com/s?wd=%E6%AC%A7%E6%B4%B2%E5%A4%9A%E5%9B%BD%E7%89%A9%E4%BB%B7%E9%A3%99%E5%8D%87%E5%BC%95%E5%8F%91%E8%A1%97%E5%A4%B4%E6%8A%97%E8%AE%AE&sa=fyb_news&rsv_dl=fyb_news"
  },
  {
    "title": "中秋假期国内游7340.9万人次",
    "description": "",
    "url": "https://www.baidu.com/s?wd=%E4%B8%AD%E7%A7%8B%E5%81%87%E6%9C%9F%E5%9B%BD%E5%86%85%E6%B8%B87340.9%E4%B8%87%E4%BA%BA%E6%AC%A1&sa=fyb_news&rsv_dl=fyb_news"
  },
  {
    "title": "俄乌攻守之势发生逆转？",
    "description": "乌克兰表示，自9月初以来，已有3000多平方公里的土地回归乌克兰控制。西方媒体称，“这是俄乌冲突爆发以来，乌军取得的最辉...   乌克兰表示，自9月初以来，已有3000多平方公里的土地回归乌克兰控制。西方媒体称，“这是俄乌冲突爆发以来，乌军取得的最辉煌成就。",
    "url": "https://www.baidu.com/s?wd=%E4%BF%84%E4%B9%8C%E6%94%BB%E5%AE%88%E4%B9%8B%E5%8A%BF%E5%8F%91%E7%94%9F%E9%80%86%E8%BD%AC%EF%BC%9F&sa=fyb_news&rsv_dl=fyb_news"
  },
  {
    "title": "希拉里称美国枪支暴力已失控",
    "description": "",
    "url": "https://www.baidu.com/s?wd=%E5%B8%8C%E6%8B%89%E9%87%8C%E7%A7%B0%E7%BE%8E%E5%9B%BD%E6%9E%AA%E6%94%AF%E6%9A%B4%E5%8A%9B%E5%B7%B2%E5%A4%B1%E6%8E%A7&sa=fyb_news&rsv_dl=fyb_news"
  },
  {
    "title": "受台风“梅花”影响 上海已降雨",
    "description": "据上海气象部门介绍，12-13日受台风“梅花”北侧倒槽影响，上海有强降水过程；14-15日受台风直接影响，上海有明显风雨...   据上海气象部门介绍，12-13日受台风“梅花”北侧倒槽影响，上海有强降水过程；14-15日受台风直接影响，上海有明显风雨过程。",
    "url": "https://www.baidu.com/s?wd=%E5%8F%97%E5%8F%B0%E9%A3%8E%E2%80%9C%E6%A2%85%E8%8A%B1%E2%80%9D%E5%BD%B1%E5%93%8D+%E4%B8%8A%E6%B5%B7%E5%B7%B2%E9%99%8D%E9%9B%A8&sa=fyb_news&rsv_dl=fyb_news"
  },
  {
    "title": "贵阳多名官员因防疫不力被通报",
    "description": "贵阳市疫情防控现场处置省市联动指挥部9月12日通报了疫情发生以来，履职不到位、失察失责，导致疫情外溢、扩散的多名官员。   贵阳市疫情防控现场处置省市联动指挥部9月12日通报了疫情发生以来，履职不到位、失察失责，导致疫情外溢、扩散的多名官员。",
    "url": "https://www.baidu.com/s?wd=%E8%B4%B5%E9%98%B3%E5%A4%9A%E5%90%8D%E5%AE%98%E5%91%98%E5%9B%A0%E9%98%B2%E7%96%AB%E4%B8%8D%E5%8A%9B%E8%A2%AB%E9%80%9A%E6%8A%A5&sa=fyb_news&rsv_dl=fyb_news"
  },
  {
    "title": "官方辟谣山东集中隔离人员住羊圈",
    "description": "",
    "url": "https://www.baidu.com/s?wd=%E5%AE%98%E6%96%B9%E8%BE%9F%E8%B0%A3%E5%B1%B1%E4%B8%9C%E9%9B%86%E4%B8%AD%E9%9A%94%E7%A6%BB%E4%BA%BA%E5%91%98%E4%BD%8F%E7%BE%8A%E5%9C%88&sa=fyb_news&rsv_dl=fyb_news"
  },
  {
    "title": "良品铺子月饼被曝吃出塑料",
    "description": "9月11日，湖北一女子称在外卖平台购买良品铺子的月饼，刚吃第一口就吃出了塑料纸。店家回应，可能是在制作过程中原料带入，已...   9月11日，湖北一女子称在外卖平台购买良品铺子的月饼，刚吃第一口就吃出了塑料纸。店家回应，可能是在制作过程中原料带入，已和消费者协商解决。",
    "url": "https://www.baidu.com/s?wd=%E8%89%AF%E5%93%81%E9%93%BA%E5%AD%90%E6%9C%88%E9%A5%BC%E8%A2%AB%E6%9B%9D%E5%90%83%E5%87%BA%E5%A1%91%E6%96%99&sa=fyb_news&rsv_dl=fyb_news"
  },
  {
    "title": "多地调整常态化核酸检测频次",
    "description": "9月以来，全国29个省份报告了新增本土感染者，各地仍存在聚集行疫情风险。近日多地根据疫情形势，调整了常态化核酸检测频次。   9月以来，全国29个省份报告了新增本土感染者，各地仍存在聚集行疫情风险。近日多地根据疫情形势，调整了常态化核酸检测频次。",
    "url": "https://www.baidu.com/s?wd=%E5%A4%9A%E5%9C%B0%E8%B0%83%E6%95%B4%E5%B8%B8%E6%80%81%E5%8C%96%E6%A0%B8%E9%85%B8%E6%A3%80%E6%B5%8B%E9%A2%91%E6%AC%A1&sa=fyb_news&rsv_dl=fyb_news"
  },
  {
    "title": "考研复试保过班最贵要花近10万",
    "description": "",
    "url": "https://www.baidu.com/s?wd=%E8%80%83%E7%A0%94%E5%A4%8D%E8%AF%95%E4%BF%9D%E8%BF%87%E7%8F%AD%E6%9C%80%E8%B4%B5%E8%A6%81%E8%8A%B1%E8%BF%9110%E4%B8%87&sa=fyb_news&rsv_dl=fyb_news"
  },
  {
    "title": "1卢布等于1元人民币是误读",
    "description": "网传“1俄罗斯卢布等于1元人民币”的说法是一种误读，所谓“卢布和人民币比例为50:50”，指的是同时使用人民币和俄罗斯卢...   网传“1俄罗斯卢布等于1元人民币”的说法是一种误读，所谓“卢布和人民币比例为50:50”，指的是同时使用人民币和俄罗斯卢布两种货币，比例各占50%。",
    "url": "https://www.baidu.com/s?wd=1%E5%8D%A2%E5%B8%83%E7%AD%89%E4%BA%8E1%E5%85%83%E4%BA%BA%E6%B0%91%E5%B8%81%E6%98%AF%E8%AF%AF%E8%AF%BB&sa=fyb_news&rsv_dl=fyb_news"
  },
  {
    "title": "俄军是在溃退还是在憋大招？",
    "description": "",
    "url": "https://www.baidu.com/s?wd=%E4%BF%84%E5%86%9B%E6%98%AF%E5%9C%A8%E6%BA%83%E9%80%80%E8%BF%98%E6%98%AF%E5%9C%A8%E6%86%8B%E5%A4%A7%E6%8B%9B%EF%BC%9F&sa=fyb_news&rsv_dl=fyb_news"
  },
  {
    "title": "嫦娥五号月壤中发现存在高含量水",
    "description": "近日，中国科学院地球化学研究所科研团队针对嫦娥五号月壤样品开展了研究，发现月壤矿物中存在高含量的水，证实了月表矿物是水的...   近日，中国科学院地球化学研究所科研团队针对嫦娥五号月壤样品开展了研究，发现月壤矿物中存在高含量的水，证实了月表矿物是水的重要“储库”。",
    "url": "https://www.baidu.com/s?wd=%E5%AB%A6%E5%A8%A5%E4%BA%94%E5%8F%B7%E6%9C%88%E5%A3%A4%E4%B8%AD%E5%8F%91%E7%8E%B0%E5%AD%98%E5%9C%A8%E9%AB%98%E5%90%AB%E9%87%8F%E6%B0%B4&sa=fyb_news&rsv_dl=fyb_news"
  },
  {
    "title": "胡锡进谈俄军哈尔科夫地区失利",
    "description": "",
    "url": "https://www.baidu.com/s?wd=%E8%83%A1%E9%94%A1%E8%BF%9B%E8%B0%88%E4%BF%84%E5%86%9B%E5%93%88%E5%B0%94%E7%A7%91%E5%A4%AB%E5%9C%B0%E5%8C%BA%E5%A4%B1%E5%88%A9&sa=fyb_news&rsv_dl=fyb_news"
  },
  {
    "title": "1人核检复核阳性 三河全域静默管理",
    "description": "9月13日，三河市1名北京协查密接人员核酸检测复核阳性。三河市决定于9月13日6时起，对全域开展为期4天的静默管理，并开...   9月13日，三河市1名北京协查密接人员核酸检测复核阳性。三河市决定于9月13日6时起，对全域开展为期4天的静默管理，并开展4轮全员核酸检测。",
    "url": "https://www.baidu.com/s?wd=1%E4%BA%BA%E6%A0%B8%E6%A3%80%E5%A4%8D%E6%A0%B8%E9%98%B3%E6%80%A7+%E4%B8%89%E6%B2%B3%E5%85%A8%E5%9F%9F%E9%9D%99%E9%BB%98%E7%AE%A1%E7%90%86&sa=fyb_news&rsv_dl=fyb_news"
  },
  {
    "title": "张瀚新剧里疑对女演员咸猪手",
    "description": "9月12日，张翰因在新剧《东八区的先生》最新一集中疑对女主角王晓晨有咸猪手的举动，再次引发争议。   9月12日，张翰因在新剧《东八区的先生》最新一集中疑对女主角王晓晨有咸猪手的举动，再次引发争议。",
    "url": "https://www.baidu.com/s?wd=%E5%BC%A0%E7%80%9A%E6%96%B0%E5%89%A7%E9%87%8C%E7%96%91%E5%AF%B9%E5%A5%B3%E6%BC%94%E5%91%98%E5%92%B8%E7%8C%AA%E6%89%8B&sa=fyb_news&rsv_dl=fyb_news"
  },
  {
    "title": "警方连续3年在观潮时抓住逃犯",
    "description": "",
    "url": "https://www.baidu.com/s?wd=%E8%AD%A6%E6%96%B9%E8%BF%9E%E7%BB%AD3%E5%B9%B4%E5%9C%A8%E8%A7%82%E6%BD%AE%E6%97%B6%E6%8A%93%E4%BD%8F%E9%80%83%E7%8A%AF&sa=fyb_news&rsv_dl=fyb_news"
  },
  {
    "title": "泽连斯基：已夺回6000平方公里土地",
    "description": "乌克兰国家通讯社9月12日报道称，乌克兰总统泽连斯基表示，乌军已夺回6000平方公里土地。   乌克兰国家通讯社9月12日报道称，乌克兰总统泽连斯基表示，乌军已夺回6000平方公里土地。",
    "url": "https://www.baidu.com/s?wd=%E6%B3%BD%E8%BF%9E%E6%96%AF%E5%9F%BA%EF%BC%9A%E5%B7%B2%E5%A4%BA%E5%9B%9E6000%E5%B9%B3%E6%96%B9%E5%85%AC%E9%87%8C%E5%9C%9F%E5%9C%B0&sa=fyb_news&rsv_dl=fyb_news"
  },
  {
    "title": "31省份昨日新增本土188+727",
    "description": "",
    "url": "https://www.baidu.com/s?wd=31%E7%9C%81%E4%BB%BD%E6%98%A8%E6%97%A5%E6%96%B0%E5%A2%9E%E6%9C%AC%E5%9C%9F188%2B727&sa=fyb_news&rsv_dl=fyb_news"
  },
  {
    "title": "女子和她的76只羊消失在了地震中",
    "description": "9月5日12时52分，四川省甘孜州泸定县发生6.8级地震。肖华平的妻子和家里的76只羊都消失在了地震中。   9月5日12时52分，四川省甘孜州泸定县发生6.8级地震。肖华平的妻子和家里的76只羊都消失在了地震中。",
    "url": "https://www.baidu.com/s?wd=%E5%A5%B3%E5%AD%90%E5%92%8C%E5%A5%B9%E7%9A%8476%E5%8F%AA%E7%BE%8A%E6%B6%88%E5%A4%B1%E5%9C%A8%E4%BA%86%E5%9C%B0%E9%9C%87%E4%B8%AD&sa=fyb_news&rsv_dl=fyb_news"
  },
  {
    "title": "张翰新剧里疑对女演员咸猪手",
    "description": "",
    "url": "https://www.baidu.com/s?wd=%E5%BC%A0%E7%BF%B0%E6%96%B0%E5%89%A7%E9%87%8C%E7%96%91%E5%AF%B9%E5%A5%B3%E6%BC%94%E5%91%98%E5%92%B8%E7%8C%AA%E6%89%8B&sa=fyb_news&rsv_dl=fyb_news"
  },
  {
    "title": "一场脱口秀带火一支股票?公司回应",
    "description": "600759是ST洲际的股票代码，脱口秀演员House讲述自己投资该股票血亏的经历实现“炸场”。随后，ST洲际发布澄清公...   600759是ST洲际的股票代码，脱口秀演员House讲述自己投资该股票血亏的经历实现“炸场”。随后，ST洲际发布澄清公告称，请广大投资者理性投资，...",
    "url": "https://www.baidu.com/s?wd=%E4%B8%80%E5%9C%BA%E8%84%B1%E5%8F%A3%E7%A7%80%E5%B8%A6%E7%81%AB%E4%B8%80%E6%94%AF%E8%82%A1%E7%A5%A8%3F%E5%85%AC%E5%8F%B8%E5%9B%9E%E5%BA%94&sa=fyb_news&rsv_dl=fyb_news"
  },
  {
    "title": "泰国大象“失业”",
    "description": "",
    "url": "https://www.baidu.com/s?wd=%E6%B3%B0%E5%9B%BD%E5%A4%A7%E8%B1%A1%E2%80%9C%E5%A4%B1%E4%B8%9A%E2%80%9D&sa=fyb_news&rsv_dl=fyb_news"
  },
  {
    "title": "落马正厅被点名 曾高调宣布平安归来",
    "description": "12日，《中国纪检监察报》的刊文点名了原黑龙江省粮食局局长胡东胜。2013年中储粮黑龙江公司腐败窝案爆发，胡东胜被问话，...   12日，《中国纪检监察报》的刊文点名了原黑龙江省粮食局局长胡东胜。2013年中储粮黑龙江公司腐败窝案爆发，胡东胜被问话，后又高调 “平安归来”。",
    "url": "https://www.baidu.com/s?wd=%E8%90%BD%E9%A9%AC%E6%AD%A3%E5%8E%85%E8%A2%AB%E7%82%B9%E5%90%8D+%E6%9B%BE%E9%AB%98%E8%B0%83%E5%AE%A3%E5%B8%83%E5%B9%B3%E5%AE%89%E5%BD%92%E6%9D%A5&sa=fyb_news&rsv_dl=fyb_news"
  },
  {
    "title": "美国或扩大对中国出口芯片限制",
    "description": "",
    "url": "https://www.baidu.com/s?wd=%E7%BE%8E%E5%9B%BD%E6%88%96%E6%89%A9%E5%A4%A7%E5%AF%B9%E4%B8%AD%E5%9B%BD%E5%87%BA%E5%8F%A3%E8%8A%AF%E7%89%87%E9%99%90%E5%88%B6&sa=fyb_news&rsv_dl=fyb_news"
  },
  {
    "title": "杭州一KTV门口有人被打死？假的",
    "description": "",
    "url": "https://www.baidu.com/s?wd=%E6%9D%AD%E5%B7%9E%E4%B8%80KTV%E9%97%A8%E5%8F%A3%E6%9C%89%E4%BA%BA%E8%A2%AB%E6%89%93%E6%AD%BB%EF%BC%9F%E5%81%87%E7%9A%84&sa=fyb_news&rsv_dl=fyb_news"
  },
  {
    "title": "查尔斯三世兄妹4人为已故女王守夜",
    "description": "据英国天空新闻网消息，当地时间12日晚，英国国王查尔斯三世等王室成员在苏格兰爱丁堡圣吉尔斯大教堂，为已故女王伊丽莎白二世...   据英国天空新闻网消息，当地时间12日晚，英国国王查尔斯三世等王室成员在苏格兰爱丁堡圣吉尔斯大教堂，为已故女王伊丽莎白二世进行守夜。",
    "url": "https://www.baidu.com/s?wd=%E6%9F%A5%E5%B0%94%E6%96%AF%E4%B8%89%E4%B8%96%E5%85%84%E5%A6%B94%E4%BA%BA%E4%B8%BA%E5%B7%B2%E6%95%85%E5%A5%B3%E7%8E%8B%E5%AE%88%E5%A4%9C&sa=fyb_news&rsv_dl=fyb_news"
  },
  {
    "title": "脱口秀演员回应带火股票“600759”",
    "description": "",
    "url": "https://www.baidu.com/s?wd=%E8%84%B1%E5%8F%A3%E7%A7%80%E6%BC%94%E5%91%98%E5%9B%9E%E5%BA%94%E5%B8%A6%E7%81%AB%E8%82%A1%E7%A5%A8%E2%80%9C600759%E2%80%9D&sa=fyb_news&rsv_dl=fyb_news"
  },
  {
    "title": "前线“吃紧”之际 普京表态引人关注",
    "description": "西方媒体正大肆渲染俄军“溃败”，就在外界纷纷猜测俄方将在“前线”拿出的下一步动作时，普京在“后方”开会研究俄罗斯经济状况...   西方媒体正大肆渲染俄军“溃败”，就在外界纷纷猜测俄方将在“前线”拿出的下一步动作时，普京在“后方”开会研究俄罗斯经济状况，并给出积极信号。",
    "url": "https://www.baidu.com/s?wd=%E5%89%8D%E7%BA%BF%E2%80%9C%E5%90%83%E7%B4%A7%E2%80%9D%E4%B9%8B%E9%99%85+%E6%99%AE%E4%BA%AC%E8%A1%A8%E6%80%81%E5%BC%95%E4%BA%BA%E5%85%B3%E6%B3%A8&sa=fyb_news&rsv_dl=fyb_news"
  },
  {
    "title": "未来哪些工作岗位会是“铁饭碗”",
    "description": "",
    "url": "https://www.baidu.com/s?wd=%E6%9C%AA%E6%9D%A5%E5%93%AA%E4%BA%9B%E5%B7%A5%E4%BD%9C%E5%B2%97%E4%BD%8D%E4%BC%9A%E6%98%AF%E2%80%9C%E9%93%81%E9%A5%AD%E7%A2%97%E2%80%9D&sa=fyb_news&rsv_dl=fyb_news"
  },
  {
    "title": "张翰新剧《东八区的先生们》引争议",
    "description": "9月12日，张翰因在新剧《东八区的先生》最新一集中疑对女主角王晓晨有咸猪手的举动，再次引发争议。   9月12日，张翰因在新剧《东八区的先生》最新一集中疑对女主角王晓晨有咸猪手的举动，再次引发争议。",
    "url": "https://www.baidu.com/s?wd=%E5%BC%A0%E7%BF%B0%E6%96%B0%E5%89%A7%E3%80%8A%E4%B8%9C%E5%85%AB%E5%8C%BA%E7%9A%84%E5%85%88%E7%94%9F%E4%BB%AC%E3%80%8B%E5%BC%95%E4%BA%89%E8%AE%AE&sa=fyb_news&rsv_dl=fyb_news"
  },
  {
    "title": "最高检依法对王滨决定逮捕",
    "description": "日前，最高人民检察院依法以涉嫌受贿罪、隐瞒境外存款罪对王滨作出逮捕决定。该案正在进一步办理中。   日前，最高人民检察院依法以涉嫌受贿罪、隐瞒境外存款罪对王滨作出逮捕决定。该案正在进一步办理中。",
    "url": "https://www.baidu.com/s?wd=%E6%9C%80%E9%AB%98%E6%A3%80%E4%BE%9D%E6%B3%95%E5%AF%B9%E7%8E%8B%E6%BB%A8%E5%86%B3%E5%AE%9A%E9%80%AE%E6%8D%95&sa=fyb_news&rsv_dl=fyb_news"
  },
  {
    "title": "iPhone14ProMax成预售冠军",
    "description": "苹果分析师郭明錤9日发表最新iPhone14线下预购调查，调查显示，中国地区iPhone14 Pro系列占订单分配约为8...   苹果分析师郭明錤9日发表最新iPhone14线下预购调查，调查显示，中国地区iPhone14 Pro系列占订单分配约为85%，iPhone 14 P...",
    "url": "https://www.baidu.com/s?wd=iPhone14ProMax%E6%88%90%E9%A2%84%E5%94%AE%E5%86%A0%E5%86%9B&sa=fyb_news&rsv_dl=fyb_news"
  },
  {
    "title": "女子拖行李箱进厂被保安要求开箱",
    "description": "",
    "url": "https://www.baidu.com/s?wd=%E5%A5%B3%E5%AD%90%E6%8B%96%E8%A1%8C%E6%9D%8E%E7%AE%B1%E8%BF%9B%E5%8E%82%E8%A2%AB%E4%BF%9D%E5%AE%89%E8%A6%81%E6%B1%82%E5%BC%80%E7%AE%B1&sa=fyb_news&rsv_dl=fyb_news"
  },
  {
    "title": "日本机场引入地沟油燃料",
    "description": "",
    "url": "https://www.baidu.com/s?wd=%E6%97%A5%E6%9C%AC%E6%9C%BA%E5%9C%BA%E5%BC%95%E5%85%A5%E5%9C%B0%E6%B2%9F%E6%B2%B9%E7%87%83%E6%96%99&sa=fyb_news&rsv_dl=fyb_news"
  },
  {
    "title": "明星塌房险已出为何国内不敢承保",
    "description": "",
    "url": "https://www.baidu.com/s?wd=%E6%98%8E%E6%98%9F%E5%A1%8C%E6%88%BF%E9%99%A9%E5%B7%B2%E5%87%BA%E4%B8%BA%E4%BD%95%E5%9B%BD%E5%86%85%E4%B8%8D%E6%95%A2%E6%89%BF%E4%BF%9D&sa=fyb_news&rsv_dl=fyb_news"
  },
  {
    "title": "《亲爱的》唯一未找到孩子疑有线索",
    "description": "",
    "url": "https://www.baidu.com/s?wd=%E3%80%8A%E4%BA%B2%E7%88%B1%E7%9A%84%E3%80%8B%E5%94%AF%E4%B8%80%E6%9C%AA%E6%89%BE%E5%88%B0%E5%AD%A9%E5%AD%90%E7%96%91%E6%9C%89%E7%BA%BF%E7%B4%A2&sa=fyb_news&rsv_dl=fyb_news"
  },
  {
    "title": "拜登吐槽全球前25机场没有美国的",
    "description": "“我们到底是怎么了”？美国当地时间9月12日，波士顿洛根国际机场，拜登这样问。综合外媒报道，拜登当日在演讲中抱怨美国机场...   “我们到底是怎么了”？美国当地时间9月12日，波士顿洛根国际机场，拜登这样问。综合外媒报道，拜登当日在演讲中抱怨美国机场设施就要落后于竞争对手。",
    "url": "https://www.baidu.com/s?wd=%E6%8B%9C%E7%99%BB%E5%90%90%E6%A7%BD%E5%85%A8%E7%90%83%E5%89%8D25%E6%9C%BA%E5%9C%BA%E6%B2%A1%E6%9C%89%E7%BE%8E%E5%9B%BD%E7%9A%84&sa=fyb_news&rsv_dl=fyb_news"
  },
  {
    "title": "中国人寿原董事长王滨被逮捕",
    "description": "日前，最高人民检察院依法以涉嫌受贿罪、隐瞒境外存款罪对王滨作出逮捕决定。该案正在进一步办理中。   日前，最高人民检察院依法以涉嫌受贿罪、隐瞒境外存款罪对王滨作出逮捕决定。该案正在进一步办理中。",
    "url": "https://www.baidu.com/s?wd=%E4%B8%AD%E5%9B%BD%E4%BA%BA%E5%AF%BF%E5%8E%9F%E8%91%A3%E4%BA%8B%E9%95%BF%E7%8E%8B%E6%BB%A8%E8%A2%AB%E9%80%AE%E6%8D%95&sa=fyb_news&rsv_dl=fyb_news"
  },
  {
    "title": "台风“梅花”或登陆浙江沿海",
    "description": "据中央气象台消息，今年第12号台风“梅花”逐渐向浙江沿海靠近。预计台风将在14日夜间登陆或擦过浙江三门到舟山一带沿海。   据中央气象台消息，今年第12号台风“梅花”逐渐向浙江沿海靠近。预计台风将在14日夜间登陆或擦过浙江三门到舟山一带沿海。",
    "url": "https://www.baidu.com/s?wd=%E5%8F%B0%E9%A3%8E%E2%80%9C%E6%A2%85%E8%8A%B1%E2%80%9D%E6%88%96%E7%99%BB%E9%99%86%E6%B5%99%E6%B1%9F%E6%B2%BF%E6%B5%B7&sa=fyb_news&rsv_dl=fyb_news"
  },
  {
    "title": "顺丰寄丢20克黄金 保价8千只赔2千",
    "description": "近日，杭州萧山的小刘在顺丰下单同城急送寄20克黄金，特意进行了保价，保价金额8000元，不料2小时后，快递员打电话说黄金...   近日，杭州萧山的小刘在顺丰下单同城急送寄20克黄金，特意进行了保价，保价金额8000元，不料2小时后，快递员打电话说黄金丢了。顺丰客服称：赔付200...",
    "url": "https://www.baidu.com/s?wd=%E9%A1%BA%E4%B8%B0%E5%AF%84%E4%B8%A220%E5%85%8B%E9%BB%84%E9%87%91+%E4%BF%9D%E4%BB%B78%E5%8D%83%E5%8F%AA%E8%B5%942%E5%8D%83&sa=fyb_news&rsv_dl=fyb_news"
  },
  {
    "title": "多地出台稳楼市政策",
    "description": "",
    "url": "https://www.baidu.com/s?wd=%E5%A4%9A%E5%9C%B0%E5%87%BA%E5%8F%B0%E7%A8%B3%E6%A5%BC%E5%B8%82%E6%94%BF%E7%AD%96&sa=fyb_news&rsv_dl=fyb_news"
  },
  {
    "title": "张翰新剧《东八区的先生们》遭质疑",
    "description": "近日，由张翰、王晓晨、杜淳等人主演的都市生活轻喜剧《东八区的先生们》播出。剧中，张翰在与王晓晨演戏时，他的手放在女生身体...   近日，由张翰、王晓晨、杜淳等人主演的都市生活轻喜剧《东八区的先生们》播出。剧中，张翰在与王晓晨演戏时，他的手放在女生身体不合适的地方引争议。",
    "url": "https://www.baidu.com/s?wd=%E5%BC%A0%E7%BF%B0%E6%96%B0%E5%89%A7%E3%80%8A%E4%B8%9C%E5%85%AB%E5%8C%BA%E7%9A%84%E5%85%88%E7%94%9F%E4%BB%AC%E3%80%8B%E9%81%AD%E8%B4%A8%E7%96%91&sa=fyb_news&rsv_dl=fyb_news"
  },
  {
    "title": "阿塞拜疆和亚美尼亚边境发生冲突",
    "description": "",
    "url": "https://www.baidu.com/s?wd=%E9%98%BF%E5%A1%9E%E6%8B%9C%E7%96%86%E5%92%8C%E4%BA%9A%E7%BE%8E%E5%B0%BC%E4%BA%9A%E8%BE%B9%E5%A2%83%E5%8F%91%E7%94%9F%E5%86%B2%E7%AA%81&sa=fyb_news&rsv_dl=fyb_news"
  },
  {
    "title": "普京称去美元化进程不可避免",
    "description": "",
    "url": "https://www.baidu.com/s?wd=%E6%99%AE%E4%BA%AC%E7%A7%B0%E5%8E%BB%E7%BE%8E%E5%85%83%E5%8C%96%E8%BF%9B%E7%A8%8B%E4%B8%8D%E5%8F%AF%E9%81%BF%E5%85%8D&sa=fyb_news&rsv_dl=fyb_news"
  },
  {
    "title": "英国国王穿苏格兰裙为女王守夜",
    "description": "",
    "url": "https://www.baidu.com/s?wd=%E8%8B%B1%E5%9B%BD%E5%9B%BD%E7%8E%8B%E7%A9%BF%E8%8B%8F%E6%A0%BC%E5%85%B0%E8%A3%99%E4%B8%BA%E5%A5%B3%E7%8E%8B%E5%AE%88%E5%A4%9C&sa=fyb_news&rsv_dl=fyb_news"
  },
  {
    "title": "老人去世核酸报告仍更新？官方回应",
    "description": "9月12日，有网友发文称家中老人于8月去世，却发现老人的核酸报告还在不断更新。对此官方回应：经核实，是同名同姓弄错了，老...   9月12日，有网友发文称家中老人于8月去世，却发现老人的核酸报告还在不断更新。对此官方回应：经核实，是同名同姓弄错了，老人的核酸不会再更新。",
    "url": "https://www.baidu.com/s?wd=%E8%80%81%E4%BA%BA%E5%8E%BB%E4%B8%96%E6%A0%B8%E9%85%B8%E6%8A%A5%E5%91%8A%E4%BB%8D%E6%9B%B4%E6%96%B0%EF%BC%9F%E5%AE%98%E6%96%B9%E5%9B%9E%E5%BA%94&sa=fyb_news&rsv_dl=fyb_news"
  },
  {
    "title": "王一博方否认“嫖娼”传闻：已报案",
    "description": "",
    "url": "https://www.baidu.com/s?wd=%E7%8E%8B%E4%B8%80%E5%8D%9A%E6%96%B9%E5%90%A6%E8%AE%A4%E2%80%9C%E5%AB%96%E5%A8%BC%E2%80%9D%E4%BC%A0%E9%97%BB%EF%BC%9A%E5%B7%B2%E6%8A%A5%E6%A1%88&sa=fyb_news&rsv_dl=fyb_news"
  },
  {
    "title": "乌称用网络攻击瘫痪2400多个俄网站",
    "description": "乌克兰国家通讯社12日报道，乌克兰数字化转型部当天宣布，8月29日至9月11日，乌克兰方面通过网络攻击致使2400多个俄...   乌克兰国家通讯社12日报道，乌克兰数字化转型部当天宣布，8月29日至9月11日，乌克兰方面通过网络攻击致使2400多个俄罗斯网站瘫痪。",
    "url": "https://www.baidu.com/s?wd=%E4%B9%8C%E7%A7%B0%E7%94%A8%E7%BD%91%E7%BB%9C%E6%94%BB%E5%87%BB%E7%98%AB%E7%97%AA2400%E5%A4%9A%E4%B8%AA%E4%BF%84%E7%BD%91%E7%AB%99&sa=fyb_news&rsv_dl=fyb_news"
  },
  {
    "title": "潘粤明更新iOS16后打不开微信",
    "description": "",
    "url": "https://www.baidu.com/s?wd=%E6%BD%98%E7%B2%A4%E6%98%8E%E6%9B%B4%E6%96%B0iOS16%E5%90%8E%E6%89%93%E4%B8%8D%E5%BC%80%E5%BE%AE%E4%BF%A1&sa=fyb_news&rsv_dl=fyb_news"
  },
  {
    "title": "韩国保守团体与反日团体发生冲突",
    "description": "韩联社12日报道称，韩国保守团体与反日团体成员11日晚在首尔日本驻韩大使馆旧址前的“慰安妇”少女像附近，发生近4小时的冲...   韩联社12日报道称，韩国保守团体与反日团体成员11日晚在首尔日本驻韩大使馆旧址前的“慰安妇”少女像附近，发生近4小时的冲突。",
    "url": "https://www.baidu.com/s?wd=%E9%9F%A9%E5%9B%BD%E4%BF%9D%E5%AE%88%E5%9B%A2%E4%BD%93%E4%B8%8E%E5%8F%8D%E6%97%A5%E5%9B%A2%E4%BD%93%E5%8F%91%E7%94%9F%E5%86%B2%E7%AA%81&sa=fyb_news&rsv_dl=fyb_news"
  },
  {
    "title": "理想汽车总裁已套现超9000万",
    "description": "",
    "url": "https://www.baidu.com/s?wd=%E7%90%86%E6%83%B3%E6%B1%BD%E8%BD%A6%E6%80%BB%E8%A3%81%E5%B7%B2%E5%A5%97%E7%8E%B0%E8%B6%859000%E4%B8%87&sa=fyb_news&rsv_dl=fyb_news"
  },
  {
    "title": "成都有人在楼里养5头猪?物业回应",
    "description": "",
    "url": "https://www.baidu.com/s?wd=%E6%88%90%E9%83%BD%E6%9C%89%E4%BA%BA%E5%9C%A8%E6%A5%BC%E9%87%8C%E5%85%BB5%E5%A4%B4%E7%8C%AA%3F%E7%89%A9%E4%B8%9A%E5%9B%9E%E5%BA%94&sa=fyb_news&rsv_dl=fyb_news"
  },
  {
    "title": "勇救5人的蒋正全被评为烈士",
    "description": "",
    "url": "https://www.baidu.com/s?wd=%E5%8B%87%E6%95%915%E4%BA%BA%E7%9A%84%E8%92%8B%E6%AD%A3%E5%85%A8%E8%A2%AB%E8%AF%84%E4%B8%BA%E7%83%88%E5%A3%AB&sa=fyb_news&rsv_dl=fyb_news"
  },
  {
    "title": "15666666666靓号拍卖",
    "description": "",
    "url": "https://www.baidu.com/s?wd=15666666666%E9%9D%93%E5%8F%B7%E6%8B%8D%E5%8D%96&sa=fyb_news&rsv_dl=fyb_news"
  },
  {
    "title": "赞达亚获艾美奖最佳女主角",
    "description": "",
    "url": "https://www.baidu.com/s?wd=%E8%B5%9E%E8%BE%BE%E4%BA%9A%E8%8E%B7%E8%89%BE%E7%BE%8E%E5%A5%96%E6%9C%80%E4%BD%B3%E5%A5%B3%E4%B8%BB%E8%A7%92&sa=fyb_news&rsv_dl=fyb_news"
  },
  {
    "title": "st洲际开盘一字涨停",
    "description": "",
    "url": "https://www.baidu.com/s?wd=st%E6%B4%B2%E9%99%85%E5%BC%80%E7%9B%98%E4%B8%80%E5%AD%97%E6%B6%A8%E5%81%9C&sa=fyb_news&rsv_dl=fyb_news"
  },
  {
    "title": "普京：西方对俄“经济闪电战”无效",
    "description": "据塔斯社报道，俄罗斯总统普京12日在一个经济问题会议上表示，不友好国家对俄罗斯发起的“经济闪电战”策略没有奏效。   据塔斯社报道，俄罗斯总统普京12日在一个经济问题会议上表示，不友好国家对俄罗斯发起的“经济闪电战”策略没有奏效。",
    "url": "https://www.baidu.com/s?wd=%E6%99%AE%E4%BA%AC%EF%BC%9A%E8%A5%BF%E6%96%B9%E5%AF%B9%E4%BF%84%E2%80%9C%E7%BB%8F%E6%B5%8E%E9%97%AA%E7%94%B5%E6%88%98%E2%80%9D%E6%97%A0%E6%95%88&sa=fyb_news&rsv_dl=fyb_news"
  },
  {
    "title": "杜小华与疑似男孩DNA比对不匹配",
    "description": "《亲爱的》原型中唯一未找到孩子的父亲杜小华，与湖南常德安乡县一疑似男孩进行DNA比对。13日，鉴定结果已出，杜小华与疑似...   《亲爱的》原型中唯一未找到孩子的父亲杜小华，与湖南常德安乡县一疑似男孩进行DNA比对。13日，鉴定结果已出，杜小华与疑似男孩DNA比对不匹配。",
    "url": "https://www.baidu.com/s?wd=%E6%9D%9C%E5%B0%8F%E5%8D%8E%E4%B8%8E%E7%96%91%E4%BC%BC%E7%94%B7%E5%AD%A9DNA%E6%AF%94%E5%AF%B9%E4%B8%8D%E5%8C%B9%E9%85%8D&sa=fyb_news&rsv_dl=fyb_news"
  },
  {
    "title": "《鱿鱼游戏》李政宰获艾美奖视帝",
    "description": "13日，第74届黄金时段艾美奖颁出全部奖项。李政宰凭借《鱿鱼游戏》成为艾美奖历史上第一位获得剧情类最佳男主角奖的亚洲演员...   13日，第74届黄金时段艾美奖颁出全部奖项。李政宰凭借《鱿鱼游戏》成为艾美奖历史上第一位获得剧情类最佳男主角奖的亚洲演员。",
    "url": "https://www.baidu.com/s?wd=%E3%80%8A%E9%B1%BF%E9%B1%BC%E6%B8%B8%E6%88%8F%E3%80%8B%E6%9D%8E%E6%94%BF%E5%AE%B0%E8%8E%B7%E8%89%BE%E7%BE%8E%E5%A5%96%E8%A7%86%E5%B8%9D&sa=fyb_news&rsv_dl=fyb_news"
  }
]