[
  {
    "title": "擦亮美丽中国底色",
    "description": "近日，“美丽中国·网络媒体生态行”主题活动第一站内蒙古自治区的行程圆满落下帷幕。走进内蒙古绿色发展一线，讲述美丽中国故事...   近日，“美丽中国·网络媒体生态行”主题活动第一站内蒙古自治区的行程圆满落下帷幕。走进内蒙古绿色发展一线，讲述美丽中国故事，擦亮美丽中国底色。",
    "url": "https://www.baidu.com/s?wd=%E6%93%A6%E4%BA%AE%E7%BE%8E%E4%B8%BD%E4%B8%AD%E5%9B%BD%E5%BA%95%E8%89%B2&sa=fyb_news&rsv_dl=fyb_news"
  },
  {
    "title": "四川一民警持枪击伤2人后逃匿",
    "description": "7月26日晚，四川乐山沐川县一民警持枪击伤两人后驾车逃匿。据悉，两名伤者正在抢救，截至26日20时30分，嫌疑人尚未落网...   7月26日晚，四川乐山沐川县一民警持枪击伤两人后驾车逃匿。据悉，两名伤者正在抢救，截至26日20时30分，嫌疑人尚未落网。",
    "url": "https://www.baidu.com/s?wd=%E5%9B%9B%E5%B7%9D%E4%B8%80%E6%B0%91%E8%AD%A6%E6%8C%81%E6%9E%AA%E5%87%BB%E4%BC%A42%E4%BA%BA%E5%90%8E%E9%80%83%E5%8C%BF&sa=fyb_news&rsv_dl=fyb_news"
  },
  {
    "title": "王力宏确诊新冠",
    "description": "7月26日，台媒报道称王力宏确诊新冠肺炎，其经纪人受访证实确有其事，但只是轻症，没有大碍。   7月26日，台媒报道称王力宏确诊新冠肺炎，其经纪人受访证实确有其事，但只是轻症，没有大碍。",
    "url": "https://www.baidu.com/s?wd=%E7%8E%8B%E5%8A%9B%E5%AE%8F%E7%A1%AE%E8%AF%8A%E6%96%B0%E5%86%A0&sa=fyb_news&rsv_dl=fyb_news"
  },
  {
    "title": "扎实推动共同富裕",
    "description": "让人民过上好日子，是“国之大者”。深刻践行以人民为中心的发展思想，既要尽力而为也要量力而行，我们在高质量发展中促进共同富...   让人民过上好日子，是“国之大者”。深刻践行以人民为中心的发展思想，既要尽力而为也要量力而行，我们在高质量发展中促进共同富裕的脚步更加笃定。",
    "url": "https://www.baidu.com/s?wd=%E6%89%8E%E5%AE%9E%E6%8E%A8%E5%8A%A8%E5%85%B1%E5%90%8C%E5%AF%8C%E8%A3%95&sa=fyb_news&rsv_dl=fyb_news"
  },
  {
    "title": "2岁女童疑患性病 官方：排除遭性侵",
    "description": "近日，两岁女童疑患性病及疑似被性侵一事引发关注。26日，镇宁直治县卫生健康局回应，经各部门联合调查，该女童已排除被性侵可...   近日，两岁女童疑患性病及疑似被性侵一事引发关注。26日，镇宁直治县卫生健康局回应，经各部门联合调查，该女童已排除被性侵可能。",
    "url": "https://www.baidu.com/s?wd=2%E5%B2%81%E5%A5%B3%E7%AB%A5%E7%96%91%E6%82%A3%E6%80%A7%E7%97%85+%E5%AE%98%E6%96%B9%EF%BC%9A%E6%8E%92%E9%99%A4%E9%81%AD%E6%80%A7%E4%BE%B5&sa=fyb_news&rsv_dl=fyb_news"
  },
  {
    "title": "网友称在大连横山寺为关东军立牌位",
    "description": "26日，有网友称曾为关东军司令部在大连旅顺口横山寺立牌位引发关注。大连民族和宗教事务局宗教处工作人员回应，相关人员已前往...   26日，有网友称曾为关东军司令部在大连旅顺口横山寺立牌位引发关注。大连民族和宗教事务局宗教处工作人员回应，相关人员已前往横山寺，正在调查核实。",
    "url": "https://www.baidu.com/s?wd=%E7%BD%91%E5%8F%8B%E7%A7%B0%E5%9C%A8%E5%A4%A7%E8%BF%9E%E6%A8%AA%E5%B1%B1%E5%AF%BA%E4%B8%BA%E5%85%B3%E4%B8%9C%E5%86%9B%E7%AB%8B%E7%89%8C%E4%BD%8D&sa=fyb_news&rsv_dl=fyb_news"
  },
  {
    "title": "教招笔试缺考者入围面试？河南回应",
    "description": "近日，一位参加2021年开封祥符区教师招聘考试的考生反映，这次招聘有笔试缺考者竟入围了面试。对此，祥符区政府区长热线工作...   近日，一位参加2021年开封祥符区教师招聘考试的考生反映，这次招聘有笔试缺考者竟入围了面试。对此，祥符区政府区长热线工作人员表示，正在进行调查。",
    "url": "https://www.baidu.com/s?wd=%E6%95%99%E6%8B%9B%E7%AC%94%E8%AF%95%E7%BC%BA%E8%80%83%E8%80%85%E5%85%A5%E5%9B%B4%E9%9D%A2%E8%AF%95%EF%BC%9F%E6%B2%B3%E5%8D%97%E5%9B%9E%E5%BA%94&sa=fyb_news&rsv_dl=fyb_news"
  },
  {
    "title": "“二舅视频”被质疑真实性 作者回应",
    "description": "",
    "url": "https://www.baidu.com/s?wd=%E2%80%9C%E4%BA%8C%E8%88%85%E8%A7%86%E9%A2%91%E2%80%9D%E8%A2%AB%E8%B4%A8%E7%96%91%E7%9C%9F%E5%AE%9E%E6%80%A7+%E4%BD%9C%E8%80%85%E5%9B%9E%E5%BA%94&sa=fyb_news&rsv_dl=fyb_news"
  },
  {
    "title": "男子跳伞时遇火箭发射激动大喊",
    "description": "24日，在海南万宁，一男子跳伞时遇火箭发射，激动大喊，记录同框瞬间。   24日，在海南万宁，一男子跳伞时遇火箭发射，激动大喊，记录同框瞬间。",
    "url": "https://www.baidu.com/s?wd=%E7%94%B7%E5%AD%90%E8%B7%B3%E4%BC%9E%E6%97%B6%E9%81%87%E7%81%AB%E7%AE%AD%E5%8F%91%E5%B0%84%E6%BF%80%E5%8A%A8%E5%A4%A7%E5%96%8A&sa=fyb_news&rsv_dl=fyb_news"
  },
  {
    "title": "媒体：国企员工炫富最终会坑到谁?",
    "description": "24日，一位江西男子周某在朋友圈炫富之事引发舆论关注。有媒体锐评此事：周某是如何进江西国控公司的？周某朋友圈炫富秀权，值...   24日，一位江西男子周某在朋友圈炫富之事引发舆论关注。有媒体锐评此事：周某是如何进江西国控公司的？周某朋友圈炫富秀权，值得深查！",
    "url": "https://www.baidu.com/s?wd=%E5%AA%92%E4%BD%93%EF%BC%9A%E5%9B%BD%E4%BC%81%E5%91%98%E5%B7%A5%E7%82%AB%E5%AF%8C%E6%9C%80%E7%BB%88%E4%BC%9A%E5%9D%91%E5%88%B0%E8%B0%81%3F&sa=fyb_news&rsv_dl=fyb_news"
  },
  {
    "title": "美宝莲将关闭中国所有线下门店",
    "description": "",
    "url": "https://www.baidu.com/s?wd=%E7%BE%8E%E5%AE%9D%E8%8E%B2%E5%B0%86%E5%85%B3%E9%97%AD%E4%B8%AD%E5%9B%BD%E6%89%80%E6%9C%89%E7%BA%BF%E4%B8%8B%E9%97%A8%E5%BA%97&sa=fyb_news&rsv_dl=fyb_news"
  },
  {
    "title": "高中生暑假发自拍朋友圈被处分",
    "description": "近日，盘锦一女生暑假期间在朋友圈发自拍被学校通报记处分。对此，盘锦市教育局回应称：教育局没有此项规定，但是有的学校会有自...   近日，盘锦一女生暑假期间在朋友圈发自拍被学校通报记处分。对此，盘锦市教育局回应称：教育局没有此项规定，但是有的学校会有自己的规定。",
    "url": "https://www.baidu.com/s?wd=%E9%AB%98%E4%B8%AD%E7%94%9F%E6%9A%91%E5%81%87%E5%8F%91%E8%87%AA%E6%8B%8D%E6%9C%8B%E5%8F%8B%E5%9C%88%E8%A2%AB%E5%A4%84%E5%88%86&sa=fyb_news&rsv_dl=fyb_news"
  },
  {
    "title": "杭州独居教授因热射病晕倒家中",
    "description": "近日，杭州一独居教授因热射病导致晕厥住院。据悉，老人因对电器怀有不信任感一直没开空调。医生提醒，持续的极端高温天里，空调...   近日，杭州一独居教授因热射病导致晕厥住院。据悉，老人因对电器怀有不信任感一直没开空调。医生提醒，持续的极端高温天里，空调和风扇最好都开起来。",
    "url": "https://www.baidu.com/s?wd=%E6%9D%AD%E5%B7%9E%E7%8B%AC%E5%B1%85%E6%95%99%E6%8E%88%E5%9B%A0%E7%83%AD%E5%B0%84%E7%97%85%E6%99%95%E5%80%92%E5%AE%B6%E4%B8%AD&sa=fyb_news&rsv_dl=fyb_news"
  },
  {
    "title": "佩洛西拟访台 国防部：不会坐视不管",
    "description": "26日，针对佩洛西计划访台一事，国防部新闻发言人谭克非回应称，如果美方一意孤行，中国军队绝不会坐视不管。   26日，针对佩洛西计划访台一事，国防部新闻发言人谭克非回应称，如果美方一意孤行，中国军队绝不会坐视不管。",
    "url": "https://www.baidu.com/s?wd=%E4%BD%A9%E6%B4%9B%E8%A5%BF%E6%8B%9F%E8%AE%BF%E5%8F%B0+%E5%9B%BD%E9%98%B2%E9%83%A8%EF%BC%9A%E4%B8%8D%E4%BC%9A%E5%9D%90%E8%A7%86%E4%B8%8D%E7%AE%A1&sa=fyb_news&rsv_dl=fyb_news"
  },
  {
    "title": "被周劼炫耀的银行行长已离任",
    "description": "近日，国企员工周劼炫权炫富引发热议。周劼在朋友圈中“炫”的行长罗焱已在2021年12月15日被江西银行免去行长、副董事长...   近日，国企员工周劼炫权炫富引发热议。周劼在朋友圈中“炫”的行长罗焱已在2021年12月15日被江西银行免去行长、副董事长、执行董事等职务。",
    "url": "https://www.baidu.com/s?wd=%E8%A2%AB%E5%91%A8%E5%8A%BC%E7%82%AB%E8%80%80%E7%9A%84%E9%93%B6%E8%A1%8C%E8%A1%8C%E9%95%BF%E5%B7%B2%E7%A6%BB%E4%BB%BB&sa=fyb_news&rsv_dl=fyb_news"
  },
  {
    "title": "苹果应用商店被曝有大量色情App",
    "description": "26日，苹果应用商店被曝有大量色情App，它们打着答题类游戏等伪装，实际打开后却是色情内容。对此，苹果客服回应称：很震惊...   26日，苹果应用商店被曝有大量色情App，它们打着答题类游戏等伪装，实际打开后却是色情内容。对此，苹果客服回应称：很震惊，会进一步了解情况。",
    "url": "https://www.baidu.com/s?wd=%E8%8B%B9%E6%9E%9C%E5%BA%94%E7%94%A8%E5%95%86%E5%BA%97%E8%A2%AB%E6%9B%9D%E6%9C%89%E5%A4%A7%E9%87%8F%E8%89%B2%E6%83%85App&sa=fyb_news&rsv_dl=fyb_news"
  },
  {
    "title": "房地产专家称坚决不能取消预售制",
    "description": "北师大房地产研究中心主任董藩认为：现在网上很多人呼吁取消预售制，是因为没有看到预售制背后的积极意义。   北师大房地产研究中心主任董藩认为：现在网上很多人呼吁取消预售制，是因为没有看到预售制背后的积极意义。",
    "url": "https://www.baidu.com/s?wd=%E6%88%BF%E5%9C%B0%E4%BA%A7%E4%B8%93%E5%AE%B6%E7%A7%B0%E5%9D%9A%E5%86%B3%E4%B8%8D%E8%83%BD%E5%8F%96%E6%B6%88%E9%A2%84%E5%94%AE%E5%88%B6&sa=fyb_news&rsv_dl=fyb_news"
  },
  {
    "title": "周劼回应炫富：父亲并非副局长",
    "description": "近日，国企员工在微信朋友圈炫富一事持续引发关注。26日，当事人周劼回应称，父亲并非升任副局长，朋友圈的一些言论存在夸大不...   近日，国企员工在微信朋友圈炫富一事持续引发关注。26日，当事人周劼回应称，父亲并非升任副局长，朋友圈的一些言论存在夸大不实的成分。",
    "url": "https://www.baidu.com/s?wd=%E5%91%A8%E5%8A%BC%E5%9B%9E%E5%BA%94%E7%82%AB%E5%AF%8C%EF%BC%9A%E7%88%B6%E4%BA%B2%E5%B9%B6%E9%9D%9E%E5%89%AF%E5%B1%80%E9%95%BF&sa=fyb_news&rsv_dl=fyb_news"
  },
  {
    "title": "中学新生报到需老人疫苗证明?已取消",
    "description": "日前，网传江苏无锡雪浪中学新生报到要求提供居住在无锡的爷爷奶奶、外公外婆新冠疫苗接种证明，否则不予以报到。对此学校回应，...   日前，网传江苏无锡雪浪中学新生报到要求提供居住在无锡的爷爷奶奶、外公外婆新冠疫苗接种证明，否则不予以报到。对此学校回应，目前这一要求已经取消。",
    "url": "https://www.baidu.com/s?wd=%E4%B8%AD%E5%AD%A6%E6%96%B0%E7%94%9F%E6%8A%A5%E5%88%B0%E9%9C%80%E8%80%81%E4%BA%BA%E7%96%AB%E8%8B%97%E8%AF%81%E6%98%8E%3F%E5%B7%B2%E5%8F%96%E6%B6%88&sa=fyb_news&rsv_dl=fyb_news"
  },
  {
    "title": "孙杨与张豆豆牵手回老家",
    "description": "7月26日，有媒体曝出，张豆豆带孙杨回到老家看望她的父母，一路上两人手牵着手，而她的无名指上戴着一枚大钻戒，疑似好事将近...   7月26日，有媒体曝出，张豆豆带孙杨回到老家看望她的父母，一路上两人手牵着手，而她的无名指上戴着一枚大钻戒，疑似好事将近。",
    "url": "https://www.baidu.com/s?wd=%E5%AD%99%E6%9D%A8%E4%B8%8E%E5%BC%A0%E8%B1%86%E8%B1%86%E7%89%B5%E6%89%8B%E5%9B%9E%E8%80%81%E5%AE%B6&sa=fyb_news&rsv_dl=fyb_news"
  },
  {
    "title": "人民网：对炫权炫富的周劼一查到底",
    "description": "近日，国企员工在朋友圈高调炫富秀权一事引发热议。26日，人民网对此事作出评论称，只有一查到底，才能依法维护社会公平正义。   近日，国企员工在朋友圈高调炫富秀权一事引发热议。26日，人民网对此事作出评论称，只有一查到底，才能依法维护社会公平正义。",
    "url": "https://www.baidu.com/s?wd=%E4%BA%BA%E6%B0%91%E7%BD%91%EF%BC%9A%E5%AF%B9%E7%82%AB%E6%9D%83%E7%82%AB%E5%AF%8C%E7%9A%84%E5%91%A8%E5%8A%BC%E4%B8%80%E6%9F%A5%E5%88%B0%E5%BA%95&sa=fyb_news&rsv_dl=fyb_news"
  },
  {
    "title": "女子怀孕八个月流浪街头",
    "description": "近日，一条“女子怀孕八个月流浪街头”的视频引发关注。视频中一女子挺着大肚子，自称已怀孕八个月。   近日，一条“女子怀孕八个月流浪街头”的视频引发关注。视频中一女子挺着大肚子，自称已怀孕八个月。",
    "url": "https://www.baidu.com/s?wd=%E5%A5%B3%E5%AD%90%E6%80%80%E5%AD%95%E5%85%AB%E4%B8%AA%E6%9C%88%E6%B5%81%E6%B5%AA%E8%A1%97%E5%A4%B4&sa=fyb_news&rsv_dl=fyb_news"
  },
  {
    "title": "林志颖第一场手术完成：耗时5小时",
    "description": "26日，台媒曝林志颖第一阶段的手术已在早上顺利完成。据悉，林志颖26日上午开始手术，耗时约4、5个小时，将肩膀粉碎性骨折...   26日，台媒曝林志颖第一阶段的手术已在早上顺利完成。据悉，林志颖26日上午开始手术，耗时约4、5个小时，将肩膀粉碎性骨折的部分修复完成。",
    "url": "https://www.baidu.com/s?wd=%E6%9E%97%E5%BF%97%E9%A2%96%E7%AC%AC%E4%B8%80%E5%9C%BA%E6%89%8B%E6%9C%AF%E5%AE%8C%E6%88%90%EF%BC%9A%E8%80%97%E6%97%B65%E5%B0%8F%E6%97%B6&sa=fyb_news&rsv_dl=fyb_news"
  },
  {
    "title": "与趣店合作惹争议 贾乃亮傅首尔致歉",
    "description": "",
    "url": "https://www.baidu.com/s?wd=%E4%B8%8E%E8%B6%A3%E5%BA%97%E5%90%88%E4%BD%9C%E6%83%B9%E4%BA%89%E8%AE%AE+%E8%B4%BE%E4%B9%83%E4%BA%AE%E5%82%85%E9%A6%96%E5%B0%94%E8%87%B4%E6%AD%89&sa=fyb_news&rsv_dl=fyb_news"
  },
  {
    "title": "#二舅真能治疗精神内耗吗#",
    "description": "",
    "url": "https://www.baidu.com/s?wd=%23%E4%BA%8C%E8%88%85%E7%9C%9F%E8%83%BD%E6%B2%BB%E7%96%97%E7%B2%BE%E7%A5%9E%E5%86%85%E8%80%97%E5%90%97%23&sa=fyb_news&rsv_dl=fyb_news"
  },
  {
    "title": "高校学生毕业13年后被撤销毕业证",
    "description": "近日，西安工业大学发布一则《关于撤销陈华良毕业证书的公告》。公告显示，毕业13年的陈华良因违反相关规定，非法取得学籍被撤...   近日，西安工业大学发布一则《关于撤销陈华良毕业证书的公告》。公告显示，毕业13年的陈华良因违反相关规定，非法取得学籍被撤销毕业证。",
    "url": "https://www.baidu.com/s?wd=%E9%AB%98%E6%A0%A1%E5%AD%A6%E7%94%9F%E6%AF%95%E4%B8%9A13%E5%B9%B4%E5%90%8E%E8%A2%AB%E6%92%A4%E9%94%80%E6%AF%95%E4%B8%9A%E8%AF%81&sa=fyb_news&rsv_dl=fyb_news"
  },
  {
    "title": "中国女足获得东亚杯亚军",
    "description": "在2022东亚杯女足第三轮比赛中，中国女足0比0战平日本。至此本届东亚杯女足的比赛全部收官，中国女足三场比赛1胜2平，获...   在2022东亚杯女足第三轮比赛中，中国女足0比0战平日本。至此本届东亚杯女足的比赛全部收官，中国女足三场比赛1胜2平，获得本届东亚杯女足的亚军。",
    "url": "https://www.baidu.com/s?wd=%E4%B8%AD%E5%9B%BD%E5%A5%B3%E8%B6%B3%E8%8E%B7%E5%BE%97%E4%B8%9C%E4%BA%9A%E6%9D%AF%E4%BA%9A%E5%86%9B&sa=fyb_news&rsv_dl=fyb_news"
  },
  {
    "title": "“二舅治好了我的精神内耗”刷屏",
    "description": "近日，《回村三天，二舅治好了我的精神内耗》的视频刷屏了，UP主“衣戈猜想”在视频中讲述了农村二舅平凡又有力量的一生，让很...   近日，《回村三天，二舅治好了我的精神内耗》的视频刷屏了，UP主“衣戈猜想”在视频中讲述了农村二舅平凡又有力量的一生，让很多网友直呼治愈。",
    "url": "https://www.baidu.com/s?wd=%E2%80%9C%E4%BA%8C%E8%88%85%E6%B2%BB%E5%A5%BD%E4%BA%86%E6%88%91%E7%9A%84%E7%B2%BE%E7%A5%9E%E5%86%85%E8%80%97%E2%80%9D%E5%88%B7%E5%B1%8F&sa=fyb_news&rsv_dl=fyb_news"
  },
  {
    "title": "小伙喝珍珠奶茶卡喉身亡？家属辟谣",
    "description": "近日，四川一名16岁小伙“因喝珍珠奶茶被卡喉身亡”的消息引发网友热议。26日，家属李先生表示，弟弟死亡的原因是心脏骤停，...   近日，四川一名16岁小伙“因喝珍珠奶茶被卡喉身亡”的消息引发网友热议。26日，家属李先生表示，弟弟死亡的原因是心脏骤停，希望不要再炒作。",
    "url": "https://www.baidu.com/s?wd=%E5%B0%8F%E4%BC%99%E5%96%9D%E7%8F%8D%E7%8F%A0%E5%A5%B6%E8%8C%B6%E5%8D%A1%E5%96%89%E8%BA%AB%E4%BA%A1%EF%BC%9F%E5%AE%B6%E5%B1%9E%E8%BE%9F%E8%B0%A3&sa=fyb_news&rsv_dl=fyb_news"
  },
  {
    "title": "祭奠网站回应为多名战犯设纪念堂",
    "description": "近日，网曝线上祭奠网站孝爱之家网为侵华战犯设立纪念堂。26日，网站客服回应称，该纪念堂是2014年建的，建馆人已被封号。   近日，网曝线上祭奠网站孝爱之家网为侵华战犯设立纪念堂。26日，网站客服回应称，该纪念堂是2014年建的，建馆人已被封号。",
    "url": "https://www.baidu.com/s?wd=%E7%A5%AD%E5%A5%A0%E7%BD%91%E7%AB%99%E5%9B%9E%E5%BA%94%E4%B8%BA%E5%A4%9A%E5%90%8D%E6%88%98%E7%8A%AF%E8%AE%BE%E7%BA%AA%E5%BF%B5%E5%A0%82&sa=fyb_news&rsv_dl=fyb_news"
  },
  {
    "title": "丈夫出轨赠情人379万 妻子全部追回",
    "description": "辽宁一对结婚30年夫妻，丈夫出轨14年并赠与情人钱款379万元，妻子一怒之下诉至法院。最终法院判决情人返还李女士人379...   辽宁一对结婚30年夫妻，丈夫出轨14年并赠与情人钱款379万元，妻子一怒之下诉至法院。最终法院判决情人返还李女士人379万余元，本案已于近日生效。",
    "url": "https://www.baidu.com/s?wd=%E4%B8%88%E5%A4%AB%E5%87%BA%E8%BD%A8%E8%B5%A0%E6%83%85%E4%BA%BA379%E4%B8%87+%E5%A6%BB%E5%AD%90%E5%85%A8%E9%83%A8%E8%BF%BD%E5%9B%9E&sa=fyb_news&rsv_dl=fyb_news"
  },
  {
    "title": "13岁男孩昆仑山地区爬山时走失",
    "description": "7月26日17时许，在格尔木往拉萨方向132公里处，一名13岁男孩与家人爬山途中走失，该地区为昆仑山区。目前，搜救工作正...   7月26日17时许，在格尔木往拉萨方向132公里处，一名13岁男孩与家人爬山途中走失，该地区为昆仑山区。目前，搜救工作正在紧张进行中。",
    "url": "https://www.baidu.com/s?wd=13%E5%B2%81%E7%94%B7%E5%AD%A9%E6%98%86%E4%BB%91%E5%B1%B1%E5%9C%B0%E5%8C%BA%E7%88%AC%E5%B1%B1%E6%97%B6%E8%B5%B0%E5%A4%B1&sa=fyb_news&rsv_dl=fyb_news"
  },
  {
    "title": "苏州雷暴大风：公交站亭被吹垮",
    "description": "26日，苏州市气象台升级发布雷暴大风红色预警信号，吴中区木渎镇出现局地短暂龙卷风。当地翠坊桥公交站台不敌强风侵袭，顷刻间...   26日，苏州市气象台升级发布雷暴大风红色预警信号，吴中区木渎镇出现局地短暂龙卷风。当地翠坊桥公交站台不敌强风侵袭，顷刻间垮塌，飘起巨大扬尘。",
    "url": "https://www.baidu.com/s?wd=%E8%8B%8F%E5%B7%9E%E9%9B%B7%E6%9A%B4%E5%A4%A7%E9%A3%8E%EF%BC%9A%E5%85%AC%E4%BA%A4%E7%AB%99%E4%BA%AD%E8%A2%AB%E5%90%B9%E5%9E%AE&sa=fyb_news&rsv_dl=fyb_news"
  },
  {
    "title": "二舅视频UP主回应网友直播建议",
    "description": "近日，《回村三天，二舅治好了我的精神内耗》的视频刷屏网络，有网友建议二舅去各大短视频平台直播。对此，作者回应：让二舅和姥...   近日，《回村三天，二舅治好了我的精神内耗》的视频刷屏网络，有网友建议二舅去各大短视频平台直播。对此，作者回应：让二舅和姥姥安静生活吧。",
    "url": "https://www.baidu.com/s?wd=%E4%BA%8C%E8%88%85%E8%A7%86%E9%A2%91UP%E4%B8%BB%E5%9B%9E%E5%BA%94%E7%BD%91%E5%8F%8B%E7%9B%B4%E6%92%AD%E5%BB%BA%E8%AE%AE&sa=fyb_news&rsv_dl=fyb_news"
  },
  {
    "title": "台北开展大规模防空演习",
    "description": "25日下午1点30分至2点，台湾军方于台湾北部7县巿举行“万安45号”演习。对台北市而言，这次演习是史上规模最大防空演习...   25日下午1点30分至2点，台湾军方于台湾北部7县巿举行“万安45号”演习。对台北市而言，这次演习是史上规模最大防空演习。",
    "url": "https://www.baidu.com/s?wd=%E5%8F%B0%E5%8C%97%E5%BC%80%E5%B1%95%E5%A4%A7%E8%A7%84%E6%A8%A1%E9%98%B2%E7%A9%BA%E6%BC%94%E4%B9%A0&sa=fyb_news&rsv_dl=fyb_news"
  },
  {
    "title": "国家宗教局：对宗教场所紧急排查",
    "description": "近日，国家宗教事务局发出通知，紧急部署各地指导宗教界深刻汲取教训，对宗教活动场所开展全面自查整改，发现问题立即纠正，依法...   近日，国家宗教事务局发出通知，紧急部署各地指导宗教界深刻汲取教训，对宗教活动场所开展全面自查整改，发现问题立即纠正，依法依规严肃处理。",
    "url": "https://www.baidu.com/s?wd=%E5%9B%BD%E5%AE%B6%E5%AE%97%E6%95%99%E5%B1%80%EF%BC%9A%E5%AF%B9%E5%AE%97%E6%95%99%E5%9C%BA%E6%89%80%E7%B4%A7%E6%80%A5%E6%8E%92%E6%9F%A5&sa=fyb_news&rsv_dl=fyb_news"
  },
  {
    "title": "不续签超30岁未育女员工？汇丰回应",
    "description": "26日，网传汇丰银行不再续签1993年1月1日以前出生的女员工（未婚未育，已婚未育）。汇丰中国回应：切勿轻信网络不实信息...   26日，网传汇丰银行不再续签1993年1月1日以前出生的女员工（未婚未育，已婚未育）。汇丰中国回应：切勿轻信网络不实信息。",
    "url": "https://www.baidu.com/s?wd=%E4%B8%8D%E7%BB%AD%E7%AD%BE%E8%B6%8530%E5%B2%81%E6%9C%AA%E8%82%B2%E5%A5%B3%E5%91%98%E5%B7%A5%EF%BC%9F%E6%B1%87%E4%B8%B0%E5%9B%9E%E5%BA%94&sa=fyb_news&rsv_dl=fyb_news"
  },
  {
    "title": "北京一男子划皮划艇上班：不堵车",
    "description": "7月25日，北京朝阳市民杨先生走水路划船上班引发网友关注热议。当事人杨先生称，汽车限号自己又爱好皮划艇，就选择这种方式上...   7月25日，北京朝阳市民杨先生走水路划船上班引发网友关注热议。当事人杨先生称，汽车限号自己又爱好皮划艇，就选择这种方式上班，同时还能锻炼身体。",
    "url": "https://www.baidu.com/s?wd=%E5%8C%97%E4%BA%AC%E4%B8%80%E7%94%B7%E5%AD%90%E5%88%92%E7%9A%AE%E5%88%92%E8%89%87%E4%B8%8A%E7%8F%AD%EF%BC%9A%E4%B8%8D%E5%A0%B5%E8%BD%A6&sa=fyb_news&rsv_dl=fyb_news"
  },
  {
    "title": "消防员抓捕黄鼠狼被臭屁熏吐",
    "description": "25日，重庆一老人家中跑进黄鼠狼，消防员在帮忙抓捕过程中多次被喷臭屁，导致被臭吐了。不过消防员表示，能够为老百姓排忧解难...   25日，重庆一老人家中跑进黄鼠狼，消防员在帮忙抓捕过程中多次被喷臭屁，导致被臭吐了。不过消防员表示，能够为老百姓排忧解难是值得的。",
    "url": "https://www.baidu.com/s?wd=%E6%B6%88%E9%98%B2%E5%91%98%E6%8A%93%E6%8D%95%E9%BB%84%E9%BC%A0%E7%8B%BC%E8%A2%AB%E8%87%AD%E5%B1%81%E7%86%8F%E5%90%90&sa=fyb_news&rsv_dl=fyb_news"
  },
  {
    "title": "日本天皇患心力衰竭",
    "description": "日本宫内厅表示，当地时间24日，现年88岁的日本上皇明仁在东京大学医院接受检查后被诊断为心力衰竭。目前身体状况正在改善，...   日本宫内厅表示，当地时间24日，现年88岁的日本上皇明仁在东京大学医院接受检查后被诊断为心力衰竭。目前身体状况正在改善，无需住院。",
    "url": "https://www.baidu.com/s?wd=%E6%97%A5%E6%9C%AC%E5%A4%A9%E7%9A%87%E6%82%A3%E5%BF%83%E5%8A%9B%E8%A1%B0%E7%AB%AD&sa=fyb_news&rsv_dl=fyb_news"
  },
  {
    "title": "广州一租户未打疫苗开门权限被限",
    "description": "近日，广东袁先生反映自己因未打疫苗被限制出租屋门锁的开启权限。12345回应系村规，村委人员回应，电脑系统限定如此“没规...   近日，广东袁先生反映自己因未打疫苗被限制出租屋门锁的开启权限。12345回应系村规，村委人员回应，电脑系统限定如此“没规定就这样”。",
    "url": "https://www.baidu.com/s?wd=%E5%B9%BF%E5%B7%9E%E4%B8%80%E7%A7%9F%E6%88%B7%E6%9C%AA%E6%89%93%E7%96%AB%E8%8B%97%E5%BC%80%E9%97%A8%E6%9D%83%E9%99%90%E8%A2%AB%E9%99%90&sa=fyb_news&rsv_dl=fyb_news"
  },
  {
    "title": "炫富国企员工家族成员身份疑曝光",
    "description": "近日，国企员工在朋友圈高调炫富秀权一事引发热议。有网友找出疑似当事人周劼大伯、三伯以及父亲的资料，不过均未得到官方证实。   近日，国企员工在朋友圈高调炫富秀权一事引发热议。有网友找出疑似当事人周劼大伯、三伯以及父亲的资料，不过均未得到官方证实。",
    "url": "https://www.baidu.com/s?wd=%E7%82%AB%E5%AF%8C%E5%9B%BD%E4%BC%81%E5%91%98%E5%B7%A5%E5%AE%B6%E6%97%8F%E6%88%90%E5%91%98%E8%BA%AB%E4%BB%BD%E7%96%91%E6%9B%9D%E5%85%89&sa=fyb_news&rsv_dl=fyb_news"
  },
  {
    "title": "百名孩子游泳后高烧 2人腺病毒阳性",
    "description": "近日，四川乐山沙湾区一游泳馆被曝水质出现问题，导致馆内至少有上百名上游泳课的孩子出现发高烧和咳嗽等相似症状，其中多人被检...   近日，四川乐山沙湾区一游泳馆被曝水质出现问题，导致馆内至少有上百名上游泳课的孩子出现发高烧和咳嗽等相似症状，其中多人被检测出腺病毒阳性。",
    "url": "https://www.baidu.com/s?wd=%E7%99%BE%E5%90%8D%E5%AD%A9%E5%AD%90%E6%B8%B8%E6%B3%B3%E5%90%8E%E9%AB%98%E7%83%A7+2%E4%BA%BA%E8%85%BA%E7%97%85%E6%AF%92%E9%98%B3%E6%80%A7&sa=fyb_news&rsv_dl=fyb_news"
  },
  {
    "title": "樊振东缺赛被扣1400分仍排世界第一",
    "description": "近日，国际乒联公布了最新一期的世界排名。男单方面，由于樊振东缺席了两项赛事，按照规则他被扣除了1400分的积分，但排名仍...   近日，国际乒联公布了最新一期的世界排名。男单方面，由于樊振东缺席了两项赛事，按照规则他被扣除了1400分的积分，但排名仍在第一位。",
    "url": "https://www.baidu.com/s?wd=%E6%A8%8A%E6%8C%AF%E4%B8%9C%E7%BC%BA%E8%B5%9B%E8%A2%AB%E6%89%A31400%E5%88%86%E4%BB%8D%E6%8E%92%E4%B8%96%E7%95%8C%E7%AC%AC%E4%B8%80&sa=fyb_news&rsv_dl=fyb_news"
  },
  {
    "title": "警方回应贵阳一美食街多人斗殴",
    "description": "7月26日凌晨4时许，贵州贵阳市一商业街区发生一起群体斗殴事件。目前警方回应，称已接到报警，相关人员已被控制。   7月26日凌晨4时许，贵州贵阳市一商业街区发生一起群体斗殴事件。目前警方回应，称已接到报警，相关人员已被控制。",
    "url": "https://www.baidu.com/s?wd=%E8%AD%A6%E6%96%B9%E5%9B%9E%E5%BA%94%E8%B4%B5%E9%98%B3%E4%B8%80%E7%BE%8E%E9%A3%9F%E8%A1%97%E5%A4%9A%E4%BA%BA%E6%96%97%E6%AE%B4&sa=fyb_news&rsv_dl=fyb_news"
  },
  {
    "title": "法国敞门开空调或被罚超5000元",
    "description": "当地时间24日，法国能源转型部长称为应对极端高温和能源危机，将要求商店在使用空调时必须保持大门关闭，否则处以最高750欧...   当地时间24日，法国能源转型部长称为应对极端高温和能源危机，将要求商店在使用空调时必须保持大门关闭，否则处以最高750欧元（5176.65人民币）罚...",
    "url": "https://www.baidu.com/s?wd=%E6%B3%95%E5%9B%BD%E6%95%9E%E9%97%A8%E5%BC%80%E7%A9%BA%E8%B0%83%E6%88%96%E8%A2%AB%E7%BD%9A%E8%B6%855000%E5%85%83&sa=fyb_news&rsv_dl=fyb_news"
  },
  {
    "title": "4名发小6年后一起考上清华",
    "description": "25日，四川绵阳“四发小”全部考上清华大学的消息，刷爆了当地市民的朋友圈。他们4人是小学同班同学，在时隔6年后，又将成为...   25日，四川绵阳“四发小”全部考上清华大学的消息，刷爆了当地市民的朋友圈。他们4人是小学同班同学，在时隔6年后，又将成为大学校友。",
    "url": "https://www.baidu.com/s?wd=4%E5%90%8D%E5%8F%91%E5%B0%8F6%E5%B9%B4%E5%90%8E%E4%B8%80%E8%B5%B7%E8%80%83%E4%B8%8A%E6%B8%85%E5%8D%8E&sa=fyb_news&rsv_dl=fyb_news"
  },
  {
    "title": "拍婚纱照吵架男子将女友丢服务区",
    "description": "7月23日，一对来自湖南长沙的情侣在新疆拍婚纱照时发生了矛盾，男子将女友扔在服务区，独自驾车离开。最后女子不得不求助民警...   7月23日，一对来自湖南长沙的情侣在新疆拍婚纱照时发生了矛盾，男子将女友扔在服务区，独自驾车离开。最后女子不得不求助民警。",
    "url": "https://www.baidu.com/s?wd=%E6%8B%8D%E5%A9%9A%E7%BA%B1%E7%85%A7%E5%90%B5%E6%9E%B6%E7%94%B7%E5%AD%90%E5%B0%86%E5%A5%B3%E5%8F%8B%E4%B8%A2%E6%9C%8D%E5%8A%A1%E5%8C%BA&sa=fyb_news&rsv_dl=fyb_news"
  },
  {
    "title": "德国中产家庭排队7小时领救济粮",
    "description": "近日，外媒在走访位于德国柏林市中心的免费食物领取救济中心后发现，一些中产阶级家庭要一大早跑去援助中心，排队7个小时领取免...   近日，外媒在走访位于德国柏林市中心的免费食物领取救济中心后发现，一些中产阶级家庭要一大早跑去援助中心，排队7个小时领取免费的“救济粮”。",
    "url": "https://www.baidu.com/s?wd=%E5%BE%B7%E5%9B%BD%E4%B8%AD%E4%BA%A7%E5%AE%B6%E5%BA%AD%E6%8E%92%E9%98%9F7%E5%B0%8F%E6%97%B6%E9%A2%86%E6%95%91%E6%B5%8E%E7%B2%AE&sa=fyb_news&rsv_dl=fyb_news"
  },
  {
    "title": "辽大辅导员骚扰女学生被免职",
    "description": "7月25日，有网友发文称辽宁大学新华学院一辅导员性骚扰学生。26日校方发布通报：已对该辅导员进行免职处分，撤销教师资格证...   7月25日，有网友发文称辽宁大学新华学院一辅导员性骚扰学生。26日校方发布通报：已对该辅导员进行免职处分，撤销教师资格证。",
    "url": "https://www.baidu.com/s?wd=%E8%BE%BD%E5%A4%A7%E8%BE%85%E5%AF%BC%E5%91%98%E9%AA%9A%E6%89%B0%E5%A5%B3%E5%AD%A6%E7%94%9F%E8%A2%AB%E5%85%8D%E8%81%8C&sa=fyb_news&rsv_dl=fyb_news"
  },
  {
    "title": "炫富秀权国企员工停职 其父晋升合规",
    "description": "",
    "url": "https://www.baidu.com/s?wd=%E7%82%AB%E5%AF%8C%E7%A7%80%E6%9D%83%E5%9B%BD%E4%BC%81%E5%91%98%E5%B7%A5%E5%81%9C%E8%81%8C+%E5%85%B6%E7%88%B6%E6%99%8B%E5%8D%87%E5%90%88%E8%A7%84&sa=fyb_news&rsv_dl=fyb_news"
  },
  {
    "title": "横山寺未发现为关东军立牌位情况",
    "description": "26日，针对网友称“给大连关东军司令部怨灵立过牌位”一事，大连高新区社会管理局对横山寺逐个牌位、逐项登记进行核查，未发现...   26日，针对网友称“给大连关东军司令部怨灵立过牌位”一事，大连高新区社会管理局对横山寺逐个牌位、逐项登记进行核查，未发现为关东军立牌位的情况。",
    "url": "https://www.baidu.com/s?wd=%E6%A8%AA%E5%B1%B1%E5%AF%BA%E6%9C%AA%E5%8F%91%E7%8E%B0%E4%B8%BA%E5%85%B3%E4%B8%9C%E5%86%9B%E7%AB%8B%E7%89%8C%E4%BD%8D%E6%83%85%E5%86%B5&sa=fyb_news&rsv_dl=fyb_news"
  },
  {
    "title": "女子穿马面裙进迪奥拍照被制止",
    "description": "近日，法国奢侈品牌Dior被质疑文化挪用中国马面裙一事仍在发酵。博主包女士穿着马面裙逛Dior拍摄被店员“请出”，包女士...   近日，法国奢侈品牌Dior被质疑文化挪用中国马面裙一事仍在发酵。博主包女士穿着马面裙逛Dior拍摄被店员“请出”，包女士表示：想通过这种方式发声。",
    "url": "https://www.baidu.com/s?wd=%E5%A5%B3%E5%AD%90%E7%A9%BF%E9%A9%AC%E9%9D%A2%E8%A3%99%E8%BF%9B%E8%BF%AA%E5%A5%A5%E6%8B%8D%E7%85%A7%E8%A2%AB%E5%88%B6%E6%AD%A2&sa=fyb_news&rsv_dl=fyb_news"
  },
  {
    "title": "二舅残疾证办下来了",
    "description": "26日，二舅治好了我的精神内耗视频在网络刷屏。很多人关心二舅的残疾证有没有办下来，视频作者表示，二舅从北京回去不久，残疾...   26日，二舅治好了我的精神内耗视频在网络刷屏。很多人关心二舅的残疾证有没有办下来，视频作者表示，二舅从北京回去不久，残疾证就办下来了。",
    "url": "https://www.baidu.com/s?wd=%E4%BA%8C%E8%88%85%E6%AE%8B%E7%96%BE%E8%AF%81%E5%8A%9E%E4%B8%8B%E6%9D%A5%E4%BA%86&sa=fyb_news&rsv_dl=fyb_news"
  },
  {
    "title": "警方通报持枪伤2人持械杀3人案",
    "description": "四川省乐山市沐川县公安局通报，26日该县发生一起持枪击伤2人、持械杀害3人后逃逸的重大刑事案件。经侦查，李某（男，36岁...   四川省乐山市沐川县公安局通报，26日该县发生一起持枪击伤2人、持械杀害3人后逃逸的重大刑事案件。经侦查，李某（男，36岁）有重大作案嫌疑。",
    "url": "https://www.baidu.com/s?wd=%E8%AD%A6%E6%96%B9%E9%80%9A%E6%8A%A5%E6%8C%81%E6%9E%AA%E4%BC%A42%E4%BA%BA%E6%8C%81%E6%A2%B0%E6%9D%803%E4%BA%BA%E6%A1%88&sa=fyb_news&rsv_dl=fyb_news"
  },
  {
    "title": "李国庆曝董宇辉拉黑罗敏真正原因",
    "description": "近日，当当创始人李国庆分析董宇辉拉黑罗敏一事。李国庆表示，罗敏是去东方甄选直播间吸粉蹭粉，花5万就能冲到榜一，这太赚了，...   近日，当当创始人李国庆分析董宇辉拉黑罗敏一事。李国庆表示，罗敏是去东方甄选直播间吸粉蹭粉，花5万就能冲到榜一，这太赚了，当然给拉黑了。",
    "url": "https://www.baidu.com/s?wd=%E6%9D%8E%E5%9B%BD%E5%BA%86%E6%9B%9D%E8%91%A3%E5%AE%87%E8%BE%89%E6%8B%89%E9%BB%91%E7%BD%97%E6%95%8F%E7%9C%9F%E6%AD%A3%E5%8E%9F%E5%9B%A0&sa=fyb_news&rsv_dl=fyb_news"
  },
  {
    "title": "炫富国企员工被停职 全家名下6套房",
    "description": "近日，国企员工周劼朋友圈炫富引关注。27日，江西国控通报：周劼目前已停职配合调查，经查周劼本人及父母名下共计住房6套。   近日，国企员工周劼朋友圈炫富引关注。27日，江西国控通报：周劼目前已停职配合调查，经查周劼本人及父母名下共计住房6套。",
    "url": "https://www.baidu.com/s?wd=%E7%82%AB%E5%AF%8C%E5%9B%BD%E4%BC%81%E5%91%98%E5%B7%A5%E8%A2%AB%E5%81%9C%E8%81%8C+%E5%85%A8%E5%AE%B6%E5%90%8D%E4%B8%8B6%E5%A5%97%E6%88%BF&sa=fyb_news&rsv_dl=fyb_news"
  },
  {
    "title": "特朗普重回华盛顿：我必须拯救美国",
    "description": "据美媒报道，当地时间26日，特朗普自卸任以来，首次回到华盛顿并登台演讲。特朗普曾在演讲中多次暗示，将竞逐2024年大选，...   据美媒报道，当地时间26日，特朗普自卸任以来，首次回到华盛顿并登台演讲。特朗普曾在演讲中多次暗示，将竞逐2024年大选，并表示自己必须拯救美国。",
    "url": "https://www.baidu.com/s?wd=%E7%89%B9%E6%9C%97%E6%99%AE%E9%87%8D%E5%9B%9E%E5%8D%8E%E7%9B%9B%E9%A1%BF%EF%BC%9A%E6%88%91%E5%BF%85%E9%A1%BB%E6%8B%AF%E6%95%91%E7%BE%8E%E5%9B%BD&sa=fyb_news&rsv_dl=fyb_news"
  },
  {
    "title": "英首相候选人电视辩论因意外中断",
    "description": "当地时间26日，英国首相的两位候选人——前财政大臣苏纳克和前外交大臣特拉斯参加的电视辩论活动上突发意外，主持人在直播中突...   当地时间26日，英国首相的两位候选人——前财政大臣苏纳克和前外交大臣特拉斯参加的电视辩论活动上突发意外，主持人在直播中突然晕倒。",
    "url": "https://www.baidu.com/s?wd=%E8%8B%B1%E9%A6%96%E7%9B%B8%E5%80%99%E9%80%89%E4%BA%BA%E7%94%B5%E8%A7%86%E8%BE%A9%E8%AE%BA%E5%9B%A0%E6%84%8F%E5%A4%96%E4%B8%AD%E6%96%AD&sa=fyb_news&rsv_dl=fyb_news"
  },
  {
    "title": "30岁人大硕士为学医重新高考",
    "description": "30岁的纪思璇是一名就读于人大的在职研究生，但她梦想着成为一名医生。为了圆梦，去年年底开始备战高考，最终成功被首都医科大...   30岁的纪思璇是一名就读于人大的在职研究生，但她梦想着成为一名医生。为了圆梦，去年年底开始备战高考，最终成功被首都医科大学的临床医学专业录取。",
    "url": "https://www.baidu.com/s?wd=30%E5%B2%81%E4%BA%BA%E5%A4%A7%E7%A1%95%E5%A3%AB%E4%B8%BA%E5%AD%A6%E5%8C%BB%E9%87%8D%E6%96%B0%E9%AB%98%E8%80%83&sa=fyb_news&rsv_dl=fyb_news"
  },
  {
    "title": "男子夜晚尾随骚扰女子追问约不约",
    "description": "近日，山东威海一女子晚上回家时遭陌生男子尾随骚扰。该男子不停追问女子“约不约”。女子称，已报警，但由于没有实质性拉扯或猥...   近日，山东威海一女子晚上回家时遭陌生男子尾随骚扰。该男子不停追问女子“约不约”。女子称，已报警，但由于没有实质性拉扯或猥亵，警方不立案。",
    "url": "https://www.baidu.com/s?wd=%E7%94%B7%E5%AD%90%E5%A4%9C%E6%99%9A%E5%B0%BE%E9%9A%8F%E9%AA%9A%E6%89%B0%E5%A5%B3%E5%AD%90%E8%BF%BD%E9%97%AE%E7%BA%A6%E4%B8%8D%E7%BA%A6&sa=fyb_news&rsv_dl=fyb_news"
  },
  {
    "title": "31省份新增本土79+525",
    "description": "",
    "url": "https://www.baidu.com/s?wd=31%E7%9C%81%E4%BB%BD%E6%96%B0%E5%A2%9E%E6%9C%AC%E5%9C%9F79%2B525&sa=fyb_news&rsv_dl=fyb_news"
  },
  {
    "title": "油价三连降 加满一箱油少花12元",
    "description": "7月26日24时，新一轮成品油调价窗口将开启。央视财经测算显示，以油箱容量在50L的家用轿车为例，加满一箱92号汽油将少...   7月26日24时，新一轮成品油调价窗口将开启。央视财经测算显示，以油箱容量在50L的家用轿车为例，加满一箱92号汽油将少花12元。",
    "url": "https://www.baidu.com/s?wd=%E6%B2%B9%E4%BB%B7%E4%B8%89%E8%BF%9E%E9%99%8D+%E5%8A%A0%E6%BB%A1%E4%B8%80%E7%AE%B1%E6%B2%B9%E5%B0%91%E8%8A%B112%E5%85%83&sa=fyb_news&rsv_dl=fyb_news"
  },
  {
    "title": "“二舅”走红后全家哭了一场",
    "description": "一条名为《回村三天，二舅治好了我的精神内耗》的视频里，UP主“衣戈猜想”以第三人称的视角，用镜头讲述了他二舅的一生。“二...   一条名为《回村三天，二舅治好了我的精神内耗》的视频里，UP主“衣戈猜想”以第三人称的视角，用镜头讲述了他二舅的一生。“二舅”走红后，全家哭了一场。",
    "url": "https://www.baidu.com/s?wd=%E2%80%9C%E4%BA%8C%E8%88%85%E2%80%9D%E8%B5%B0%E7%BA%A2%E5%90%8E%E5%85%A8%E5%AE%B6%E5%93%AD%E4%BA%86%E4%B8%80%E5%9C%BA&sa=fyb_news&rsv_dl=fyb_news"
  },
  {
    "title": "乐山持枪伤人案：警方公布照片悬赏",
    "description": "7月26日，四川省沐川县发生一起持枪击伤2人、持械杀害3人的重大刑事案件，涉案枪弹已于当日全部查获，警方公布照片悬赏。   7月26日，四川省沐川县发生一起持枪击伤2人、持械杀害3人的重大刑事案件，涉案枪弹已于当日全部查获，警方公布照片悬赏。",
    "url": "https://www.baidu.com/s?wd=%E4%B9%90%E5%B1%B1%E6%8C%81%E6%9E%AA%E4%BC%A4%E4%BA%BA%E6%A1%88%EF%BC%9A%E8%AD%A6%E6%96%B9%E5%85%AC%E5%B8%83%E7%85%A7%E7%89%87%E6%82%AC%E8%B5%8F&sa=fyb_news&rsv_dl=fyb_news"
  },
  {
    "title": "江苏农民比四川农民一年多赚50％",
    "description": "中国社科院农村发展研究所26日发布的《中国农村发展报告2022》）显示，2020年江苏省农民人均可支配收入24198.5...   中国社科院农村发展研究所26日发布的《中国农村发展报告2022》）显示，2020年江苏省农民人均可支配收入24198.5元，高出四川51.9%。",
    "url": "https://www.baidu.com/s?wd=%E6%B1%9F%E8%8B%8F%E5%86%9C%E6%B0%91%E6%AF%94%E5%9B%9B%E5%B7%9D%E5%86%9C%E6%B0%91%E4%B8%80%E5%B9%B4%E5%A4%9A%E8%B5%9A50%EF%BC%85&sa=fyb_news&rsv_dl=fyb_news"
  },
  {
    "title": "华尔街日报回怼马斯克",
    "description": "近日，《华尔街日报》报道马斯克和谢尔盖·布林的妻子有外遇。马斯克回应称，完全是胡说八道。华尔街日报回怼马斯克：对我们的消...   近日，《华尔街日报》报道马斯克和谢尔盖·布林的妻子有外遇。马斯克回应称，完全是胡说八道。华尔街日报回怼马斯克：对我们的消息源充满信心。",
    "url": "https://www.baidu.com/s?wd=%E5%8D%8E%E5%B0%94%E8%A1%97%E6%97%A5%E6%8A%A5%E5%9B%9E%E6%80%BC%E9%A9%AC%E6%96%AF%E5%85%8B&sa=fyb_news&rsv_dl=fyb_news"
  },
  {
    "title": "菲律宾7.0级强震：地面开裂民众避难",
    "description": "经中国地震台网正式测定，7月27日8时43分在菲律宾发生7.0级地震，震源深度10千米。菲律宾部分地区出现地面开裂，民众...   经中国地震台网正式测定，7月27日8时43分在菲律宾发生7.0级地震，震源深度10千米。菲律宾部分地区出现地面开裂，民众逃往空旷地带躲避。",
    "url": "https://www.baidu.com/s?wd=%E8%8F%B2%E5%BE%8B%E5%AE%BE7.0%E7%BA%A7%E5%BC%BA%E9%9C%87%EF%BC%9A%E5%9C%B0%E9%9D%A2%E5%BC%80%E8%A3%82%E6%B0%91%E4%BC%97%E9%81%BF%E9%9A%BE&sa=fyb_news&rsv_dl=fyb_news"
  },
  {
    "title": "江苏多地罚没收入大涨",
    "description": "近日，《南方周末》统计了2021年全国300余个地级市的罚没收入，江苏多地罚没收入大涨。财政局回应称，系破获经济大案所得...   近日，《南方周末》统计了2021年全国300余个地级市的罚没收入，江苏多地罚没收入大涨。财政局回应称，系破获经济大案所得。",
    "url": "https://www.baidu.com/s?wd=%E6%B1%9F%E8%8B%8F%E5%A4%9A%E5%9C%B0%E7%BD%9A%E6%B2%A1%E6%94%B6%E5%85%A5%E5%A4%A7%E6%B6%A8&sa=fyb_news&rsv_dl=fyb_news"
  },
  {
    "title": "女大学生送外卖被骂哭 美团回应",
    "description": "",
    "url": "https://www.baidu.com/s?wd=%E5%A5%B3%E5%A4%A7%E5%AD%A6%E7%94%9F%E9%80%81%E5%A4%96%E5%8D%96%E8%A2%AB%E9%AA%82%E5%93%AD+%E7%BE%8E%E5%9B%A2%E5%9B%9E%E5%BA%94&sa=fyb_news&rsv_dl=fyb_news"
  },
  {
    "title": "来百度搜有惊喜 品牌小样火热领",
    "description": "",
    "url": "https://www.baidu.com/s?wd=%E6%9C%89%E6%83%8A%E5%96%9C&sa=fyb_news&rsv_dl=fyb_news"
  },
  {
    "title": "iPhone14或全系6G内存",
    "description": "据报道，iPhone14系列或全系提供6GBRAM，不过仅14Pro/ProMax是LPDDR5，而14/14Plus仍...   据报道，iPhone14系列或全系提供6GBRAM，不过仅14Pro/ProMax是LPDDR5，而14/14Plus仍旧是LPDDR4X。",
    "url": "https://www.baidu.com/s?wd=iPhone14%E6%88%96%E5%85%A8%E7%B3%BB6G%E5%86%85%E5%AD%98&sa=fyb_news&rsv_dl=fyb_news"
  },
  {
    "title": "俄方称2024年后退出国际空间站项目",
    "description": "当地时间26日，俄罗斯国家航天公司新任总裁鲍里索夫表示，俄罗斯将在2024年后退出国际空间站项目，届时将开始组建俄罗斯轨...   当地时间26日，俄罗斯国家航天公司新任总裁鲍里索夫表示，俄罗斯将在2024年后退出国际空间站项目，届时将开始组建俄罗斯轨道服务站。",
    "url": "https://www.baidu.com/s?wd=%E4%BF%84%E6%96%B9%E7%A7%B02024%E5%B9%B4%E5%90%8E%E9%80%80%E5%87%BA%E5%9B%BD%E9%99%85%E7%A9%BA%E9%97%B4%E7%AB%99%E9%A1%B9%E7%9B%AE&sa=fyb_news&rsv_dl=fyb_news"
  },
  {
    "title": "祭奠网站为战犯设纪念堂 已关停",
    "description": "26日，孝爱之家网发布公告致歉：由于疏于管理，导致孝爱之家网站存在祭奠侵华日军战犯网页，真诚向同胞们致歉，并按照主管部门...   26日，孝爱之家网发布公告致歉：由于疏于管理，导致孝爱之家网站存在祭奠侵华日军战犯网页，真诚向同胞们致歉，并按照主管部门要求关停整顿。",
    "url": "https://www.baidu.com/s?wd=%E7%A5%AD%E5%A5%A0%E7%BD%91%E7%AB%99%E4%B8%BA%E6%88%98%E7%8A%AF%E8%AE%BE%E7%BA%AA%E5%BF%B5%E5%A0%82+%E5%B7%B2%E5%85%B3%E5%81%9C&sa=fyb_news&rsv_dl=fyb_news"
  },
  {
    "title": "四川沐川通报持枪伤人案",
    "description": "四川省乐山市沐川县公安局通报，26日该县发生一起持枪击伤2人、持械杀害3人后逃逸的重大刑事案件。涉案枪弹已全部查获，公安...   四川省乐山市沐川县公安局通报，26日该县发生一起持枪击伤2人、持械杀害3人后逃逸的重大刑事案件。涉案枪弹已全部查获，公安机关正全力缉捕。",
    "url": "https://www.baidu.com/s?wd=%E5%9B%9B%E5%B7%9D%E6%B2%90%E5%B7%9D%E9%80%9A%E6%8A%A5%E6%8C%81%E6%9E%AA%E4%BC%A4%E4%BA%BA%E6%A1%88&sa=fyb_news&rsv_dl=fyb_news"
  },
  {
    "title": "二舅和姥姥已不在小山村",
    "description": "",
    "url": "https://www.baidu.com/s?wd=%E4%BA%8C%E8%88%85%E5%92%8C%E5%A7%A5%E5%A7%A5%E5%B7%B2%E4%B8%8D%E5%9C%A8%E5%B0%8F%E5%B1%B1%E6%9D%91&sa=fyb_news&rsv_dl=fyb_news"
  },
  {
    "title": "车主因眼睛小被辅助驾驶误判",
    "description": "近日，有网友爆料称，因眼睛小被小鹏辅助驾驶误判睡觉，从而被扣除了智驾分。对此，小鹏汽车回应称，自动驾驶同学已经连夜收到了...   近日，有网友爆料称，因眼睛小被小鹏辅助驾驶误判睡觉，从而被扣除了智驾分。对此，小鹏汽车回应称，自动驾驶同学已经连夜收到了优化需求。",
    "url": "https://www.baidu.com/s?wd=%E8%BD%A6%E4%B8%BB%E5%9B%A0%E7%9C%BC%E7%9D%9B%E5%B0%8F%E8%A2%AB%E8%BE%85%E5%8A%A9%E9%A9%BE%E9%A9%B6%E8%AF%AF%E5%88%A4&sa=fyb_news&rsv_dl=fyb_news"
  },
  {
    "title": "刘诗诗也跳刘畊宏",
    "description": "刘诗诗登上《嘉人》杂志8月封面，在采访中谈到了自己私下的生活，会和朋友一起开视频，一边聊天一边运动，晚上读一读书，或跟着...   刘诗诗登上《嘉人》杂志8月封面，在采访中谈到了自己私下的生活，会和朋友一起开视频，一边聊天一边运动，晚上读一读书，或跟着刘畊宏跳操。",
    "url": "https://www.baidu.com/s?wd=%E5%88%98%E8%AF%97%E8%AF%97%E4%B9%9F%E8%B7%B3%E5%88%98%E7%95%8A%E5%AE%8F&sa=fyb_news&rsv_dl=fyb_news"
  },
  {
    "title": "C罗与曼联谈崩了",
    "description": "据英媒《每日电讯报》报道，曼联高层和C罗会面，意见分歧仍存在，双方的首次会谈陷入僵局。   据英媒《每日电讯报》报道，曼联高层和C罗会面，意见分歧仍存在，双方的首次会谈陷入僵局。",
    "url": "https://www.baidu.com/s?wd=C%E7%BD%97%E4%B8%8E%E6%9B%BC%E8%81%94%E8%B0%88%E5%B4%A9%E4%BA%86&sa=fyb_news&rsv_dl=fyb_news"
  },
  {
    "title": "多地取消承办 夏日祭为何惹众怒？",
    "description": "近日，日本的传统节日——“夏日祭”登上各大社交平台的热榜。该活动引发网友强烈不满被广泛抵制，目前已有多地取消“夏日祭”活...   近日，日本的传统节日——“夏日祭”登上各大社交平台的热榜。该活动引发网友强烈不满被广泛抵制，目前已有多地取消“夏日祭”活动。",
    "url": "https://www.baidu.com/s?wd=%E5%A4%9A%E5%9C%B0%E5%8F%96%E6%B6%88%E6%89%BF%E5%8A%9E+%E5%A4%8F%E6%97%A5%E7%A5%AD%E4%B8%BA%E4%BD%95%E6%83%B9%E4%BC%97%E6%80%92%EF%BC%9F&sa=fyb_news&rsv_dl=fyb_news"
  },
  {
    "title": "炫富秀权者周劼“家族圈”浮现",
    "description": "近日，周劼“炫富”“秀后台”的朋友圈引关注。据悉，周劼父辈四人加其母五人，上班和任职的地方都和“交通”有关，其大伯和三伯...   近日，周劼“炫富”“秀后台”的朋友圈引关注。据悉，周劼父辈四人加其母五人，上班和任职的地方都和“交通”有关，其大伯和三伯还是这些单位的高管。",
    "url": "https://www.baidu.com/s?wd=%E7%82%AB%E5%AF%8C%E7%A7%80%E6%9D%83%E8%80%85%E5%91%A8%E5%8A%BC%E2%80%9C%E5%AE%B6%E6%97%8F%E5%9C%88%E2%80%9D%E6%B5%AE%E7%8E%B0&sa=fyb_news&rsv_dl=fyb_news"
  },
  {
    "title": "男子一胎得女发朋友圈称“晦气”",
    "description": "近日，重庆市云阳县一男子发文称“生女儿晦气，名字都懒得取”，遭到网友的一致谴责。27日，该男子回应：一时激动发牢骚，会尽...   近日，重庆市云阳县一男子发文称“生女儿晦气，名字都懒得取”，遭到网友的一致谴责。27日，该男子回应：一时激动发牢骚，会尽抚养义务。",
    "url": "https://www.baidu.com/s?wd=%E7%94%B7%E5%AD%90%E4%B8%80%E8%83%8E%E5%BE%97%E5%A5%B3%E5%8F%91%E6%9C%8B%E5%8F%8B%E5%9C%88%E7%A7%B0%E2%80%9C%E6%99%A6%E6%B0%94%E2%80%9D&sa=fyb_news&rsv_dl=fyb_news"
  },
  {
    "title": "被质疑升华苦难 二舅创作者回应",
    "description": "一则《回村三天，二舅治好了我的精神内耗》的视频刷屏了朋友圈，网友质疑二舅的苦难存在刻意升华，作者回应：苦难有什么可升华的...   一则《回村三天，二舅治好了我的精神内耗》的视频刷屏了朋友圈，网友质疑二舅的苦难存在刻意升华，作者回应：苦难有什么可升华的，最想表达的是庄敬自强。",
    "url": "https://www.baidu.com/s?wd=%E8%A2%AB%E8%B4%A8%E7%96%91%E5%8D%87%E5%8D%8E%E8%8B%A6%E9%9A%BE+%E4%BA%8C%E8%88%85%E5%88%9B%E4%BD%9C%E8%80%85%E5%9B%9E%E5%BA%94&sa=fyb_news&rsv_dl=fyb_news"
  },
  {
    "title": "女子在超市偷一盒榴莲躲厕所吃完",
    "description": "近日，广东揭阳一女子在超市厕所内三分钟偷吃完一盒榴莲。27日，超市回应称，清洁工在厕所发现榴莲盒子和果核，于是调取监控。   近日，广东揭阳一女子在超市厕所内三分钟偷吃完一盒榴莲。27日，超市回应称，清洁工在厕所发现榴莲盒子和果核，于是调取监控。",
    "url": "https://www.baidu.com/s?wd=%E5%A5%B3%E5%AD%90%E5%9C%A8%E8%B6%85%E5%B8%82%E5%81%B7%E4%B8%80%E7%9B%92%E6%A6%B4%E8%8E%B2%E8%BA%B2%E5%8E%95%E6%89%80%E5%90%83%E5%AE%8C&sa=fyb_news&rsv_dl=fyb_news"
  },
  {
    "title": "冬奥会后中国接待的首位外国元首",
    "description": "7月26日，习近平主席同印度尼西亚总统佐科举行会谈。佐科是北京冬奥会后中国接待的首位外国元首，中国也是佐科总统疫后首次东...   7月26日，习近平主席同印度尼西亚总统佐科举行会谈。佐科是北京冬奥会后中国接待的首位外国元首，中国也是佐科总统疫后首次东亚之行的首站。",
    "url": "https://www.baidu.com/s?wd=%E5%86%AC%E5%A5%A5%E4%BC%9A%E5%90%8E%E4%B8%AD%E5%9B%BD%E6%8E%A5%E5%BE%85%E7%9A%84%E9%A6%96%E4%BD%8D%E5%A4%96%E5%9B%BD%E5%85%83%E9%A6%96&sa=fyb_news&rsv_dl=fyb_news"
  },
  {
    "title": "跨省异地就医新规出台",
    "description": "7月26日，国家医保局、财政部发布《关于进一步做好基本医疗保险跨省异地就医直接结算工作通知》，将对每一名有外出就医需求的...   7月26日，国家医保局、财政部发布《关于进一步做好基本医疗保险跨省异地就医直接结算工作通知》，将对每一名有外出就医需求的参保人产生重要影响。",
    "url": "https://www.baidu.com/s?wd=%E8%B7%A8%E7%9C%81%E5%BC%82%E5%9C%B0%E5%B0%B1%E5%8C%BB%E6%96%B0%E8%A7%84%E5%87%BA%E5%8F%B0&sa=fyb_news&rsv_dl=fyb_news"
  },
  {
    "title": "上海一医院8000元招疫苗接种志愿者",
    "description": "近日，网上流传一则关于上海东方医院疫苗接种志愿者的招募贴，招募感染过新冠并接种过疫苗的60-80周岁的老年人，补贴额度高...   近日，网上流传一则关于上海东方医院疫苗接种志愿者的招募贴，招募感染过新冠并接种过疫苗的60-80周岁的老年人，补贴额度高达8000元，分4次发放。",
    "url": "https://www.baidu.com/s?wd=%E4%B8%8A%E6%B5%B7%E4%B8%80%E5%8C%BB%E9%99%A28000%E5%85%83%E6%8B%9B%E7%96%AB%E8%8B%97%E6%8E%A5%E7%A7%8D%E5%BF%97%E6%84%BF%E8%80%85&sa=fyb_news&rsv_dl=fyb_news"
  },
  {
    "title": "大爷不想购物遭导游辱骂 官方通报",
    "description": "7月25日，一老年游客在新疆吐鲁番被导游辱骂的视频引发关注。新疆发调查通报：目前，兵团文化体育广电和旅游局文化市场综合执...   7月25日，一老年游客在新疆吐鲁番被导游辱骂的视频引发关注。新疆发调查通报：目前，兵团文化体育广电和旅游局文化市场综合执法监督局已受理此案。",
    "url": "https://www.baidu.com/s?wd=%E5%A4%A7%E7%88%B7%E4%B8%8D%E6%83%B3%E8%B4%AD%E7%89%A9%E9%81%AD%E5%AF%BC%E6%B8%B8%E8%BE%B1%E9%AA%82+%E5%AE%98%E6%96%B9%E9%80%9A%E6%8A%A5&sa=fyb_news&rsv_dl=fyb_news"
  }
]